Workbook

Sheet 2013
A1: Cobre LME Prices 2013 US$/Ton | P1: US$ | Q1: Var (%) | R1: R$ | S1: Var (%)
A2: Janeiro 2013 | C2: Fevereiro 2013 | E2: Março 2013 | G2: Abril 2013 | I2: Maio 2013 | K2: Junho 2013 | O2: 41275 | P2: 8049.2455 | Q2: 0.0095984124 | R2: 16364.921 | S2: 0.0095984124
B3: Cash | D3: Cash | F3: Cash | H3: Cash | J3: Cash | L3: Cash | O3: 41306 | P3: 8070.475 | Q3: 0.0026374578 | R3: 15912.556 | S3: -0.027642381
C4: 1 | D4: 8160 | E4: 1 | F4: 7620.5 | G4: 1 | H4: Feriado | I4: 1 | J4: 6875 | K4: 3 | L4: 7330.5 | O4: 41334 | P4: 7662.4 | Q4: -0.050563938 | R4: 15212.929 | S4: -0.043966954
A5: 2 | B5: 8085 | C5: 4 | D5: 8226 | E5: 4 | F5: 7751 | G5: 2 | H5: 7434.5 | I5: 2 | J5: 6870.5 | K5: 4 | L5: 7337.5 | O5: 41365 | P5: 7203.3571 | Q5: -0.059908496 | R5: 14413.918 | S5: -0.052521859
A6: 3 | B6: 8140.5 | C6: 5 | D6: 8242.5 | E6: 5 | F6: 7720 | G6: 3 | H6: 7405.5 | I6: 3 | J6: 7122 | K6: 5 | L6: 7421.5 | O6: 41395 | P6: 7229.1429 | Q6: 0.0035796801 | R6: 14704.077 | S6: 0.020130469
A7: 4 | B7: 8026 | C7: 6 | D7: 8200 | E7: 6 | F7: 7699.5 | G7: 4 | H7: 7336.5 | I7: 6 | J7: Feriado | K7: 6 | L7: 7311 | O7: 41426 | P7: 7004.05 | Q7: -0.031136867 | R7: 15198.789 | S7: 0.033644542
A8: 7 | B8: 7995.5 | C8: 7 | D8: 8212 | E8: 7 | F8: 7671 | G8: 5 | H8: 7376 | I8: 7 | J8: 7240.5 | K8: 7 | L8: 7282 | O8: 41456 | P8: 6896.9773 | Q8: -0.015287259 | R8: 15536.683 | S8: 0.022231658
A9: 8 | B9: 8050.5 | C9: 8 | D9: 8215 | E9: 8 | F9: 7730 | G9: 8 | H9: 7457.5 | I9: 8 | J9: 7326 | K9: 10 | L9: 7120 | O9: 41487 | P9: 7182.2619 | Q9: 0.041363719 | R9: 16802.902 | S9: 0.081498669
A10: 9 | B10: 8059 | C10: 11 | D10: 8216 | E10: 11 | F10: 7667 | G10: 9 | H10: 7485.5 | I10: 9 | J10: 7311 | K10: 11 | L10: 7036 | O10: 41518 | P10: 7161.4286 | Q10: -0.0029006647 | R10: 16264.32 | S10: -0.032052874
A11: 10 | B11: 8117 | C11: 12 | D11: 8184.5 | E11: 12 | F11: 7815 | G11: 10 | H11: 7547 | I11: 10 | J11: 7390.5 | K11: 12 | L11: 7086 | O11: 41548 | P11: 7188.7826 | Q11: 0.0038196342 | R11: 15720.43 | S11: -0.033440722
A12: 11 | B12: 8071 | C12: 13 | D12: 8221 | E12: 13 | F12: 7777.5 | G12: 11 | H12: 7510 | I12: 13 | J12: 7350.5 | K12: 13 | L12: 7057.5 | O12: 41579 | P12: 7066.4048 | Q12: -0.017023445 | R12: 16235.772 | S12: 0.032781659
A13: 14 | B13: 8030 | C13: 14 | D13: 8197 | E13: 14 | F13: 7762 | G13: 12 | H13: 7510 | I13: 14 | J13: 7195 | K13: 14 | L13: 7045 | O13: 41609 | P13: 7202.95 | Q13: 0.019323156 | R13: 16911.086 | S13: 0.041594231
A14: 15 | B14: 7945 | C14: 15 | D14: 8198.5 | E14: 15 | F14: 7782 | G14: 15 | H14: 7120.5 | I14: 15 | J14: 7095.5 | K14: 17 | L14: 7020.5
A15: 16 | B15: 7910.5 | C15: 18 | D15: 8075.5 | E15: 18 | F15: 7555.5 | G15: 16 | H15: 7219 | I15: 16 | J15: 7095.5 | K15: 18 | L15: 6970.5
A16: 17 | B16: 7930 | C16: 19 | D16: 8070 | E16: 19 | F16: 7539 | G16: 17 | H16: 7067 | I16: 17 | J16: 7329.5 | K16: 19 | L16: 6972.5
A17: 18 | B17: 8053 | C17: 20 | D17: 8009.5 | E17: 20 | F17: 7574.5 | G17: 18 | H17: 6962.5 | I17: 20 | J17: 7276 | K17: 20 | L17: 6808
A18: 21 | B18: 8020.5 | C18: 21 | D18: 7847.5 | E18: 21 | F18: 7580 | G18: 19 | H18: 6975 | I18: 21 | J18: 7384 | K18: 21 | L18: 6777
A19: 22 | B19: 8068 | C19: 22 | D19: 7825 | E19: 22 | F19: 7618 | G19: 22 | H19: 6875.5 | I19: 22 | J19: 7480 | K19: 24 | L19: 6637.5
A20: 23 | B20: 8115.2 | C20: 25 | D20: 7865.5 | E20: 25 | F20: 7602 | G20: 23 | H20: 6811 | I20: 23 | J20: 7285.5 | K20: 25 | L20: 6726.5
A21: 24 | B21: 8036 | C21: 26 | D21: 7785 | E21: 26 | F21: 7631 | G21: 24 | H21: 6935.5 | I21: 24 | J21: 7240 | K21: 26 | L21: 6685.5
A22: 25 | B22: 8060 | C22: 27 | D22: 7831 | E22: 27 | F22: 7570 | G22: 25 | H22: 7035 | I22: 27 | J22: Feriado | K22: 27 | L22: 6705.5
A23: 28 | B23: 8015 | C23: 28 | D23: 7828 | E23: 28 | F23: 7582.5 | G23: 26 | H23: 7054.5 | I23: 28 | J23: 7257 | K23: 28 | L23: 6750.5
A24: 29 | B24: 8010.5 | G24: 29 | H24: 7079 | I24: 29 | J24: 7201.5
A25: 30 | B25: 8175.2 | G25: 30 | H25: 7073.5 | I25: 30 | J25: 7245.5
A26: 31 | B26: 8170 | I26: 31 | J26: 7241
A27: =B28/B69-1 -> #DIV/0! | C27: =D28/B28-1 -> 0.0026374578 | E27: =F28/D28-1 -> -0.050563938 | G27: =H28/F28-1 -> -0.059908496 | I27: =J28/H28-1 -> 0.0035796801 | K27: =L28/J28-1 -> -0.031136867
A28: MM | B28: =AVERAGE(B4:B26) -> 8049.2455 | C28: MM | D28: =AVERAGE(D4:D24) -> 8070.475 | E28: MM | F28: =AVERAGE(F4:F25) -> 7662.4 | G28: MM | H28: =AVERAGE(H4:H25) -> 7203.3571 | I28: MM | J28: =AVERAGE(J4:J26) -> 7229.1429 | K28: MM | L28: =AVERAGE(L4:L24) -> 7004.05
C29: =D23/B26-1 -> -0.041860465 | E29: =F23/D23-1 -> -0.031361778 | G29: =H25/F23-1 -> -0.067128256 | I29: =J26/H25-1 -> 0.023679932 | K29: =L23/J26-1 -> -0.067739263
A30: MM R$ | B30: =B28*A31 -> 16364.921 | C30: MM R$ | D30: =D28*C31 -> 15912.556 | E30: MM R$ | F30: =F28*E31 -> 15212.929 | G30: MM R$ | H30: =H28*G31 -> 14413.918 | I30: MM R$ | J30: =J28*I31 -> 14704.077 | K30: MM R$ | L30: =L28*K31 -> 15198.789
A31: 2.0331 | C31: 1.9717 | D31: =D30/B30-1 -> -0.027642381 | E31: 1.9854 | F31: =F30/D30-1 -> -0.043966954 | G31: 2.001 | H31: =H30/F30-1 -> -0.052521859 | I31: 2.034 | J31: =J30/H30-1 -> 0.020130469 | K31: 2.17 | L31: =L30/J30-1 -> 0.033644542
A32: Cobre LME Prices 2013 US$/Ton
A33: Julho 2013 | C33: Agosto 2013 | E33: Setembro 2013 | G33: Outubro 2013 | I33: Novembro 2013 | K33: Dezembro 2013
B34: Cash | D34: Cash | F34: Cash | H34: Cash | J34: Cash | L34: Cash
A35: 1 | B35: 6917 | C35: 1 | D35: 6999 | E35: 2 | F35: 7175.5 | G35: 1 | H35: 7219 | I35: 1 | J35: 7255.5 | K35: 2 | L35: 7008.5
A36: 2 | B36: 6980 | C36: 2 | D36: 7019 | E36: 3 | F36: 7183.5 | G36: 2 | H36: 7156 | I36: 4 | J36: 7180 | K36: 3 | L36: 6945
A37: 3 | B37: 6922 | C37: 5 | D37: 6950.5 | E37: 4 | F37: 7125.5 | G37: 3 | H37: 7216.5 | I37: 5 | J37: 7138.5 | K37: 4 | L37: 6975
A38: 4 | B38: 6920.5 | C38: 6 | D38: 7026.5 | E38: 5 | F38: 7103 | G38: 4 | H38: 7148 | I38: 6 | J38: 7200 | K38: 5 | L38: 7081
A39: 5 | B39: 6821 | C39: 7 | D39: 6892 | E39: 6 | F39: 7170.5 | G39: 7 | H39: 7171 | I39: 7 | J39: 7119 | K39: 6 | L39: 7113
A40: 8 | B40: 6765 | C40: 8 | D40: 7121.5 | E40: 9 | F40: 7191.5 | G40: 8 | H40: 7231.5 | I40: 8 | J40: 7125.5 | K40: 9 | L40: 7141
A41: 9 | B41: 6719 | C41: 9 | D41: 7186 | E41: 10 | F41: 7172 | G41: 9 | H41: 7141 | I41: 11 | J41: 7135 | K41: 10 | L41: 7165.5
A42: 10 | B42: 6780 | C42: 12 | D42: 7246 | E42: 11 | F42: 7163 | G42: 10 | H42: 7112.5 | I42: 12 | J42: 7124 | K42: 11 | L42: 7169.5
A43: 11 | B43: 6995.5 | C43: 13 | D43: 7281 | E43: 12 | F43: 7043.5 | G43: 11 | H43: 7125 | I43: 13 | J43: 7021.5 | K43: 12 | L43: 7230
A44: 12 | B44: 6923 | C44: 14 | D44: 7272.5 | E44: 13 | F44: 7028.5 | G44: 14 | H44: 7205.5 | I44: 14 | J44: 6939 | K44: 13 | L44: 7218.5
A45: 15 | B45: 6891.5 | C45: 15 | D45: 7228 | E45: 16 | F45: 7050 | G45: 15 | H45: 7186 | I45: 15 | J45: 6967.5 | K45: 16 | L45: 7325.5
A46: 16 | B46: 6936.5 | C46: 16 | D46: 7335.5 | E46: 17 | F46: 7056.5 | G46: 16 | H46: 7158.5 | I46: 18 | J46: 6999.5 | K46: 17 | L46: 7286
... A51: 23 | B51: 6961 | C51: 23 | D51: 7300.5 | E51: 24 | F51: 7140.5 | G51: 23 | H51: 7200.5 | I51: 25 | J51: 7067.5 | K51: 24 | L51: 7280
A52: 24 | B52: 7076.5 | C52: 26 | D52: Feriado | E52: 25 | F52: 7155 | G52: 24 | H52: 7160 | I52: 26 | J52: 7071 | K52: 27 | L52: 7375
A53: 25 | B53: 6927.5 | C53: 27 | D53: 7300.5 | E53: 26 | F53: 7220.5 | G53: 25 | H53: 7126 | I53: 27 | J53: 7051.5 | K53: 30 | L53: 7387
A54: 26 | B54: 6905.5 | C54: 28 | D54: 7236 | E54: 27 | F54: 7252.5 | G54: 28 | H54: 7161 | I54: 28 | J54: 6988 | K54: 31 | L54: 7394.5
A55: 29 | B55: 6860.5 | C55: 29 | D55: 7210.5 | E55: 30 | F55: 7290.5 | G55: 29 | H55: 7215.5 | I55: 29 | J55: 7027
A56: 30 | B56: 6752 | C56: 30 | D56: 7095 | G56: 30 | H56: 7275.5
A57: 31 | B57: 6805 | G57: 31 | H57: 7234
A58: Média | B58: =B59/L28-1 -> -0.015287259 | C58: Média | D58: =D59/B59-1 -> 0.041363719 | E58: Média | F58: =F59/D59-1 -> -0.0029006647 | G58: Média | H58: =H59/F59-1 -> 0.0038196342 | I58: Média | J58: =J59/H59-1 -> -0.017023445 | K58: Média | L58: =L59/J59-1 -> 0.019323156
A59: MM | B59: =AVERAGE(B35:B56) -> 6896.9773 | C59: MM | D59: =AVERAGE(D35:D57) -> 7182.2619 | E59: MM | F59: =AVERAGE(F35:F56) -> 7161.4286 | G59: MM | H59: =AVERAGE(H35:H57) -> 7188.7826 | I59: MM | J59: =AVERAGE(J35:J56) -> 7066.4048 | K59: MM | L59: =AVERAGE(L35:L54) -> 7202.95
A60: =B57/L23-1 -> 0.008073476 | C60: =D56/B57-1 -> 0.042615724 | E60: =F55/D56-1 -> 0.027554616 | G60: =H57/F55-1 -> -0.0077498114 | I60: =J55/H57-1 -> -0.028614874 | K60: =L54/J55-1 -> 0.052298278
A61: MM R$ | B61: =B59*A62 -> 15536.683 | C61: MM R$ | D61: =C62*D59 -> 16802.902 | E61: MM R$ | F61: =E62*F59 -> 16264.32 | G61: MM R$ | H61: =H59*G62 -> 15720.43 | I61: MM R$ | J61: =J59*I62 -> 16235.772 | K61: MM R$ | L61: =L59*K62 -> 16911.086
A62: 2.25268 | B62: =B61/L30-1 -> 0.022231658 | C62: 2.3395 | D62: =D61/B61-1 -> 0.081498669 | E62: 2.2711 | F62: =F61/D61-1 -> -0.032052874 | G62: 2.1868 | H62: =H61/F61-1 -> -0.033440722 | I62: 2.2976 | J62: =J61/H61-1 -> 0.032781659 | K62: 2.3478 | L62: =L61/J61-1 -> 0.041594231

Sheet 2014
A1: Cobre LME Prices 2014 US$/Ton | O1: MÉDIAS
A2: Janeiro 2014 | C2: Fevereiro 2014 | E2: Março 2014 | G2: Abril 2014 | I2: Maio 2014 | K2: Junho 2014 | P2: US$ | Q2: Var (%) | R2: R$ | S2: Var (%)
B3: Cash | D3: Cash | F3: Cash | H3: Cash | J3: Cash | L3: Cash | O3: 41275 | P3: 8049.2455 | Q3: =P3/7962.58-1 -> 0.010884092 | R3: 16364.921 | S3: =R3/16546.24-1 -> -0.010958324
A4: 1 | B4: Feriado | C4: 3 | D4: 7095.5 | E4: 3 | F4: 7032.5 | G4: 1 | H4: 6632 | I4: 1 | J4: 6670.5 | K4: 2 | L4: 7003 | O4: 41306 | P4: 8070.475 | Q4: =P4/P3-1 -> 0.0026374578 | R4: 15912.556 | S4: =R4/R3-1 -> -0.027642381
A5: 2 | B5: 7439.5 | C5: 4 | D5: 7107 | E5: 4 | F5: 7035 | G5: 2 | H5: 6713 | I5: 2 | J5: 6699 | K5: 3 | L5: 6930 | O5: 41334 | P5: 7662.4 | Q5: =P5/P4-1 -> -0.050563938 | R5: 15212.929 | S5: =R5/R4-1 -> -0.043966954
A6: 3 | B6: 7335.5 | C6: 5 | D6: 7096 | E6: 5 | F6: 7102.5 | G6: 3 | H6: 6606 | I6: 6 | J6: 6740 | K6: 4 | L6: 6835 | O6: 41365 | P6: 7203.3571 | Q6: =P6/P5-1 -> -0.059908496 | R6: 14413.918 | S6: =R6/R5-1 -> -0.052521859
A7: 6 | B7: 7313.5 | C7: 6 | D7: 7109 | E7: 6 | F7: 7054.5 | G7: 4 | H7: 6677 | I7: 7 | J7: 6688 | K7: 5 | L7: 6800 | O7: 41395 | P7: 7229.1429 | Q7: =P7/P6-1 -> 0.0035796801 | R7: 14704.077 | S7: =R7/R6-1 -> 0.020130469
A8: 7 | B8: 7354 | C8: 7 | D8: 7200 | E8: 7 | F8: 6930.5 | G8: 7 | H8: 6610.5 | I8: 8 | J8: 6690.5 | K8: 6 | L8: 6660.5 | O8: 41426 | P8: 7004.05 | Q8: =P8/P7-1 -> -0.031136867 | R8: 15198.789 | S8: =R8/R7-1 -> 0.033644542
A9: 8 | B9: 7368 | C9: 10 | D9: 7190.5 | E9: 10 | F9: 6716 | G9: 8 | H9: 6652 | I9: 9 | J9: 6770 | K9: 9 | L9: 6667.5 | O9: 41456 | P9: 6896.9773 | Q9: =P9/P8-1 -> -0.015287259 | R9: 15536.683 | S9: =R9/R8-1 -> 0.022231658
A10: 9 | B10: 7282 | C10: 11 | D10: 7120 | E10: 11 | F10: 6720.5 | G10: 9 | H10: 6630.5 | I10: 12 | J10: 6930 | K10: 10 | L10: 6695.5 | O10: 41487 | P10: 7182.2619 | Q10: =P10/P9-1 -> 0.041363719 | R10: 16802.902 | S10: =R10/R9-1 -> 0.081498669
A11: 10 | B11: 7283.5 | C11: 12 | D11: 7174.5 | E11: 12 | F11: 6498 | G11: 10 | H11: 6637.5 | I11: 13 | J11: 6884.5 | K11: 11 | L11: 6689.5 | O11: 41518 | P11: 7161.4286 | Q11: =P11/P10-1 -> -0.0029006647 | R11: 16264.32 | S11: =R11/R10-1 -> -0.032052874
A12: 13 | B12: 7305.5 | C12: 13 | D12: 7157 | E12: 13 | F12: 6495 | G12: 11 | H12: 6686 | I12: 14 | J12: 6976.5 | K12: 12 | L12: 6725 | O12: 41548 | P12: 7188.7826 | Q12: =P12/P11-1 -> 0.0038196342 | R12: 15720.43 | S12: =R12/R11-1 -> -0.033440722
A13: 14 | B13: 7343 | C13: 14 | D13: 7175.5 | E13: 14 | F13: 6490 | G13: 14 | H13: 6645 | I13: 15 | J13: 6949 | K13: 13 | L13: 6671.5 | O13: 41579 | P13: 7066.4048 | Q13: =P13/P12-1 -> -0.017023445 | R13: 16235.772 | S13: =R13/R12-1 -> 0.032781659
A14: 15 | B14: 7309 | C14: 17 | D14: 7210 | E14: 17 | F14: 6550 | G14: 15 | H14: 6630 | I14: 16 | J14: 6950 | K14: 16 | L14: 6735 | O14: 41609 | P14: 7202.95 | Q14: =P14/P13-1 -> 0.019323156 | R14: 16911.086 | S14: =R14/R13-1 -> 0.041594231
A15: 16 | B15: 7345.5 | C15: 18 | D15: 7205 | E15: 18 | F15: 6471.5 | G15: 16 | H15: 6600 | I15: 19 | J15: 7009 | K15: 17 | L15: 6711 | O15: 41640 | P15: =B28 -> 7294.8864 | Q15: =P15/P14-1 -> 0.01276371 | R15: =B30 -> 17368.395 | S15: =R15/R14-1 -> 0.027041961
A16: 17 | B16: 7379.5 | C16: 19 | D16: 7220 | E16: 19 | F16: 6446 | G16: 17 | H16: 6631 | I16: 20 | J16: 6922.5 | K16: 18 | L16: 6739 | O16: 41671 | P16: =D28 -> 7152.15 | Q16: =P16/P15-1 -> -0.019566633 | R16: =D30 -> 17062.884 | S16: =R16/R15-1 -> -0.017590036
A17: 20 | B17: 7340 | C17: 20 | D17: 7185 | E17: 20 | F17: 6434.5 | G17: 18 | H17: Feriado | I17: 21 | J17: 6841 | K17: 19 | L17: 6730.5 | O17: 41699 | P17: =F28 -> 6667.8095 | Q17: =P17/P16-1 -> -0.067719564 | R17: =F30 -> 15507.991 | S17: =R17/R16-1 -> -0.0911272
A18: 21 | B18: 7332 | C18: 21 | D18: 7211.5 | E18: 21 | F18: 6539.5 | G18: 21 | H18: Feriado | I18: 22 | J18: 6945.5 | K18: 20 | L18: 6777.5 | O18: 41730 | P18: =H28 -> 6670.825 | Q18: =P18/P17-1 -> 0.0004522439 | R18: =H30 -> 14896.619 | S18: =R18/R17-1 -> -0.039423035
A19: 22 | B19: 7327 | C19: 24 | D19: 7130 | E19: 24 | F19: 6510 | G19: 22 | H19: 6628.5 | I19: 23 | J19: 6991 | K19: 23 | L19: 6901 | O19: 41760 | P19: =J28 -> 6883.875 | Q19: =P19/P18-1 -> 0.031937579 | R19: =J30 -> 15289.775 | S19: =R19/R18-1 -> 0.02639226
A20: 23 | B20: 7285 | C20: 25 | D20: 7115 | E20: 25 | F20: 6559.5 | G20: 23 | H20: 6645 | I20: 26 | J20: Feriado | K20: 24 | L20: 6898.5 | O20: 41791 | P20: =L28 -> 6806.0952 | Q20: =P20/P19-1 -> -0.011298834 | R20: =L30 -> 15206.178 | S20: =R20/R19-1 -> -0.0054674959
A21: 24 | B21: 7240 | C21: 26 | D21: 7149 | E21: 26 | F21: 6555 | G21: 24 | H21: 6731 | I21: 27 | J21: 7020 | K21: 25 | L21: 6890.5 | O21: 41821 | P21: =B82 -> 7104.8478 | Q21: =P21/P20-1 -> 0.043894859 | R21: =B84 -> 15807.576 | S21: =R21/R20-1 -> 0.03954958
A22: 27 | B22: 7235 | C22: 27 | D22: 7095 | E22: 27 | F22: 6581 | G22: 25 | H22: 6785.5 | I22: 28 | J22: 7035 | K22: 26 | L22: 6936.5 | O22: 41852 | P22: =D82 -> 7000.55 | Q22: =P22/P21-1 -> -0.014679811 | R22: =D84 -> 15880.048 | S22: =R22/R21-1 -> 0.0045846177
A23: 28 | B23: 7215 | C23: 28 | D23: 7097.5 | E23: 28 | F23: 6667 | G23: 28 | H23: 6782 | I23: 29 | J23: 6970 | K23: 27 | L23: 6976 | O23: 41883 | P23: =F82 -> 6872.2273 | Q23: =P23/P22-1 -> -0.018330378 | R23: =F84 -> 16046.651 | S23: =R23/R22-1 -> 0.010491345
A24: 29 | B24: 7209 | E24: 31 | F24: 6635.5 | G24: 29 | H24: 6770 | I24: 30 | J24: 6995.5 | K24: 30 | L24: 6955 | O24: 41913 | P24: =H82 -> 6739.1957 | Q24: =P24/P23-1 -> -0.019357861 | R24: =H84 -> 16515.747 | S24: =R24/R23-1 -> 0.029233272
A25: 30 | B25: 7155 | G25: 30 | H25: 6724 | O25: 41944 | P25: =J82 -> 6701.135 | Q25: =P25/P24-1 -> -0.005647655 | R25: =J84 -> 17154.906 | S25: =R25/R24-1 -> 0.038699965
A26: 31 | B26: 7091 | O26: 41974 | P26: =L82 -> 6422.9524 | Q26: =P26/P25-1 -> -0.041512762 | R26: =L84 -> 16968.798 | S26: =R26/R25-1 -> -0.010848658
A27: =B28/B88-1 -> 0.01276371 | C27: =D28/B28-1 -> -0.019566633 | E27: =F28/D28-1 -> -0.067719564 | G27: =H28/F28-1 -> 0.0004522439 | I27: =J28/H28-1 -> 0.031937579 | K27: =L28/J28-1 -> -0.011298834 | O27: Acumulado 2014 | Q27: =P26/P14-1 -> -0.10828863 | S27: =R26/R14-1 -> 0.0034126658
A28: MM | B28: =AVERAGE(B5:B26) -> 7294.8864 | C28: MM | D28: =AVERAGE(D4:D23) -> 7152.15 | E28: MM | F28: =AVERAGE(F4:F24) -> 6667.8095 | G28: MM | H28: =AVERAGE(H4:H25) -> 6670.825 | I28: MM | J28: =AVERAGE(J4:J24) -> 6883.875 | K28: MM | L28: =AVERAGE(L4:L24) -> 6806.0952
A29: =B26/B87-1 -> -0.041044019 | C29: =D19/B26-1 -> 0.0054999295 | E29: =F24/D23-1 -> -0.065093343 | G29: =H25/F24-1 -> 0.013337352 | I29: =J24/H25-1 -> 0.040377751 | K29: =L24/J24-1 -> -0.0057894361
A30: MM R$ | B30: =B28*A31 -> 17368.395 | C30: MM R$ | D30: =D28*C31 -> 17062.884 | E30: MM R$ | F30: =F28*E31 -> 15507.991 | G30: MM R$ | H30: =H28*G31 -> 14896.619 | I30: MM R$ | J30: =J28*I31 -> 15289.775 | K30: MM R$ | L30: =L28*K31 -> 15206.178
A31: 2.3809 | B31: =B30/B89-1 -> 0.027041961 | C31: 2.3857 | D31: =D30/B30-1 -> -0.017590036 | E31: 2.3258 | F31: =F30/D30-1 -> -0.0911272 | G31: 2.2331 | H31: =H30/F30-1 -> -0.039423035 | I31: 2.2211 | J31: =J30/H30-1 -> 0.02639226 | K31: 2.2342 | L31: =L30/J30-1 -> -0.0054674959
A32: Cobre LME Prices 2014 US$/Ton
A33: Julho 2014 | C33: Agosto 2014 | E33: Setembro 2014 | G33: Outubro 2014 | I33: Novembro 2014 | K33: Dezembro 2014
B34: Cash | D34: Cash | F34: Cash | H34: Cash | J34: Cash | L34: Cash
A51: Média | B51: #DIV/0! | C51: Média | D51: #DIV/0! | E51: Média | F51: #DIV/0! | G51: Média | H51: #DIV/0! | I51: Média | J51: #DIV/0! | K51: Média | L51: #DIV/0!
A52: MM | B52: #DIV/0! | C52: MM | D52: #DIV/0! | E52: MM | F52: #DIV/0! | G52: MM | H52: #DIV/0! | I52: MM | J52: #DIV/0! | K52: MM | L52: #DIV/0!
A53: #DIV/0! | C53: #DIV/0! | E53: #DIV/0! | G53: #DIV/0! | I53: #DIV/0! | K53: #DIV/0!
A54: MM R$ | B54: #DIV/0! | C54: MM R$ | D54: #DIV/0! | E54: MM R$ | F54: #DIV/0! | G54: MM R$ | H54: #DIV/0! | I54: MM R$ | J54: #DIV/0! | K54: MM R$ | L54: #DIV/0!
B55: #DIV/0! | D55: #DIV/0! | F55: #DIV/0! | H55: #DIV/0! | J55: #DIV/0! | L55: #DIV/0!
A56: Julho 2014 | C56: Agosto 2014 | E56: Setembro 2014 | G56: Outubro 2014 | I56: Novembro 2014 | K56: Dezembro 2014
B57: Cash | D57: Cash | F57: Cash | H57: Cash | J57: Cash | L57: Cash
A58: 1 | B58: 7015 | C58: 1 | D58: 7078 | E58: 1 | F58: 6966.5 | G58: 1 | H58: 6755 | I58: 3 | J58: 6801 | K58: 1 | L58: 6385
A59: 2 | B59: 7050 | C59: 4 | D59: 7104 | E59: 2 | F59: 6965.5 | G59: 2 | H59: 6693.5 | I59: 4 | J59: 6705.5 | K59: 2 | L59: 6455
A60: 3 | B60: 7121 | C60: 5 | D60: 7100.5 | E60: 3 | F60: 6927 | G60: 3 | H60: 6665 | I60: 5 | J60: 6646 | K60: 3 | L60: 6451
A61: 4 | B61: 7159 | C61: 6 | D61: 6995 | E61: 4 | F61: 6967 | G61: 6 | H61: 6712.5 | I61: 6 | J61: 6681 | K61: 4. | L61: 6491
A62: 7 | B62: 7120.5 | C62: 7 | D62: 6980.5 | E62: 5 | F62: 6973 | G62: 7 | H62: 6715 | I62: 7 | J62: 6720.5 | K62: 5 | L62: 6536
A63: 8 | B63: 7155 | C63: 8 | D63: 7020 | E63: 8 | F63: 7040.5 | G63: 8 | H63: 6755 | I63: 10 | J63: 6735.5 | K63: 8 | L63: 6465.5
A64: 9 | B64: 7173 | C64: 11 | D64: 7010.5 | E64: 9 | F64: 6937 | G64: 9 | H64: 6767 | I64: 11 | J64: 6688 | K64: 9 | L64: 6401
A65: 10 | B65: 7110 | C65: 12 | D65: 7025.5 | E65: 10 | F65: 6897.5 | G65: 10 | H65: 6697 | I65: 12 | J65: 6752.5 | K65: 10 | L65: 6476
A66: 11 | B66: 7151 | C66: 13 | D66: 6925.5 | E66: 11 | F66: 6829 | G66: 13 | H66: 6802 | I66: 13 | J66: 6755.7 | K66: 11 | L66: 6471.5
A67: 14 | B67: 7154.5 | C67: 14 | D67: 6886.5 | E67: 12 | F67: 6856 | G67: 14 | H67: 6780.5 | I67: 14 | J67: 6695 | K67: 12 | L67: 6526.5
A68: 15 | B68: 7102.5 | C68: 15 | D68: 6852.5 | E68: 15 | F68: 6850 | G68: 15 | H68: 6781 | I68: 17 | J68: 6752 | K68: 15 | L68: 6560
A69: 16 | B69: 7112 | C69: 18 | D69: 6910 | E69: 16 | F69: 6895.5 | G69: 17 | H69: 6630 | I69: 18 | J69: 6684 | K69: 16 | L69: 6390
A70: 17 | B70: 7030.5 | C70: 19 | D70: 6934.5 | E70: 17 | F70: 6958.5 | G70: 17 | H70: 6629 | I70: 19 | J70: 6715 | K70: 17 | L70: 6306
A71: 18 | B71: 7026.5 | C71: 20 | D71: 6922 | E71: 18 | F71: 6920 | G71: 20 | H71: 6615 | I71: 20 | J71: 6688 | K71: 18 | L71: 6350.5
A72: 21 | B72: 6989.5 | C72: 21 | D72: 7003 | E72: 19 | F72: 6868.5 | G72: 21 | H72: 6660 | I72: 21 | J72: 6790 | K72: 19 | L72: 6445.5
A73: 22 | B73: 7060.5 | C73: 22 | D73: 7088 | E73: 22 | F73: 6782 | G73: 22 | H73: 6730.5 | I73: 24 | J73: 6731 | K73: 22 | L73: 6426.5
A74: 23 | B74: 7065 | C74: 25 | D74: Feriado | E74: 23 | F74: 6797 | G74: 23 | H74: 6718.5 | I74: 25 | J74: 6696 | K74: 23 | L74: 6363
A75: 24 | B75: 7151 | C75: 26 | D75: 7096 | E75: 24 | F75: 6750 | G75: 24 | H75: 6759.5 | I75: 26 | J75: 6649 | K75: 24 | L75: 6361
A76: 25 | B76: 7183.5 | C76: 27 | D76: 7051 | E76: 25 | F76: 6766 | G76: 27 | H76: 6800.5 | I76: 27 | J76: 6621.5 | K76: 29 | L76: 6332
A77: 28 | B77: 7132 | C77: 28 | D77: 7033 | E77: 26 | F77: 6771 | G77: 28 | H77: 6859.5 | I77: 28 | J77: 6515.5 | K77: 30 | L77: 6330
A78: 29 | B78: 7124 | C78: 29 | D78: 6995 | E78: 29 | F78: 6735.5 | G78: 29 | H78: 6855 | K78: 31 | L78: 6359
A79: 30 | B79: 7090 | E79: 30 | F79: 6736 | G79: 30 | H79: 6785
A80: 31 | B80: 7135.5 | G80: 31 | H80: 6835.5
A81: =B82/L28-1 -> 0.043894859 | C81: =D82/B82-1 -> -0.014679811 | E81: =F82/D82-1 -> -0.018330378 | G81: =H82/F82-1 -> -0.019357861 | I81: =J82/H82-1 -> -0.005647655 | K81: =L82/J82-1 -> -0.041512762
A82: MM | B82: =AVERAGE(B58:B80) -> 7104.8478 | C82: MM | D82: =AVERAGE(D58:D78) -> 7000.55 | E82: MM | F82: =AVERAGE(F58:F79) -> 6872.2273 | G82: MM | H82: =AVERAGE(H58:H80) -> 6739.1957 | I82: MM | J82: =AVERAGE(J58:J77) -> 6701.135 | K82: MM | L82: =AVERAGE(L58:L78) -> 6422.9524
A83: =B80/L24-1 -> 0.025952552 | C83: =D78/B80-1 -> -0.019690281 | E83: =F79/D78-1 -> -0.037026447 | G83: =H80/F79-1 -> 0.014771378 | I83: =J77/H80-1 -> -0.046814425 | K83: =L78/J77-1 -> -0.024019645
A84: MM R$ | B84: =B82*A85 -> 15807.576 | C84: MM R$ | D84: =D82*C85 -> 15880.048 | E84: MM R$ | F84: =F82*E85 -> 16046.651 | G84: MM R$ | H84: =H82*G85 -> 16515.747 | I84: MM R$ | J84: =J82*I85 -> 17154.906 | K84: MM R$ | L84: =L82*K85 -> 16968.798
A85: 2.2249 | B85: =B84/L30-1 -> 0.03954958 | C85: 2.2684 | D85: =D84/B84-1 -> 0.0045846177 | E85: 2.335 | F85: =F84/D84-1 -> 0.010491345 | G85: 2.4507 | H85: =H84/F84-1 -> 0.029233272 | I85: 2.56 | J85: =J84/H84-1 -> 0.038699965 | K85: 2.6419 | L85: =L84/J84-1 -> -0.010848658
A87: 41639 | B87: 7394.5 | L87: =L82/B88-1 -> -0.10828863
A88: MM Dolar | B88: 7202.95 | L88: =L84/B89-1 -> 0.0034126658
A89: MM Reais | B89: 16911.086

Sheet 2015
A1: Cobre LME Prices 2015 US$/Ton | O1: MÉDIAS
A2: Janeiro 2015 | C2: Fevereiro 2015 | E2: Março 2015 | G2: Abril 2015 | I2: Maio 2015 | K2: Junho 2015 | P2: US$ | Q2: Var (%) | R2: R$ | S2: Var Mês (%) | T2: Acumulado/Ano
B3: Cash | D3: Cash | F3: Cash | H3: Cash | J3: Cash | L3: Cash | O3: 41275 | P3: 8049.2455 | Q3: =P3/7962.58-1 -> 0.010884092 | R3: 16364.921 | S3: =R3/16546.24-1 -> -0.010958324
A4: 2 | B4: 6309 | C4: 2 | D4: 5535.5 | E4: 2 | F4: 5896 | G4: 1 | H4: 6019.5 | I4: 1 | J4: 6362 | K4: 1 | L4: 5970.5 | O4: 41306 | P4: 8070.475 | Q4: =P4/P3-1 -> 0.0026374578 | R4: 15912.556 | S4: =R4/R3-1 -> -0.027642381
A5: 5 | B5: 6216 | C5: 3 | D5: 5695 | E5: 3 | F5: 5855 | G5: 2 | H5: 6001.5 | I5: 5 | J5: 6410 | K5: 2 | L5: 5998.5 | O5: 41334 | P5: 7662.4 | Q5: =P5/P4-1 -> -0.050563938 | R5: 15212.929 | S5: =R5/R4-1 -> -0.043966954
A6: 6 | B6: 6191 | C6: 4 | D6: 5708 | E6: 4 | F6: 5882 | G6: 3 | H6: feriado | I6: 6 | J6: 6400.5 | K6: 3 | L6: 5992 | O6: 41365 | P6: 7203.3571 | Q6: =P6/P5-1 -> -0.059908496 | R6: 14413.918 | S6: =R6/R5-1 -> -0.052521859
A7: 7 | B7: 6170 | C7: 5 | D7: 5595 | E7: 5 | F7: 5856 | G7: 6 | H7: feriado | I7: 7 | J7: 6437 | K7: 4 | L7: 5954 | O7: 41395 | P7: 7229.1429 | Q7: =P7/P6-1 -> 0.0035796801 | R7: 14704.077 | S7: =R7/R6-1 -> 0.020130469
A8: 8 | B8: 6230.5 | C8: 6 | D8: 5692 | E8: 6 | F8: 5826.5 | G8: 7 | H8: 6041 | I8: 8 | J8: 6396.5 | K8: 5 | L8: 5924.5 | O8: 41426 | P8: 7004.05 | Q8: =P8/P7-1 -> -0.031136867 | R8: 15198.789 | S8: =R8/R7-1 -> 0.033644542
A9: 9 | B9: 6151 | C9: 9 | D9: 5666 | E9: 9 | F9: 5800 | G9: 8 | H9: 6055 | I9: 11 | J9: 6363 | K9: 8 | L9: 5915 | O9: 41456 | P9: 6896.9773 | Q9: =P9/P8-1 -> -0.015287259 | R9: 15536.683 | S9: =R9/R8-1 -> 0.022231658
A10: 12 | B10: 6131 | C10: 10 | D10: 5591 | E10: 10 | F10: 5783.5 | G10: 9 | H10: 6050 | I10: 12 | J10: 6448 | K10: 9 | L10: 5989 | O10: 41487 | P10: 7182.2619 | Q10: =P10/P9-1 -> 0.041363719 | R10: 16802.902 | S10: =R10/R9-1 -> 0.081498669
A11: 13 | B11: 5915 | C11: 11 | D11: 5645.5 | E11: 11 | F11: 5786 | G11: 10 | H11: 6055 | I11: 13 | J11: 6416 | K11: 10 | L11: 6045.5 | O11: 41518 | P11: 7161.4286 | Q11: =P11/P10-1 -> -0.0029006647 | R11: 16264.32 | S11: =R11/R10-1 -> -0.032052874
A12: 14 | B12: 5627 | C12: 12 | D12: 5695 | E12: 12 | F12: 5865.5 | G12: 13 | H12: 6011.55 | I12: 14 | J12: 6399 | K12: 11 | L12: 5906 | O12: 41548 | P12: 7188.7826 | Q12: =P12/P11-1 -> 0.0038196342 | R12: 15720.43 | S12: =R12/R11-1 -> -0.033440722
A13: 15 | B13: 5719 | C13: 13 | D13: 5731 | E13: 13 | F13: 5860 | G13: 14 | H13: 5916.5 | I13: 15 | J13: 6356 | K13: 12 | L13: 5888.5 | O13: 41579 | P13: 7066.4048 | Q13: =P13/P12-1 -> -0.017023445 | R13: 16235.772 | S13: =R13/R12-1 -> 0.032781659
A14: 16 | B14: 5660 | C14: 16 | D14: 5712 | E14: 16 | F14: 5853 | G14: 15 | H14: 5920.5 | I14: 18 | J14: 6383 | K14: 15 | L14: 5760.5 | O14: 41609 | P14: 7202.95 | Q14: =P14/P13-1 -> 0.019323156 | R14: 16911.086 | S14: =R14/R13-1 -> 0.041594231
A15: 19 | B15: 5671 | C15: 17 | D15: 5665.5 | E15: 17 | F15: 5765 | G15: 16 | H15: 6054 | I15: 19 | J15: 6270 | K15: 16 | L15: 5752 | O15: 41640 | P15: 7294.8864 | Q15: 0.01276371 | R15: 17368.395 | S15: =R15/R14-1 -> 0.027041961 | T15: =R15/R14-1 -> 0.027041961
A16: 20 | B16: 5760.5 | C16: 18 | D16: 5690 | E16: 18 | F16: 5692.5 | G16: 17 | H16: 6081 | I16: 20 | J16: 6208 | K16: 17 | L16: 5749 | O16: 41671 | P16: 7152.15 | Q16: -0.019566633 | R16: 17062.884 | S16: =R16/R15-1 -> -0.017590036 | T16: =R16/R$14-1 -> 0.0089762565
A17: 21 | B17: 5630.5 | C17: 19 | D17: 5720 | E17: 19 | F17: 5835 | G17: 20 | H17: 6002 | I17: 21 | J17: 6240 | K17: 18 | L17: 5761 | O17: 41699 | P17: 6667.8095 | Q17: -0.067719564 | R17: 15507.991 | S17: =R17/R16-1 -> -0.0911272 | T17: =R17/R$14-1 -> -0.082968925
A18: 22 | B18: 5742 | C18: 20 | D18: 5707 | E18: 20 | F18: 5920 | G18: 21 | H18: 5975 | I18: 22 | J18: 6197.5 | K18: 19 | L18: 5663 | O18: 41730 | P18: 6670.825 | Q18: 0.0004522439 | R18: 14896.619 | S18: =R18/R17-1 -> -0.039423035 | T18: =R18/R$14-1 -> -0.11912107
A19: 23 | B19: 5581 | C19: 23 | D19: 5657 | E19: 23 | F19: 6093.5 | G19: 22 | H19: 5927 | I19: 26 | J19: 6134.5 | K19: 22 | L19: 5646 | O19: 41760 | P19: 6883.875 | Q19: 0.031937579 | R19: 15289.775 | S19: =R19/R18-1 -> 0.02639226 | T19: =R19/R$14-1 -> -0.095872687
A20: 26 | B20: 5490 | C20: 24 | D20: 5715 | E20: 24 | F20: 6128 | G20: 23 | H20: 5935 | I20: 27 | J20: 6085 | K20: 23 | L20: 5725 | O20: 41791 | P20: 6806.0952 | Q20: -0.011298834 | R20: 15206.178 | S20: =R20/R19-1 -> -0.0054674959 | T20: =R20/R$14-1 -> -0.100816
A21: 27 | B21: 5557 | C21: 25 | D21: 5805 | E21: 25 | F21: 6134.5 | G21: 24 | H21: 6025.5 | I21: 28 | J21: 6117 | K21: 24 | L21: 5765 | O21: 41821 | P21: 7104.8478 | Q21: 0.043894859 | R21: 15807.576 | S21: =R21/R20-1 -> 0.03954958 | T21: =R21/R$14-1 -> -0.06525365
A22: 28 | B22: 5485.5 | C22: 26 | D22: 5935.5 | E22: 26 | F22: 6230 | G22: 27 | H22: 6061 | I22: 29 | J22: 6088.5 | K22: 25 | L22: 5715.5 | O22: 41852 | P22: 7000.55 | Q22: -0.014679811 | R22: 15880.048 | S22: =R22/R21-1 -> 0.0045846177 | T22: =R22/R$14-1 -> -0.060968195
A23: 29 | B23: 5390.5 | C23: 27 | D23: 5880.5 | E23: 27 | F23: 6146 | G23: 28 | H23: 6090.5 | K23: 26 | L23: 5731 | O23: 41883 | P23: 6872.2273 | Q23: -0.018330378 | R23: 16046.651 | S23: =R23/R22-1 -> 0.010491345 | T23: =R23/R$14-1 -> -0.051116488
A24: 30 | B24: 5505 | E24: 30 | F24: 6110 | G24: 29 | H24: 6103 | K24: 29 | L24: 5767 | O24: 41913 | P24: 6739.1957 | Q24: -0.019357861 | R24: 16515.747 | S24: =R24/R23-1 -> 0.029233272 | T24: =R24/R$14-1 -> -0.023377518
E25: 31 | F25: 6050.5 | G25: 30 | H25: 6245 | K25: 30 | L25: 5721 | O25: 41944 | P25: 6701.135 | Q25: -0.005647655 | R25: 17154.906 | S25: =R25/R24-1 -> 0.038699965 | T25: =R25/R$14-1 -> 0.014417737
O26: 41974 | P26: ='2014'!L82 -> 6422.9524 | Q26: =P26/P25-1 -> -0.041512762 | R26: ='2014'!L84 -> 16968.798 | S26: =R26/R25-1 -> -0.010848658 | T26: =R26/R$14-1 -> 0.0034126658
A27: =B28/'2014'!L82-1 -> -0.098362458 | C27: =D28/B28-1 -> -0.015385479 | E27: =F28/D28-1 -> 0.038201841 | G27: =H28/F28-1 -> 0.018340285 | I27: =J28/H28-1 -> 0.04514038 | K27: =L28/J28-1 -> -0.074118534 | O27: 42005 | P27: =B28 -> 5791.175 | Q27: =P27/P26-1 -> -0.098362458 | R27: =B30 -> 15271.908 | S27: =R27/R26-1 -> -0.10000062 | T27: =R27/R26-1 -> -0.10000062
A28: MM | B28: =AVERAGE(B5:B26) -> 5791.175 | C28: MM | D28: =AVERAGE(D4:D23) -> 5702.075 | E28: MM | F28: =AVERAGE(F4:F24) -> 5919.9048 | G28: MM | H28: =AVERAGE(H4:H25) -> 6028.4775 | I28: MM | J28: =AVERAGE(J4:J23) -> 6300.6053 | K28: MM | L28: =AVERAGE(L4:L25) -> 5833.6136 | O28: 42036 | P28: =D28 -> 5702.075 | Q28: =P28/P27-1 -> -0.015385479 | R28: =D30 -> 16059.837 | S28: =R28/R27-1 -> 0.051593399 | T28: =R28/R26-1 -> -0.053566592
O29: 42064 | P29: =F28 -> 5919.9048 | Q29: =P29/P28-1 -> 0.038201841 | R29: =F30 -> 18601.525 | S29: =R29/R28-1 -> 0.15826359 | T29: =R29/R26-1 -> 0.096219358
A30: MM R$ | B30: =B28*A31 -> 15271.908 | C30: MM R$ | D30: =D28*C31 -> 16059.837 | E30: MM R$ | F30: =F28*E31 -> 18601.525 | G30: MM R$ | H30: =H28*G31 -> 18401.928 | I30: MM R$ | J30: =J28*I31 -> 19242.048 | K30: MM R$ | L30: =L28*K31 -> 18168.79 | O30: 42095 | P30: =H28 -> 6028.4775 | Q30: =P30/P29-1 -> 0.018340285 | R30: =H30 -> 18401.928 | S30: =R30/R29-1 -> -0.010730151 | T30: =R30/R26-1 -> 0.084456759
A31: 2.6371 | B31: =B30/'2014'!L84-1 -> -0.10000062 | C31: 2.81649 | D31: =D30/B30-1 -> 0.051593399 | E31: 3.1422 | F31: =F30/D30-1 -> 0.15826359 | G31: 3.0525 | H31: =H30/F30-1 -> -0.010730151 | I31: 3.054 | J31: =J30/H30-1 -> 0.045653962 | K31: 3.1145 | L31: =L30/J30-1 -> -0.055776744 | O31: 42125 | P31: =J28 -> 6300.6053 | Q31: =P31/P30-1 -> 0.04514038 | R31: =J30 -> 19242.048 | S31: =R31/R30-1 -> 0.045653962 | T31: =R31/R26-1 -> 0.13396651
A32: Cobre LME Prices 2015 US$/Ton | O32: 42156 | P32: =L28 -> 5833.6136 | Q32: =P32/P31-1 -> -0.074118534 | R32: =L30 -> 18168.79 | S32: =R32/R31-1 -> -0.055776744 | T32: =R32/R26-1 -> 0.070717548
A33: Julho 2014 | C33: Agosto 2014 | E33: Setembro 2014 | G33: Outubro 2014 | I33: Novembro 2014 | K33: Dezembro 2014 | O33: 42186 | T33: =R33/R27-1 -> -1
B34: Cash | D34: Cash | F34: Cash | H34: Cash | J34: Cash | L34: Cash | O34: 42217 | T34: =R34/R28-1 -> -1
O35: 42248 | T35: =R35/R29-1 -> -1
O36: 42278 | T36: =R36/R30-1 -> -1
O37: 42309 | T37: =R37/R31-1 -> -1
O38: 42339 | T38: =R38/R32-1 -> -1
O39: 42370 | T39: =R39/R33-1 -> #DIV/0!
O40: 42401 | T40: =R40/R34-1 -> #DIV/0!
O41: 42430 | T41: =R41/R35-1 -> #DIV/0!
O42: 42461 | T42: =R42/R36-1 -> #DIV/0!
O43: 42491 | T43: =R43/R37-1 -> #DIV/0!
O44: 42522 | T44: =R44/R38-1 -> #DIV/0!
O45: 42552 | T45: =R45/R39-1 -> #DIV/0!
O46: 42583 | T46: =R46/R40-1 -> #DIV/0!
... O50: 42705 | T50: =R50/R44-1 -> #DIV/0!
A51: Média | B51: #DIV/0! | C51: Média | D51: #DIV/0! | E51: Média | F51: #DIV/0! | G51: Média | H51: #DIV/0! | I51: Média | J51: #DIV/0! | K51: Média | L51: #DIV/0! | O51: 42736 | T51: =R51/R45-1 -> #DIV/0!
A52: MM | B52: #DIV/0! | C52: MM | D52: #DIV/0! | E52: MM | F52: #DIV/0! | G52: MM | H52: #DIV/0! | I52: MM | J52: #DIV/0! | K52: MM | L52: #DIV/0! | O52: 42767 | T52: =R52/R46-1 -> #DIV/0!
A53: #DIV/0! | C53: #DIV/0! | E53: #DIV/0! | G53: #DIV/0! | I53: #DIV/0! | K53: #DIV/0! | O53: 42795 | T53: =R53/R47-1 -> #DIV/0!
A54: MM R$ | B54: #DIV/0! | C54: MM R$ | D54: #DIV/0! | E54: MM R$ | F54: #DIV/0! | G54: MM R$ | H54: #DIV/0! | I54: MM R$ | J54: #DIV/0! | K54: MM R$ | L54: #DIV/0! | O54: 42826 | T54: =R54/R48-1 -> #DIV/0!
B55: #DIV/0! | D55: #DIV/0! | F55: #DIV/0! | H55: #DIV/0! | J55: #DIV/0! | L55: #DIV/0! | O55: 42856 | T55: =R55/R49-1 -> #DIV/0!
A56: Julho 2015 | C56: Agosto 2015 | E56: Setembro 2015 | G56: Outubro 2015 | I56: Novembro 2015 | K56: Dezembro 2015 | O56: 42186 | P56: =B82 -> 5456.913 | Q56: =P56/P32-1 -> -0.064574142 | R56: =B84 -> 17564.712 | S56: =R56/R32-1 -> -0.033248113 | T56: =R56/R26-1 -> 0.03511821
B57: Cash | D57: Cash | F57: Cash | H57: Cash | J57: Cash | L57: Cash | O57: 42217 | P57: =D82 -> 5088.925 | Q57: =P57/P56-1 -> -0.067435204 | R57: =D84 -> 17846.351 | S57: =R57/R56-1 -> 0.016034387 | T57: =R57/R26-1 -> 0.051715696
A58: 1 | B58: 5755.5 | C58: 3 | D58: 5176.5 | E58: 1 | F58: 5095 | G58: 1 | H58: 5178 | I58: 2 | J58: 5137.5 | K58: 1 | L58: 4619 | O58: 42248 | P58: =F82 -> 5208.0909 | Q58: =P58/P57-1 -> 0.023416716 | R58: =F84 -> 20289.16 | S58: =R58/R57-1 -> 0.13688001 | T58: =R58/R26-1 -> 0.19567455
A59: 2 | B59: 5761 | C59: 4 | D59: 5215.5 | E59: 2 | F59: 5090.5 | G59: 2 | H59: 5081 | I59: 3 | J59: 5149 | K59: 2 | L59: 4589 | O59: 42278 | P59: =H82 -> 5222.6136 | Q59: =P59/P58-1 -> 0.0027884934 | R59: =H84 -> 20224.049 | S59: =R59/R58-1 -> -0.0032091378 | T59: =R59/R26-1 -> 0.19183746
A60: 3 | B60: 5761.5 | C60: 5 | D60: 5171.5 | E60: 3 | F60: 5250 | G60: 5 | H60: 5144.5 | I60: 4 | J60: 5165.5 | K60: 3 | L60: 4525 | O60: 42309 | P60: =J82 -> 4808.2381 | Q60: =P60/P59-1 -> -0.079342561 | R60: =J84 -> 18166.485 | S60: =R60/R59-1 -> -0.10173847 | T60: =R60/R26-1 -> 0.07058174
A61: 6 | B61: 5570 | C61: 6 | D61: 5165 | E61: 4 | F61: 5155.5 | G61: 6 | H61: 5175 | I61: 5 | J61: 5053 | K61: 4 | L61: 4637 | O61: 42339 | P61: =L82 -> 4629 | Q61: =P61/P60-1 -> -0.037277292 | R61: =L84 -> 17927.654 | S61: =R61/R60-1 -> -0.013146796 | T61: =R61/R26-1 -> 0.05650702
A62: 7 | B62: 5440.5 | C62: 7 | D62: 5135.5 | E62: 7 | F62: 5176 | G62: 7 | H62: 5241 | I62: 6 | J62: 5000 | K62: 7 | L62: 4592.5 | O62: Acumulado 2015 | Q62: =P61/P26-1 -> -0.27930339 | S62: =R61/R26-1 -> 0.05650702
A63: 8 | B63: 5375 | C63: 10 | D63: 5150 | E63: 8 | F63: 5280 | G63: 8 | H63: 5160 | I63: 9 | J63: 4990 | K63: 8 | L63: 4567.5
A64: 9 | B64: 5576 | C64: 11 | D64: 5140 | E64: 9 | F64: 5366 | G64: 9 | H64: 5319 | I64: 10 | J64: 4933.5 | K64: 9 | L64: 4620
A65: 10 | B65: 5561.5 | C65: 12 | D65: 5103 | E65: 10 | F65: 5400 | G65: 12 | H65: 5335 | I65: 11 | J65: 4931 | K65: 10 | L65: 4572
A66: 13 | B66: 5605.5 | C66: 13 | D66: 5148 | E66: 11 | F66: 5352 | G66: 13 | H66: 5260.5 | I66: 12 | J66: 4872.5 | K66: 11 | L66: 4667
A67: 14 | B67: 5502.5 | C67: 14 | D67: 5156 | E67: 14 | F67: 5324 | G67: 14 | H67: 5278 | I67: 13 | J67: 4825 | K67: 14 | L67: 4640
A68: 15 | B68: 5597 | C68: 17 | D68: 5101 | E68: 15 | F68: 5290 | G68: 15 | H68: 5344 | I68: 16 | J68: 4765 | K68: 15 | L68: 4586
A69: 16 | B69: 5530 | C69: 18 | D69: 5000.5 | E69: 16 | F69: 5350 | G69: 16 | H69: 5270 | I69: 17 | J69: 4700 | K69: 16 | L69: 4583
A70: 17 | B70: 5465 | C70: 19 | D70: 5006.5 | E70: 17 | F70: 5369 | G70: 19 | H70: 5240 | I70: 18 | J70: 4669 | K70: 17 | L70: 4550
A71: 20 | B71: 5425 | C71: 20 | D71: 5060.5 | E71: 18 | F71: 5358 | G71: 20 | H71: 5189 | I71: 19 | J71: 4610 | K71: 18 | L71: 4650
A72: 21 | B72: 5475.5 | C72: 21 | D72: 5046 | E72: 21 | F72: 5267 | G72: 21 | H72: 5185.5 | I72: 20 | J72: 4690 | K72: 21 | L72: 4691
A73: 22 | B73: 5350.5 | C73: 24 | D73: 4888 | E73: 22 | F73: 5131 | G73: 22 | H73: 5274 | I73: 23 | J73: 4515.5 | K73: 22 | L73: 4672.5
A74: 23 | B74: 5340 | C74: 25 | D74: 5032 | E74: 23 | F74: 5112 | G74: 23 | H74: 5295 | I74: 24 | J74: 4527 | K74: 23 | L74: 4680
... A77: 28 | B77: 5239.5 | C77: 28 | D77: 5095 | E77: 28 | F77: 4965 | G77: 28 | H77: 5179 | I77: 27 | J77: 4636 | K77: 30 | L77: 4715
A78: 29 | B78: 5302 | C78: 31 | D78: Feriado | E78: 29 | F78: 5010 | G78: 29 | H78: 5161 | I78: 30 | J78: 4595.5 | K78: 31 | L78: 4702
A79: 30 | B79: 5241 | E79: 30 | F79: 5093 | G79: 30 | H79: 5135.5
A80: 31 | B80: 5220
A81: =B82/L28-1 -> -0.064574142 | C81: =D82/B82-1 -> -0.067435204 | E81: =F82/D82-1 -> 0.023416716 | G81: =H82/F82-1 -> 0.0027884934 | I81: =J82/H82-1 -> -0.079342561 | K81: =L82/J82-1 -> -0.037277292
A82: MM | B82: =AVERAGE(B58:B80) -> 5456.913 | C82: MM | D82: =AVERAGE(D58:D78) -> 5088.925 | E82: MM | F82: =AVERAGE(F58:F79) -> 5208.0909 | G82: MM | H82: =AVERAGE(H58:H80) -> 5222.6136 | I82: MM | J82: =AVERAGE(J58:J78) -> 4808.2381 | K82: MM | L82: =AVERAGE(L58:L78) -> 4629
A84: MM R$ | B84: =B82*A85 -> 17564.712 | C84: MM R$ | D84: =D82*C85 -> 17846.351 | E84: MM R$ | F84: =F82*E85 -> 20289.16 | G84: MM R$ | H84: =H82*G85 -> 20224.049 | I84: MM R$ | J84: =J82*I85 -> 18166.485 | K84: MM R$ | L84: =L82*K85 -> 17927.654
A85: 3.2188 | B85: =B84/L30-1 -> -0.033248113 | C85: 3.5069 | D85: =D84/B84-1 -> 0.016034387 | E85: 3.8957 | F85: =F84/D84-1 -> 0.13688001 | G85: 3.8724 | H85: =H84/F84-1 -> -0.0032091378 | I85: 3.7782 | J85: =J84/H84-1 -> -0.10173847 | K85: 3.8729 | L85: =L84/J84-1 -> -0.013146796
E88: VARIAÇÃO COBRE LME - REAIS

Sheet 2016
A1: Cobre LME Prices 2016 US$/Ton | O1: MÉDIAS
A2: Janeiro 2016 | C2: Fevereiro 2016 | E2: Março 2016 | G2: Abril 2016 | I2: Maio 2016 | K2: Junho 2016 | P2: US$ | Q2: Var (%) | R2: R$ | S2: Var Mês (%) | T2: Acumulado/Ano
B3: Cash | D3: Cash | F3: Cash | H3: Cash | J3: Cash | L3: Cash | O3: 41275 | P3: 8049.2455 | Q3: 0.010884092 | R3: 16364.921 | S3: -0.010958324
A4: 4 | B4: 4645 | C4: 1 | D4: 4534 | E4: 1 | F4: 4726 | G4: 1 | H4: 4880 | I4: 3 | J4: 4960 | K4: 1 | L4: 4601 | O4: 41306 | P4: 8070.475 | Q4: 0.0026374578 | R4: 15912.556 | S4: -0.027642381
A5: 5 | B5: 4647 | C5: 2 | D5: 4605.5 | E5: 2 | F5: 4780 | G5: 4 | H5: 4816 | I5: 4 | J5: 4892 | K5: 2 | L5: 4600 | O5: 41334 | P5: 7662.4 | Q5: -0.050563938 | R5: 15212.929 | S5: -0.043966954
A6: 6 | B6: 4600 | C6: 3 | D6: 4578.5 | E6: 3 | F6: 4830 | G6: 5 | H6: 4776 | I6: 5 | J6: 4826 | K6: 3 | L6: 4688 | O6: 41365 | P6: 7203.3571 | Q6: -0.059908496 | R6: 14413.918 | S6: -0.052521859
A7: 7 | B7: 4514 | C7: 4 | D7: 4685 | E7: 4 | F7: 4918 | G7: 6 | H7: 4775 | I7: 6 | J7: 4810 | K7: 6 | L7: 4706 | O7: 41395 | P7: 7229.1429 | Q7: 0.0035796801 | R7: 14704.077 | S7: 0.020130469
A8: 8 | B8: 4486.5 | C8: 5 | D8: 4669 | E8: 7 | F8: 5000 | G8: 7 | H8: 4715 | I8: 9 | J8: 4739.5 | K8: 7 | L8: 4589 | O8: 41426 | P8: 7004.05 | Q8: -0.031136867 | R8: 15198.789 | S8: 0.033644542
A9: 11 | B9: 4402.5 | C9: 8 | D9: 4572.5 | E9: 8 | F9: 4980.5 | G9: 8 | H9: 4654 | I9: 10 | J9: 4710 | K9: 8 | L9: 4590.5 | O9: 41456 | P9: 6896.9773 | Q9: -0.015287259 | R9: 15536.683 | S9: 0.022231658
A10: 12 | B10: 4355 | C10: 9 | D10: 4530.5 | E10: 9 | F10: 4935.5 | G10: 11 | H10: 4645 | I10: 11 | J10: 4748 | K10: 9 | L10: 4546 | O10: 41487 | P10: 7182.2619 | Q10: 0.041363719 | R10: 16802.902 | S10: 0.081498669
A11: 13 | B11: 4380 | C11: 10 | D11: 4507 | E11: 10 | F11: 4920.5 | G11: 12 | H11: 4715.5 | I11: 12 | J11: 4744 | K11: 10 | L11: 4504 | O11: 41518 | P11: 7161.4286 | Q11: -0.0029006647 | R11: 16264.32 | S11: -0.032052874
A12: 14 | B12: 4365.5 | C12: 11 | D12: 4474 | E12: 11 | F12: 4941 | G12: 13 | H12: 4838 | I12: 13 | J12: 4660 | K12: 13 | L12: 4515 | O12: 41548 | P12: 7188.7826 | Q12: 0.0038196342 | R12: 15720.43 | S12: -0.033440722
A13: 15 | B13: 4310.5 | C13: 12 | D13: 4488.5 | E13: 14 | F13: 4994 | G13: 14 | H13: 4830.5 | I13: 16 | J13: 4640.5 | K13: 14 | L13: 4610.5 | O13: 41579 | P13: 7066.4048 | Q13: -0.017023445 | R13: 16235.772 | S13: 0.032781659
A14: 18 | B14: 4360 | C14: 15 | D14: 4562 | E14: 15 | F14: 4920 | G14: 15 | H14: 4813.5 | I14: 17 | J14: 4634 | K14: 15 | L14: 4632 | O14: 41609 | P14: 7202.95 | Q14: 0.019323156 | R14: 16911.086 | S14: 0.041594231
A15: 19 | B15: 4440.5 | C15: 16 | D15: 4583.5 | E15: 16 | F15: 4945 | G15: 18 | H15: 4798 | I15: 18 | J15: 4600.5 | K15: 16 | L15: 4524.5 | O15: 41640 | P15: 7294.8864 | Q15: 0.01276371 | R15: 17368.395 | S15: 0.027041961 | T15: 0.027041961
A16: 20 | B16: 4347 | C16: 17 | D16: 4562 | E16: 17 | F16: 5029 | G16: 19 | H16: 4812 | I16: 19 | J16: 4596 | K16: 17 | L16: 4521.5 | O16: 41671 | P16: 7152.15 | Q16: -0.019566633 | R16: 17062.884 | S16: -0.017590036 | T16: 0.0089762565
A17: 21 | B17: 4376 | C17: 18 | D17: 4577 | E17: 18 | F17: 5103 | G17: 20 | H17: 4938.5 | I17: 20 | J17: 4630.5 | K17: 20 | L17: 4585 | O17: 41699 | P17: 6667.8095 | Q17: -0.067719564 | R17: 15507.991 | S17: -0.0911272 | T17: -0.082968925
A18: 22 | B18: 4468 | C18: 19 | D18: 4590 | E18: 21 | F18: 5079.5 | G18: 21 | H18: 5025.5 | I18: 23 | J18: 4572 | K18: 21 | L18: 4587 | O18: 41730 | P18: 6670.825 | Q18: 0.0004522439 | R18: 14896.619 | S18: -0.039423035 | T18: -0.11912107
A19: 25 | B19: 4454 | C19: 22 | D19: 4696 | E19: 22 | F19: 5070 | G19: 22 | H19: 5015.5 | I19: 24 | J19: 4637 | K19: 22 | L19: 4687.5 | O19: 41760 | P19: 6883.875 | Q19: 0.031937579 | R19: 15289.775 | S19: 0.02639226 | T19: -0.095872687
A20: 26 | B20: 4501 | C20: 23 | D20: 4663.5 | E20: 23 | F20: 5060.5 | G20: 25 | H20: 5005.5 | I20: 25 | J20: 4636 | K20: 23 | L20: 4747 | O20: 41791 | P20: 6806.0952 | Q20: -0.011298834 | R20: 15206.178 | S20: -0.0054674959 | T20: -0.100816
A21: 27 | B21: 4507.5 | C21: 24 | D21: 4585.5 | E21: 24 | F21: 4931 | G21: 26 | H21: 4935.5 | I21: 26 | J21: 4705.5 | K21: 24 | L21: 4663 | O21: 41821 | P21: 7104.8478 | Q21: 0.043894859 | R21: 15807.576 | S21: 0.03954958 | T21: -0.06525365
A22: 28 | B22: 4553.5 | C22: 25 | D22: 4655 | E22: 29 | F22: 4939.5 | G22: 27 | H22: 4932 | I22: 27 | J22: 4725.5 | K22: 27 | L22: 4692 | O22: 41852 | P22: 7000.55 | Q22: -0.014679811 | R22: 15880.048 | S22: 0.0045846177 | T22: -0.060968195
A23: 29 | B23: 4541.5 | C23: 26 | D23: 4681 | E23: 30 | F23: 4940 | G23: 28 | H23: 4912.5 | I23: 31 | J23: 4700 | K23: 28 | L23: 4777.5 | O23: 41883 | P23: 6872.2273 | Q23: -0.018330378 | R23: 16046.651 | S23: 0.010491345 | T23: -0.051116488
C24: 29 | D24: 4705 | E24: 31 | F24: 4855.5 | G24: 29 | H24: 5045 | K24: 29 | L24: 4780 | O24: 41913 | P24: 6739.1957 | Q24: -0.019357861 | R24: 16515.747 | S24: 0.029233272 | T24: -0.023377518
K25: 30 | L25: 4827 | O25: 41944 | P25: 6701.135 | Q25: -0.005647655 | R25: 17154.906 | S25: 0.038699965 | T25: 0.014417737
A26: =B27/'2015'!L82-1 -> -0.035914884 | C26: =D27/B27-1 -> 0.029740898 | E26: =F27/D27-1 -> 0.076612611 | G26: =H27/F27-1 -> -0.019442052 | I26: =J27/H27-1 -> -0.02947776 | K26: =L27/J27-1 -> -0.01554009 | O26: 41974 | P26: 6422.9524 | Q26: -0.041512762 | R26: 16968.798 | S26: -0.010848658 | T26: 0.0034126658
A27: MM | B27: =AVERAGE(B4:B25) -> 4462.75 | C27: MM | D27: =AVERAGE(D4:D24) -> 4595.4762 | E27: MM | F27: =AVERAGE(F4:F24) -> 4947.5476 | G27: MM | H27: =AVERAGE(H4:H25) -> 4851.3571 | I27: MM | J27: =AVERAGE(J4:J23) -> 4708.35 | K27: MM | L27: =AVERAGE(L4:L25) -> 4635.1818 | O27: 42005 | P27: 5791.175 | Q27: -0.098362458 | R27: 15271.908 | S27: -0.10000062 | T27: -0.10000062
A28: MM R$ | B28: =B27*A29 -> 18027.279 | C28: MM R$ | D28: =D27*C29 -> 18233.011 | E28: MM R$ | F28: =F27*E29 -> 18272.778 | G28: MM R$ | H28: =H27*G29 -> 17299.454 | I28: MM R$ | J28: =J27*I29 -> 16669.913 | K28: MM R$ | L28: =L27*K29 -> 15898.674 | O28: 42036 | P28: 5702.075 | Q28: -0.015385479 | R28: 16059.837 | S28: 0.051593399 | T28: -0.053566592
A29: 4.0395 | B29: =B28/'2015'!L84-1 -> 0.0055570307 | C29: 3.9676 | D29: =D28/B28-1 -> 0.0114123 | E29: 3.6933 | F29: =F28/D28-1 -> 0.002181005 | G29: 3.5659 | H29: =H28/F28-1 -> -0.053266296 | I29: 3.5405 | J29: =J28/H28-1 -> -0.036390816 | K29: 3.43 | L29: =L28/J28-1 -> -0.04626536 | O29: 42064 | P29: 5919.9048 | Q29: 0.038201841 | R29: 18601.525 | S29: 0.15826359 | T29: 0.096219358
A30: Cobre LME Prices 2016 US$/Ton | O30: 42095 | P30: 6028.4775 | Q30: 0.018340285 | R30: 18401.928 | S30: -0.010730151 | T30: 0.084456759
A31: Julho 2016 | C31: Agosto 2016 | E31: Setembro 2016 | G31: Outubro 2016 | I31: Novembro 2016 | K31: Dezembro 2016 | O31: 42125 | P31: 6300.6053 | Q31: 0.04514038 | R31: 19242.048 | S31: 0.045653962 | T31: 0.13396651
B32: Cash | D32: Cash | F32: Cash | H32: Cash | J32: Cash | L32: Cash | O32: 42156 | P32: 5833.6136 | Q32: -0.074118534 | R32: 18168.79 | S32: -0.055776744 | T32: 0.070717548
O33: 42186 | T33: -1
O34: 42217 | T34: -1
O35: 42248 | T35: -1
O36: 42278 | T36: -1
O37: 42309 | T37: -1
O38: 42339 | T38: -1
O39: 42370 | T39: #DIV/0!
O40: 42401 | T40: #DIV/0!
O41: 42430 | T41: #DIV/0!
O42: 42461 | T42: #DIV/0!
O43: 42491 | T43: #DIV/0!
O44: 42522 | T44: #DIV/0!
O45: 42552 | T45: #DIV/0!
O46: 42583 | T46: #DIV/0!
O47: 42614 | T47: #DIV/0!
O48: 42644 | T48: #DIV/0!
A49: Média | B49: #DIV/0! | C49: Média | D49: #DIV/0! | E49: Média | F49: #DIV/0! | G49: Média | H49: #DIV/0! | I49: Média | J49: #DIV/0! | K49: Média | L49: #DIV/0! | O49: 42675 | T49: #DIV/0!
A50: MM | B50: #DIV/0! | C50: MM | D50: #DIV/0! | E50: MM | F50: #DIV/0! | G50: MM | H50: #DIV/0! | I50: MM | J50: #DIV/0! | K50: MM | L50: #DIV/0! | O50: 42705 | T50: #DIV/0!
A51: #DIV/0! | C51: #DIV/0! | E51: #DIV/0! | G51: #DIV/0! | I51: #DIV/0! | K51: #DIV/0! | O51: 42736 | T51: #DIV/0!
A52: MM R$ | B52: #DIV/0! | C52: MM R$ | D52: #DIV/0! | E52: MM R$ | F52: #DIV/0! | G52: MM R$ | H52: #DIV/0! | I52: MM R$ | J52: #DIV/0! | K52: MM R$ | L52: #DIV/0! | O52: 42767 | T52: #DIV/0!
B53: #DIV/0! | D53: #DIV/0! | F53: #DIV/0! | H53: #DIV/0! | J53: #DIV/0! | L53: #DIV/0! | O53: 42795 | T53: #DIV/0!
A54: Julho 2016 | C54: Agosto 2016 | E54: Setembro 2016 | G54: Outubro 2016 | I54: Novembro 2016 | K54: Dezembro 2016 | O54: 42826 | T54: #DIV/0!
B55: Cash | D55: Cash | F55: Cash | H55: Cash | J55: Cash | L55: Cash | O55: 42856 | T55: #DIV/0!
A56: 1 | B56: 4783.5 | C56: 1 | D56: 4906.5 | E56: 1 | F56: 4619.5 | G56: 3 | H56: 4807 | I56: 1 | J56: 4862.5 | K56: 1 | L56: 5773 | O56: 42186 | P56: 5456.913 | Q56: -0.064574142 | R56: 17564.712 | S56: =R56/R32-1 -> -0.033248113 | T56: 0.03511821
A57: 4 | B57: 4920 | C57: 2 | D57: 4885.25 | E57: 2 | F57: 4606.75 | G57: 4 | H57: 4790.5 | I57: 2 | J57: 4871 | K57: 2 | L57: 5736 | O57: 42217 | P57: 5088.925 | Q57: -0.067435204 | R57: 17846.351 | S57: =R57/R56-1 -> 0.016034387 | T57: 0.051715696
A58: 5 | B58: 4840 | C58: 3 | D58: 4844.25 | E58: 5 | F58: 4602.75 | G58: 5 | H58: 4777.5 | I58: 3 | J58: 4918 | K58: 5 | L58: 5851.5 | O58: 42248 | P58: 5208.0909 | Q58: 0.023416716 | R58: 20289.16 | S58: =R58/R57-1 -> 0.13688001 | T58: 0.19567455
A59: 6 | B59: 4706 | C59: 4 | D59: 4786.5 | E59: 6 | F59: 4622.25 | G59: 6 | H59: 4742 | I59: 4 | J59: 4943 | K59: 6 | L59: 5856 | O59: 42278 | P59: 5222.6136 | Q59: 0.0027884934 | R59: 20224.049 | S59: =R59/R58-1 -> -0.0032091378 | T59: 0.19183746
A60: 7 | B60: 4725 | C60: 5 | D60: 4792.25 | E60: 7 | F60: 4641.5 | G60: 7 | H60: 4742 | I60: 7 | J60: 5032 | K60: 7 | L60: 5903.5 | O60: 42309 | P60: 4808.2381 | Q60: -0.079342561 | R60: 18166.485 | S60: =R60/R59-1 -> -0.10173847 | T60: 0.07058174
A61: 8 | B61: 4709.5 | C61: 8 | D61: 4795.5 | E61: 8 | F61: 4617.25 | G61: 10 | H61: 4786 | I61: 8 | J61: 5044 | K61: 8 | L61: 5838 | O61: 42339 | P61: 4629 | Q61: -0.037277292 | R61: 17927.654 | S61: =R61/R60-1 -> -0.013146796 | T61: =R61/R26-1 -> 0.05650702
A62: 11 | B62: 4745.75 | C62: 9 | D62: 4778.5 | E62: 9 | F62: 4622.25 | G62: 11 | H62: 4801.5 | I62: 9 | J62: 5335 | K62: 9 | L62: 5824 | O62: 42370 | P62: =B27 -> 4462.75 | Q62: =P62/P61-1 -> -0.035914884 | R62: =B28 -> 18027.279 | S62: =R62/R61-1 -> 0.0055570307 | T62: =R62/$R$61-1 -> 0.0055570307
A63: 12 | B63: 4811 | C63: 10 | D63: 4874 | E63: 12 | F63: 4572.75 | G63: 12 | H63: 4805 | I63: 10 | J63: 5619 | K63: 12 | L63: 5757 | O63: 42401 | P63: =D27 -> 4595.4762 | Q63: =P63/P62-1 -> 0.029740898 | R63: =D28 -> 18233.011 | S63: =R63/R62-1 -> 0.0114123 | T63: =R63/$R$61-1 -> 0.017032749
A64: 13 | B64: 4918.25 | C64: 11 | D64: 4809.5 | E64: 13 | F64: 4641.25 | G64: 13 | H64: 4754.5 | I64: 11 | J64: 5900 | K64: 13 | L64: 5765.5 | O64: 42430 | P64: =F27 -> 4947.5476 | Q64: =P64/P63-1 -> 0.076612611 | R64: =F28 -> 18272.778 | S64: =R64/R63-1 -> 0.002181005 | T64: =R64/$R$61-1 -> 0.019250903
A65: 14 | B65: 4911.25 | C65: 12 | D65: 4745.5 | E65: 14 | F65: 4669.25 | G65: 14 | H65: 4672.5 | I65: 14 | J65: 5620 | K65: 14 | L65: 5735 | O65: 42461 | P65: =H27 -> 4851.3571 | Q65: =P65/P64-1 -> -0.019442052 | R65: =H28 -> 17299.454 | S65: =R65/R64-1 -> -0.053266296 | T65: =R65/$R$61-1 -> -0.035040818
A66: 15 | B66: 4945.25 | C66: 15 | D66: 4745.75 | E66: 15 | F66: 4726 | G66: 17 | H66: 4671.5 | I66: 15 | J66: 5448 | K66: 15 | L66: 5682.5 | O66: 42491 | P66: =J27 -> 4708.35 | Q66: =P66/P65-1 -> -0.02947776 | R66: =J28 -> 16669.913 | S66: =R66/R65-1 -> -0.036390816 | T66: =R66/R61-1 -> -0.07015647
A67: 18 | B67: 4838.5 | C67: 16 | D67: 4798 | E67: 16 | F67: 4733.25 | G67: 18 | H67: 4665.5 | I67: 16 | J67: 5459 | K67: 16 | L67: 5649 | O67: 42522 | P67: =L27 -> 4635.1818 | Q67: =P67/P66-1 -> -0.01554009 | R67: =L28 -> 15898.674 | S67: =R67/R66-1 -> -0.04626536 | T67: =R67/R61-1 -> -0.11317602
A68: 19 | B68: 4938 | C68: 17 | D68: 4755.5 | E68: 19 | F68: 4731.25 | G68: 19 | H68: 4642.5 | I68: 17 | J68: 5426 | K68: 19 | L68: 5561 | O68: 42552 | P68: =B80 -> 4855.4762 | Q68: =P68/P67-1 -> 0.047526587 | R68: =B82 -> 15885.176 | S68: =R68/R67-1 -> -0.00084898476 | T68: =R68/R61-1 -> -0.11392892
A69: 20 | B69: 4900 | C69: 18 | D69: 4802.5 | E69: 20 | F69: 4732.25 | G69: 20 | H69: 4633.5 | I69: 18 | J69: 5446 | K69: 20 | L69: 5485.5 | O69: 42583 | P69: =D80 -> 4757.9659 | Q69: =P69/P68-1 -> -0.020082537 | R69: =D82 -> 15271.167 | S69: =R69/R68-1 -> -0.038652926 | T69: =R69/R61-1 -> -0.14817816
A70: 21 | B70: 4953.25 | C70: 19 | D70: 4773.5 | E70: 21 | F70: 4732.75 | G70: 21 | H70: 4637 | I70: 21 | J70: 5535.5 | K70: 21 | L70: 5498.5 | O70: 42614 | P70: =F80 -> 4705.625 | Q70: =P70/P69-1 -> -0.01100069 | R70: =F82 -> 15323.397 | S70: =R70/R69-1 -> 0.0034201621 | T70: =R70/R61-1 -> -0.14526479
A71: 22 | B71: 4955.5 | C71: 22 | D71: 4732 | E71: 22 | F71: 4815.25 | G71: 24 | H71: 4620.5 | I71: 22 | J71: 5618 | K71: 22 | L71: 5426 | O71: 42644 | P71: =H80 -> 4732.1429 | Q71: =P71/P70-1 -> 0.0056353528 | R71: =H82 -> 15097.429 | S71: =R71/R70-1 -> -0.014746644 | T71: =R71/R61-1 -> -0.15786926
A72: 25 | B72: 4919.5 | C72: 23 | D72: 4719 | E72: 23 | F72: 4814.5 | G72: 25 | H72: 4720 | I72: 23 | J72: 5564 | K72: 23 | L72: 5482 | O72: 42675 | P72: =J80 -> 5443.25 | Q72: =P72/P71-1 -> 0.1502717 | R72: =J82 -> 18126.022 | S72: =R72/R71-1 -> 0.2006033 | T72: =R72/R61-1 -> 0.011064939
A73: 26 | B73: 4861.5 | C73: 24 | D73: 4658.5 | E73: 26 | F73: 4793.75 | G73: 26 | H73: 4717.5 | I73: 24 | J73: 5834.5 | O73: Acumulado 2016 | P73: =P72/P61-1 -> 0.17590192 | Q73: Dolar | S73: =R72/R61-1 -> 0.011064939 | T73: Reais
A74: 27 | B74: 4869.25 | C74: 25 | D74: 4639.5 | E74: 27 | F74: 4774 | G74: 27 | H74: 4774 | I74: 25 | J74: 5822.5
A75: 28 | B75: 4861.5 | C75: 26 | D75: 4622 | E75: 28 | F75: 4807.25 | G75: 28 | H75: 4787 | I75: 28 | J75: 5935.5
A76: 29 | B76: 4852.5 | C76: 29 | D76: Feriado | E76: 29 | F76: 4816.25 | G76: 31 | H76: 4827.5 | I76: 29 | J76: 5778
C77: 30 | D77: 4609 | E77: 30 | F77: 4831.75 | I77: 30 | J77: 5740
C78: 31 | D78: 4602.25
A79: =B80/L27-1 -> 0.047526587 | C79: =D80/B80-1 -> -0.020082537 | E79: =F80/D80-1 -> -0.01100069 | G79: =H80/F80-1 -> 0.0056353528 | I79: =J80/H80-1 -> 0.1502717 | K79: =L80/J80-1 -> 0.046347203
A80: MM | B80: =AVERAGE(B56:B78) -> 4855.4762 | C80: MM | D80: =AVERAGE(D56:D78) -> 4757.9659 | E80: MM | F80: =AVERAGE(F56:F77) -> 4705.625 | G80: MM | H80: =AVERAGE(H56:H78) -> 4732.1429 | I80: MM | J80: =AVERAGE(J56:J77) -> 5443.25 | K80: MM | L80: =AVERAGE(L56:L76) -> 5695.5294
A82: MM R$ | B82: =B80*A83 -> 15885.176 | C82: MM R$ | D82: =D80*C83 -> 15271.167 | E82: MM R$ | F82: =F80*E83 -> 15323.397 | G82: MM R$ | H82: =H80*G83 -> 15097.429 | I82: MM R$ | J82: =J80*I83 -> 18126.022 | K82: MM R$ | L82: =L80*K83 -> 19307.845
A83: 3.2716 | B83: =B82/L28-1 -> -0.00084898476 | C83: 3.2096 | D83: =D82/L28-1 -> -0.039469095 | E83: 3.2564 | F83: =F82/D82-1 -> 0.0034201621 | G83: 3.1904 | H83: =H82/F82-1 -> -0.014746644 | I83: 3.33 | J83: =J82/H82-1 -> 0.2006033 | K83: 3.39 | L83: =L82/J82-1 -> 0.065200306
E86: VARIAÇÃO COBRE LME - REAIS

Sheet 2017
A1: Cobre LME Prices 2017 US$/Ton | O1: MÉDIAS
A2: Janeiro 2017 | C2: Fevereiro 2017 | E2: Março 2017 | G2: Abril 2017 | I2: Maio 2017 | K2: Junho 2017 | P2: US$ | Q2: Var (%) | R2: R$ | S2: Var Mês (%) | T2: Acumulado/Ano
B3: Cash | D3: Cash | F3: Cash | H3: Cash | J3: Cash | L3: Cash | O3: 41275 | P3: 8049.2455 | Q3: 0.010884092 | R3: 16364.921 | S3: -0.010958324
A4: 3 | B4: 5574 | C4: 1 | D4: 5931 | E4: 1 | F4: 6040 | G4: 3 | H4: 5817 | I4: 2 | J4: 5746.5 | K4: 1 | L4: 5636.5 | O4: 41306 | P4: 8070.475 | Q4: 0.0026374578 | R4: 15912.556 | S4: -0.027642381
A5: 4 | B5: 5500.5 | C5: 2 | D5: 5903 | E5: 2 | F5: 5994 | G5: 4 | H5: 5724.5 | I5: 3 | J5: 5636.5 | K5: 2 | L5: 5559.5 | O5: 41334 | P5: 7662.4 | Q5: -0.050563938 | R5: 15212.929 | S5: -0.043966954
A6: 5 | B6: 5611 | C6: 3 | D6: 5836 | E6: 3 | F6: 5910 | G6: 5 | H6: 5808.5 | I6: 4 | J6: 5543 | K6: 5 | L6: 5586.5 | O6: 41365 | P6: 7203.3571 | Q6: -0.059908496 | R6: 14413.918 | S6: -0.052521859
A7: 6 | B7: 5546.5 | C7: 6 | D7: 5786 | E7: 6 | F7: 5856 | G7: 6 | H7: 5870.5 | I7: 5 | J7: 5530.5 | K7: 6 | L7: 5540.5 | O7: 41395 | P7: 7229.1429 | Q7: 0.0035796801 | R7: 14704.077 | S7: 0.020130469
A8: 9 | B8: 5551.5 | C8: 7 | D8: 5802 | E8: 7 | F8: 5807 | G8: 7 | H8: 5770 | I8: 8 | J8: 5466 | K8: 7 | L8: 5575.5 | O8: 41426 | P8: 7004.05 | Q8: -0.031136867 | R8: 15198.789 | S8: 0.033644542
A9: 10 | B9: 5642 | C9: 8 | D9: 5865 | E9: 8 | F9: 5782 | G9: 10 | H9: 5731 | I9: 9 | J9: 5496 | K9: 8 | L9: 5647.5 | O9: 41456 | P9: 6896.9773 | Q9: -0.015287259 | R9: 15536.683 | S9: 0.022231658
A10: 11 | B10: 5709.5 | C10: 9 | D10: 5863 | E10: 9 | F10: 5655 | G10: 11 | H10: 5746 | I10: 10 | J10: 5512 | K10: 9 | L10: 5739 | O10: 41487 | P10: 7182.2619 | Q10: 0.041363719 | R10: 16802.902 | S10: 0.081498669
A11: 12 | B11: 5752.5 | C11: 10 | D11: 5872 | E11: 10 | F11: 5714.5 | G11: 12 | H11: 5685 | I11: 11 | J11: 5580.5 | K11: 12 | L11: 5752 | O11: 41518 | P11: 7161.4286 | Q11: -0.0029006647 | R11: 16264.32 | S11: -0.032052874
A12: 13 | B12: 5797 | C12: 13 | D12: 6111 | E12: 13 | F12: 5794 | G12: 13 | H12: 5655 | I12: 12 | J12: 5520 | K12: 13 | L12: 5659 | O12: 41548 | P12: 7188.7826 | Q12: 0.0038196342 | R12: 15720.43 | S12: -0.033440722
A13: 16 | B13: 5857 | C13: 14 | D13: 6145 | E13: 14 | F13: 5747 | G13: 18 | H13: 5620.5 | I13: 15 | J13: 5586 | K13: 14 | L13: 5684.5 | O13: 41579 | P13: 7066.4048 | Q13: -0.017023445 | R13: 16235.772 | S13: 0.032781659
A14: 17 | B14: 5771.5 | C14: 15 | D14: 6016 | E14: 15 | F14: 5850 | G14: 19 | H14: 5600.5 | I14: 16 | J14: 5584 | K14: 15 | L14: 5637 | O14: 41609 | P14: 7202.95 | Q14: 0.019323156 | R14: 16911.086 | S14: 0.041594231
A15: 18 | B15: 5721 | C15: 16 | D15: 6015 | E15: 16 | F15: 5911 | G15: 20 | H15: 5611.5 | I15: 17 | J15: 5575 | K15: 16 | L15: 5655.5 | O15: 41640 | P15: 7294.8864 | Q15: 0.01276371 | R15: 17368.395 | S15: 0.027041961 | T15: 0.027041961
A16: 19 | B16: 5710 | C16: 17 | D16: 5939 | E16: 17 | F16: 5889 | G16: 21 | H16: 5601 | I16: 18 | J16: 5490 | K16: 19 | L16: 5687 | O16: 41671 | P16: 7152.15 | Q16: -0.019566633 | R16: 17062.884 | S16: -0.017590036 | T16: 0.0089762565
A17: 20 | B17: 5706 | C17: 20 | D17: 6002 | E17: 20 | F17: 5891 | G17: 24 | H17: 5612 | I17: 19 | J17: 5596 | K17: 20 | L17: 5673.5 | O17: 41699 | P17: 6667.8095 | Q17: -0.067719564 | R17: 15507.991 | S17: -0.0911272 | T17: -0.082968925
A18: 23 | B18: 5775 | C18: 21 | D18: 6034 | E18: 21 | F18: 5765.5 | G18: 25 | H18: 5652.5 | I18: 22 | J18: 5677 | K18: 21 | L18: 5650 | O18: 41730 | P18: 6670.825 | Q18: 0.0004522439 | R18: 14896.619 | S18: -0.039423035 | T18: -0.11912107
A19: 24 | B19: 5879 | C19: 22 | D19: 5976 | E19: 22 | F19: 5712 | G19: 26 | H19: 5677.5 | I19: 23 | J19: 5660.5 | K19: 22 | L19: 5736 | O19: 41760 | P19: 6883.875 | Q19: 0.031937579 | R19: 15289.775 | S19: 0.02639226 | T19: -0.095872687
A20: 25 | B20: 5867 | C20: 23 | D20: 5991 | E20: 23 | F20: 5790.5 | G20: 27 | H20: 5686.5 | I20: 24 | J20: 5662.5 | K20: 23 | L20: 5774 | O20: 41791 | P20: 6806.0952 | Q20: -0.011298834 | R20: 15206.178 | S20: -0.0054674959 | T20: -0.100816
A21: 26 | B21: 5890 | C21: 24 | D21: 5881 | E21: 24 | F21: 5782.5 | G21: 28 | H21: 5688.5 | I21: 25 | J21: 5665 | K21: 26 | L21: 5771 | O21: 41821 | P21: 7104.8478 | Q21: 0.043894859 | R21: 15807.576 | S21: 0.03954958 | T21: -0.06525365
A22: 27 | B22: 5847 | C22: 27 | D22: 5927 | E22: 27 | F22: 5673.5 | I22: 26 | J22: 5671 | K22: 27 | L22: 5789 | O22: 41852 | P22: 7000.55 | Q22: -0.014679811 | R22: 15880.048 | S22: 0.0045846177 | T22: -0.060968195
A23: 30 | B23: 5857 | C23: 28 | D23: 5936 | E23: 28 | F23: 5774.5 | I23: 30 | J23: 5608 | K23: 28 | L23: 5822 | O23: 41883 | P23: 6872.2273 | Q23: -0.018330378 | R23: 16046.651 | S23: 0.010491345 | T23: -0.051116488
A24: 31 | B24: 5921 | E24: 29 | F24: 5847 | I24: 31 | J24: 5615.5 | K24: 29 | L24: 5905.5 | O24: 41913 | P24: 6739.1957 | Q24: -0.019357861 | R24: 16515.747 | S24: 0.029233272 | T24: -0.023377518
E25: 30 | F25: 5860 | K25: 30 | L25: 5907.5
E26: 31 | F26: 5849 | O26: 41944 | P26: 6701.135 | Q26: -0.005647655 | R26: 17154.906 | S26: 0.038699965 | T26: 0.014417737
A27: =B28/'2016'!L80-1 -> 0.0073564996 | C27: =D28/B28-1 -> 0.035577162 | E27: =F28/D28-1 -> -0.020201506 | G27: =H28/F28-1 -> -0.021275377 | I27: =J28/H28-1 -> -0.018633359 | K27: =L28/J28-1 -> 0.019310967 | O27: 41974 | P27: 6422.9524 | Q27: -0.041512762 | R27: 16968.798 | S27: -0.010848658 | T27: 0.0034126658
A28: MM | B28: =AVERAGE(B4:B26) -> 5737.4286 | C28: MM | D28: =AVERAGE(D4:D24) -> 5941.55 | E28: MM | F28: =AVERAGE(F4:F26) -> 5821.5217 | G28: MM | H28: =AVERAGE(H4:H21) -> 5697.6667 | I28: MM | J28: =AVERAGE(J4:J24) -> 5591.5 | K28: MM | L28: =AVERAGE(L4:L26) -> 5699.4773 | O28: 42005 | P28: 5791.175 | Q28: -0.098362458 | R28: 15271.908 | S28: -0.10000062 | T28: -0.10000062
A29: MM R$ | B29: =B28*A30 -> 18359.771 | C29: MM R$ | D29: =D28*C30 -> 18478.22 | E29: MM R$ | F29: =F28*E30 -> 18191.673 | G29: MM R$ | H29: =H28*G30 -> 17859.336 | I29: MM R$ | J29: =J28*I30 -> 17934.736 | K29: MM R$ | L29: =L28*K30 -> 18764.389 | O29: 42036 | P29: 5702.075 | Q29: -0.015385479 | R29: 16059.837 | S29: 0.051593399 | T29: -0.053566592
A30: 3.2 | B30: =B29/'2016'!L82-1 -> -0.049103009 | C30: 3.11 | D30: =D29/B29-1 -> 0.0064515548 | E30: 3.1249 | F30: =F29/D29-1 -> -0.015507295 | G30: 3.1345 | H30: =H29/F29-1 -> -0.018268639 | I30: 3.2075 | J30: =J29/H29-1 -> 0.0042218861 | K30: 3.2923 | L30: =L29/J29-1 -> 0.046259547 | O30: 42064 | P30: 5919.9048 | Q30: 0.038201841 | R30: 18601.525 | S30: 0.15826359 | T30: 0.096219358
A31: Cobre LME Prices 2017 US$/Ton | O31: MÉDIAS
A32: Julho 2017 | C32: Agosto 2017 | E32: Setembro 2017 | G32: Outubro 2017 | I32: Novembro 2017 | K32: Dezembro 2017 | O32: 42125 | P32: 6300.6053 | Q32: 0.04514038 | R32: 19242.048 | S32: 0.045653962 | T32: 0.13396651
B33: Cash | D33: Cash | F33: Cash | H33: Cash | J33: Cash | L33: Cash | O33: 42156 | P33: 5833.6136 | Q33: -0.074118534 | R33: 18168.79 | S33: -0.055776744 | T33: 0.070717548
A34: Média | B34: #DIV/0! | C34: Média | D34: #DIV/0! | E34: Média | F34: #DIV/0! | G34: Média | H34: #DIV/0! | I34: Média | J34: #DIV/0! | K34: Média | L34: #DIV/0! | O34: 42675 | T34: #DIV/0!
A35: MM | B35: #DIV/0! | C35: MM | D35: #DIV/0! | E35: MM | F35: #DIV/0! | G35: MM | H35: #DIV/0! | I35: MM | J35: #DIV/0! | K35: MM | L35: #DIV/0! | O35: 42705 | T35: #DIV/0!
A36: #DIV/0! | C36: #DIV/0! | E36: #DIV/0! | G36: #DIV/0! | I36: #DIV/0! | K36: #DIV/0! | O36: 42736 | T36: #DIV/0!
A37: MM R$ | B37: #DIV/0! | C37: MM R$ | D37: #DIV/0! | E37: MM R$ | F37: #DIV/0! | G37: MM R$ | H37: #DIV/0! | I37: MM R$ | J37: #DIV/0! | K37: MM R$ | L37: #DIV/0! | O37: 42767 | T37: #DIV/0!
B38: #DIV/0! | D38: #DIV/0! | F38: #DIV/0! | H38: #DIV/0! | J38: #DIV/0! | L38: #DIV/0! | O38: 42795 | T38: #DIV/0!
A39: Julho 2016 | C39: Agosto 2016 | E39: Setembro 2016 | G39: Outubro 2016 | I39: Novembro 2016 | K39: Dezembro 2016 | O39: 42826 | T39: #DIV/0!
B40: Cash | D40: Cash | F40: Cash | H40: Cash | J40: Cash | L40: Cash | O40: 42856 | T40: #DIV/0!
A41: 3 | B41: 5894 | C41: 1 | D41: 6300.5 | E41: 1 | F41: 6776 | G41: 2 | H41: 6455 | I41: 1 | J41: 6918 | K41: 1 | L41: 6734 | O41: 42186 | P41: 5456.913 | Q41: -0.064574142 | R41: 17564.712 | S41: =R41/R33-1 -> -0.033248113 | T41: 0.03511821
A42: 4 | B42: 5847 | C42: 2 | D42: 6300 | E42: 4 | F42: 6873 | G42: 3 | H42: 6447 | I42: 2 | J42: 6855 | K42: 4 | L42: 6807 | O42: 42217 | P42: 5088.925 | Q42: -0.067435204 | R42: 17846.351 | S42: =R42/R41-1 -> 0.016034387 | T42: 0.051715696
A43: 5 | B43: 5818 | C43: 3 | D43: 6290 | E43: 5 | F43: 6904 | G43: 4 | H43: 6453 | I43: 3 | J43: 6914.5 | K43: 5 | L43: 6645 | O43: 42248 | P43: 5208.0909 | Q43: 0.023416716 | R43: 20289.16 | S43: =R43/R42-1 -> 0.13688001 | T43: 0.19567455
A44: 6 | B44: 5828.5 | C44: 4 | D44: 6330 | E44: 6 | F44: 6864 | G44: 5 | H44: 6511 | I44: 4 | J44: 6902.5 | K44: 6 | L44: 6539 | O44: 42278 | P44: 5222.6136 | Q44: 0.0027884934 | R44: 20224.049 | S44: =R44/R43-1 -> -0.0032091378 | T44: 0.19183746
A45: 7 | B45: 5809 | C45: 7 | D45: 6333 | E45: 7 | F45: 6842.5 | G45: 6 | H45: 6639 | I45: 7 | J45: 6863 | K45: 7 | L45: 6530.5 | O45: 42309 | P45: 4808.2381 | Q45: -0.079342561 | R45: 18166.485 | S45: =R45/R44-1 -> -0.10173847 | T45: 0.07058174
A46: 10 | B46: 5780 | C46: 8 | D46: 6364 | E46: 8 | F46: 6780 | G46: 9 | H46: 6607 | I46: 8 | J46: 6812 | K46: 8 | L46: 6538.5 | O46: 42339 | P46: 4629 | Q46: -0.037277292 | R46: 17927.654 | S46: =R46/R45-1 -> -0.013146796 | T46: =R46/R27-1 -> 0.05650702
A47: 11 | B47: 5795 | C47: 9 | D47: 6465 | E47: 11 | F47: 6737 | G47: 10 | H47: 6641 | I47: 9 | J47: 6777 | K47: 11 | L47: 6547.5 | O47: 42370 | P47: =B28 -> 5737.4286 | Q47: =P47/P46-1 -> 0.23945314 | R47: =B29 -> 18359.771 | S47: =R47/R46-1 -> 0.024103395 | T47: =R47/$R$46-1 -> 0.024103395
A48: 12 | B48: 5882.5 | C48: 10 | D48: 6416.5 | E48: 12 | F48: 6601.5 | G48: 11 | H48: 6685 | I48: 10 | J48: 6797 | K48: 12 | L48: 6614 | O48: 42401 | P48: =D28 -> 5941.55 | Q48: =P48/P47-1 -> 0.035577162 | R48: =D29 -> 18478.22 | S48: =R48/R47-1 -> 0.0064515548 | T48: =R48/$R$46-1 -> 0.030710454
A49: 13 | B49: 5902 | C49: 11 | D49: 6353.5 | E49: 13 | F49: 6527 | G49: 12 | H49: 6813 | I49: 13 | J49: 6768 | K49: 13 | L49: 6685 | O49: 42430 | P49: =F28 -> 5821.5217 | Q49: =P49/P48-1 -> -0.020201506 | R49: =F29 -> 18191.673 | S49: =R49/R48-1 -> -0.015507295 | T49: =R49/$R$46-1 -> 0.014726923
A50: 14 | B50: 5858 | C50: 14 | D50: 6351 | E50: 14 | F50: 6418.5 | G50: 13 | H50: 6858 | I50: 14 | J50: 6822.5 | K50: 14 | L50: 6723 | O50: 42461 | P50: =H28 -> 5697.6667 | Q50: =P50/P49-1 -> -0.021275377 | R50: =H29 -> 17859.336 | S50: =R50/R49-1 -> -0.018268639 | T50: =R50/$R$46-1 -> -0.003810757
A51: 17 | B51: 5965.5 | C51: 15 | D51: 6382 | E51: 15 | F51: 6457 | G51: 16 | H51: 7063 | I51: 15 | J51: 6715.5 | K51: 15 | L51: 6735.5 | O51: 42491 | P51: =J28 -> 5591.5 | Q51: =P51/P50-1 -> -0.018633359 | R51: =J29 -> 17934.736 | S51: =R51/R50-1 -> 0.0042218861 | T51: =R51/R46-1 -> 0.00039504053
A52: 18 | B52: 5940.5 | C52: 16 | D52: 6433 | E52: 18 | F52: 6487 | G52: 17 | H52: 7046 | I52: 16 | J52: 6764 | K52: 18 | L52: 6844 | O52: 42522 | P52: =L28 -> 5699.4773 | Q52: =P52/P51-1 -> 0.019310967 | R52: =L29 -> 18764.389 | S52: =R52/R51-1 -> 0.046259547 | T52: =R52/R46-1 -> 0.046672862
A53: 19 | B53: 5956 | C53: 17 | D53: 6460 | E53: 19 | F53: 6492 | G53: 18 | H53: 6971.5 | I53: 17 | J53: 6728.5 | K53: 19 | L53: 6845 | O53: 42552 | P53: =B65 -> 5978.5952 | Q53: =P53/P52-1 -> 0.048972555 | R53: =B67 -> 19181.725 | S53: =R53/R52-1 -> 0.022240849 | T53: =R53/R46-1 -> 0.069951755
A54: 20 | B54: 5930 | C54: 18 | D54: 6453 | E54: 20 | F54: 6520 | G54: 19 | H54: 6920 | I54: 20 | J54: 6752 | K54: 20 | L54: 6925 | O54: 42583 | P54: =D65 -> 6478.2273 | Q54: =P54/P53-1 -> 0.083570139 | R54: =D67 -> 20407.712 | S54: =R54/R53-1 -> 0.063914304 | T54: =R54/R46-1 -> 0.13833698
A55: 21 | B55: 6001.5 | C55: 21 | D55: 6515.5 | E55: 21 | F55: 6407.5 | G55: 20 | H55: 7008.5 | I55: 21 | J55: 6828 | K55: 21 | L55: 6977 | O55: 42614 | P55: =F65 -> 6583.1905 | Q55: =P55/P54-1 -> 0.016202458 | R55: =F67 -> 20612.628 | S55: =R55/R54-1 -> 0.010041113 | T55: =R55/R46-1 -> 0.14976715
A56: 24 | B56: 6000 | C56: 22 | D56: 6584 | E56: 22 | F56: 6405 | G56: 23 | H56: 6959 | I56: 22 | J56: 6872.5 | K56: 22 | L56: 7019 | O56: 42644 | P56: =H65 -> 6797.3864 | Q56: =P56/P55-1 -> 0.03253679 | R56: =H67 -> 21693.859 | S56: =R56/R55-1 -> 0.052454781 | T56: =R56/R46-1 -> 0.21007793
A57: 25 | B57: 6150 | C57: 23 | D57: 6555 | E57: 25 | F57: 6416 | G57: 24 | H57: 7073.5 | I57: 23 | J57: 6895.5 | K57: 27 | L57: 7140 | O57: 42675 | P57: =J65 -> 6825.5682 | Q57: =P57/P56-1 -> 0.0041459786 | R57: =J67 -> 22252.035 | S57: =R57/R56-1 -> 0.02572969 | T57: =R57/R46-1 -> 0.24121286
A58: 26 | B58: 6238 | C58: 24 | D58: 6577 | E58: 26 | F58: 6423 | G58: 25 | H58: 6970.5 | I58: 24 | J58: 6967.5 | K58: 28 | L58: 7216 | O58: Acumulado 2016 | P58: =P57/P46-1 -> 0.47452326 | Q58: Dolar | S58: =R57/R46-1 -> 0.24121286 | T58: Reais
A59: 27 | B59: 6325 | C59: 25 | D59: 6714 | E59: 27 | F59: 6426 | G59: 26 | H59: 6965 | I59: 27 | J59: 6892 | K59: 29 | L59: 7157
A60: 28 | B60: 6283 | C60: 29 | D60: 6797 | E60: 28 | F60: 6405 | G60: 27 | H60: 6831.5 | I60: 28 | J60: 6800
A61: 31 | B61: 6347 | C61: 30 | D61: 6755 | E61: 29 | F61: 6485 | G61: 30 | H61: 6823 | I61: 29 | J61: 6756.5
C62: 31 | D62: 6792 | G62: 31 | H62: 6802 | I62: 30 | J62: 6761
A64: =B65/L28-1 -> 0.048972555 | C64: =D65/B65-1 -> 0.083570139 | E64: =F65/D65-1 -> 0.016202458 | G64: =H65/F65-1 -> 0.03253679 | I64: =J65/H65-1 -> 0.0041459786 | K64: =L65/J65-1 -> -0.0035763011
A65: MM | B65: =AVERAGE(B41:B63) -> 5978.5952 | C65: MM | D65: =AVERAGE(D41:D63) -> 6478.2273 | E65: MM | F65: =AVERAGE(F41:F61) -> 6583.1905 | G65: MM | H65: =AVERAGE(H41:H63) -> 6797.3864 | I65: MM | J65: =AVERAGE(J41:J62) -> 6825.5682 | K65: MM | L65: =AVERAGE(L41:L61) -> 6801.1579
A67: MM R$ | B67: =B65*A68 -> 19181.725 | C67: MM R$ | D67: =D65*C68 -> 20407.712 | E67: MM R$ | F67: =F65*E68 -> 20612.628 | G67: MM R$ | H67: =H65*G68 -> 21693.859 | I67: MM R$ | J67: =J65*I68 -> 22252.035 | K67: MM R$ | L67: =L65*K68 -> 22409.135
A68: 3.2084 | B68: =B67/L29-1 -> 0.022240849 | C68: 3.1502 | D68: =D67/L29-1 -> 0.087576661 | E68: 3.1311 | F68: =F67/D67-1 -> 0.010041113 | G68: 3.1915 | H68: =H67/F67-1 -> 0.052454781 | I68: 3.2601 | J68: =J67/H67-1 -> 0.02572969 | K68: 3.2949 | L68: =L67/J67-1 -> 0.0070600428
E71: VARIAÇÃO COBRE LME - REAIS

Sheet Cotação Média LME

Sheet Dolar Medio
B1: Ano 2013 | C1: Ano 2014 | D1: Ano 2015 | E1: Ano 2016
A2: Janeiro | B2: ='2013'!A31 -> 2.0331 | C2: ='2014'!A31 -> 2.3809 | D2: ='2015'!A31 -> 2.6371 | E2: ='2016'!A29 -> 4.0395
A3: Fevereiro | B3: ='2013'!C31 -> 1.9717 | C3: ='2014'!C31 -> 2.3857 | D3: ='2015'!$C$31 -> 2.81649 | E3: ='2016'!C29 -> 3.9676
A4: Março | B4: ='2013'!E31 -> 1.9854 | C4: ='2014'!E31 -> 2.3258 | D4: ='2015'!$E$31 -> 3.1422 | E4: ='2016'!E29 -> 3.6933
A5: Abril | B5: ='2013'!G31 -> 2.001 | C5: ='2014'!G31 -> 2.2331 | D5: ='2015'!$G$31 -> 3.0525 | E5: ='2016'!G29 -> 3.5659 | M5: Ano 2015 | N5: =D13/C13-1 -> 0.46595253
A6: Maio | B6: ='2013'!I31 -> 2.034 | C6: ='2014'!I31 -> 2.2211 | D6: ='2015'!I31 -> 3.054 | E6: 3.54
A7: Junho | B7: ='2013'!K31 -> 2.17 | C7: ='2014'!K31 -> 2.2342 | D7: ='2015'!K31 -> 3.1145 | E7: ='2016'!K29 -> 3.43 | M7: Ano 2016 | N7: =E11/D13-1 -> -0.17622453
A8: Julho | B8: ='2013'!A62 -> 2.25268 | C8: ='2014'!A85 -> 2.2249 | D8: ='2015'!A85 -> 3.2188 | E8: 3.27
A9: Agosto | B9: ='2013'!C62 -> 2.3395 | C9: ='2014'!C85 -> 2.2684 | D9: ='2015'!$C$85 -> 3.5069 | E9: 3.29
A10: Setembro | B10: ='2013'!E62 -> 2.2711 | C10: ='2014'!E85 -> 2.335 | D10: ='2015'!E85 -> 3.8957 | E10: ='2016'!E83 -> 3.2564
A11: Outubro | B11: ='2013'!G62 -> 2.1868 | C11: ='2014'!G85 -> 2.4507 | D11: ='2015'!G85 -> 3.8724 | E11: ='2016'!G83 -> 3.1904
A12: Novembro | B12: ='2013'!I62 -> 2.2976 | C12: ='2014'!I85 -> 2.56 | D12: ='2015'!I85 -> 3.7782 | E12: ='2016'!I83 -> 3.33
A13: Dezembro | B13: ='2013'!$K$62 -> 2.3478 | C13: ='2014'!K85 -> 2.6419 | D13: ='2015'!K85 -> 3.8729
C14: =C13/B13-1 -> 0.12526621 | D14: =D13/C13-1 -> 0.46595253 | E14: =E12/D13-1 -> -0.14017919
A88: Mês | B88: Valor
A89: 41275 | B89: 2.0331
A90: 41306 | B90: 1.9717
A91: 41334 | B91: 1.9854
A92: 41365 | B92: 2.001
A93: 41395 | B93: 2.034
A94: 41426 | B94: 2.17
A95: 41456 | B95: 2.25268
A96: 41487 | B96: 2.3395
A97: 41518 | B97: 2.2711
A98: 41548 | B98: 2.1868
A99: 41579 | B99: 2.2976
A100: 41609 | B100: 2.3478
... A133: 42614 | B133: 3.27

Sheet LME Média
A1: MÉDIAS
C2: US$ | D2: Var (%) | E2: R$ | F2: Var (%)
A3: 41275 | C3: 8049.2455 | D3: =C3/7962.58-1 -> 0.010884092 | E3: 16364.921 | F3: =E3/16546.24-1 -> -0.010958324
A4: 41306 | C4: 8070.475 | D4: =C4/C3-1 -> 0.0026374578 | E4: 15912.556 | F4: =E4/E3-1 -> -0.027642381
A5: 41334 | C5: 7662.4 | D5: =C5/C4-1 -> -0.050563938 | E5: 15212.929 | F5: =E5/E4-1 -> -0.043966954
A6: 41365 | C6: 7203.3571 | D6: =C6/C5-1 -> -0.059908496 | E6: 14413.918 | F6: =E6/E5-1 -> -0.052521859
A7: 41395 | C7: 7229.1429 | D7: =C7/C6-1 -> 0.0035796801 | E7: 14704.077 | F7: =E7/E6-1 -> 0.020130469
A8: 41426 | C8: 7004.05 | D8: =C8/C7-1 -> -0.031136867 | E8: 15198.789 | F8: =E8/E7-1 -> 0.033644542
A9: 41456 | C9: 6896.9773 | D9: =C9/C8-1 -> -0.015287259 | E9: 15536.683 | F9: =E9/E8-1 -> 0.022231658
A10: 41487 | C10: 7182.2619 | D10: =C10/C9-1 -> 0.041363719 | E10: 16802.902 | F10: =E10/E9-1 -> 0.081498669
A11: 41518 | C11: 7161.4286 | D11: =C11/C10-1 -> -0.0029006647 | E11: 16264.32 | F11: =E11/E10-1 -> -0.032052874
A12: 41548 | C12: 7188.7826 | D12: =C12/C11-1 -> 0.0038196342 | E12: 15720.43 | F12: =E12/E11-1 -> -0.033440722
A13: 41579 | C13: 7066.4048 | D13: =C13/C12-1 -> -0.017023445 | E13: 16235.772 | F13: =E13/E12-1 -> 0.032781659
A14: 41609 | C14: 7202.95 | D14: =C14/C13-1 -> 0.019323156 | E14: 16911.086 | F14: =E14/E13-1 -> 0.041594231
A15: 41640 | C15: ='2014'!B28 -> 7294.8864 | D15: =C15/C14-1 -> 0.01276371 | E15: ='2014'!B30 -> 17368.395 | F15: =E15/E14-1 -> 0.027041961
A16: 41671 | C16: ='2014'!D28 -> 7152.15 | D16: =C16/C15-1 -> -0.019566633 | E16: ='2014'!D30 -> 17062.884 | F16: =E16/E15-1 -> -0.017590036
A17: 41699 | C17: ='2014'!P17 -> 6667.8095 | D17: =C17/C16-1 -> -0.067719564 | E17: ='2014'!R17 -> 15507.991 | F17: =E17/E16-1 -> -0.0911272
A18: 41730 | C18: ='2014'!$P$18 -> 6670.825 | D18: =C18/C17-1 -> 0.0004522439 | E18: ='2014'!$R$18 -> 14896.619 | F18: =E18/E17-1 -> -0.039423035
A19: 41760 | C19: ='2015'!$P$19 -> 6883.875 | D19: =C19/C18-1 -> 0.031937579 | E19: ='2015'!$R$19 -> 15289.775 | F19: =E19/E18-1 -> 0.02639226
A20: 41791 | C20: ='2015'!$P$20 -> 6806.0952 | D20: =C20/C19-1 -> -0.011298834 | E20: ='2015'!$R$20 -> 15206.178 | F20: =E20/E19-1 -> -0.0054674959
A21: 41821 | C21: ='2015'!$P$21 -> 7104.8478 | D21: =C21/C20-1 -> 0.043894859 | E21: ='2015'!$R$21 -> 15807.576 | F21: =E21/E20-1 -> 0.03954958
A22: 41852 | C22: ='2015'!$P$22 -> 7000.55 | D22: =C22/C21-1 -> -0.014679811 | E22: ='2015'!R22 -> 15880.048 | F22: =E22/E21-1 -> 0.0045846177
A23: 41883 | C23: ='2015'!$P$23 -> 6872.2273 | D23: =C23/C22-1 -> -0.018330378 | E23: ='2015'!R23 -> 16046.651 | F23: =E23/E22-1 -> 0.010491345
A24: 41913 | C24: ='2015'!$P$24 -> 6739.1957 | D24: =C24/C23-1 -> -0.019357861 | E24: ='2015'!R24 -> 16515.747 | F24: =E24/E23-1 -> 0.029233272
A25: 41944 | C25: ='2015'!$P$25 -> 6701.135 | D25: =C25/C24-1 -> -0.005647655 | E25: ='2015'!R25 -> 17154.906 | F25: =E25/E24-1 -> 0.038699965
A26: 41974 | C26: ='2015'!$P$26 -> 6422.9524 | D26: =C26/C25-1 -> -0.041512762 | E26: ='2015'!R26 -> 16968.798 | F26: =E26/E25-1 -> -0.010848658
A27: 42005 | C27: ='2015'!$P$27 -> 5791.175 | D27: =C27/C26-1 -> -0.098362458 | E27: ='2015'!R27 -> 15271.908 | F27: =E27/E26-1 -> -0.10000062
A28: 42036 | C28: ='2015'!$P$28 -> 5702.075 | D28: =C28/C27-1 -> -0.015385479 | E28: ='2015'!R28 -> 16059.837 | F28: =E28/E27-1 -> 0.051593399
A29: 42064 | C29: ='2015'!$P$29 -> 5919.9048 | D29: =C29/C28-1 -> 0.038201841 | E29: ='2015'!R29 -> 18601.525 | F29: =E29/E28-1 -> 0.15826359
A30: 42095 | C30: ='2015'!$P$30 -> 6028.4775 | D30: =C30/C29-1 -> 0.018340285 | E30: ='2015'!R30 -> 18401.928 | F30: =E30/E29-1 -> -0.010730151
A31: 42125 | C31: ='2015'!$P$31 -> 6300.6053 | D31: =C31/C30-1 -> 0.04514038 | E31: ='2015'!R31 -> 19242.048 | F31: =E31/E30-1 -> 0.045653962
A32: 42156 | C32: ='2015'!$P$32 -> 5833.6136 | D32: =C32/C31-1 -> -0.074118534 | E32: ='2015'!R32 -> 18168.79 | F32: =E32/E31-1 -> -0.055776744
A33: 42186 | C33: ='2015'!$P$56 -> 5456.913 | D33: =C33/C32-1 -> -0.064574142 | E33: ='2015'!R56 -> 17564.712 | F33: =E33/E32-1 -> -0.033248113
A34: 42217 | C34: ='2015'!$P$57 -> 5088.925 | D34: =C34/C33-1 -> -0.067435204 | E34: ='2015'!R57 -> 17846.351 | F34: =E34/E33-1 -> 0.016034387
A35: 42248 | C35: ='2015'!P58 -> 5208.0909 | D35: =C35/C34-1 -> 0.023416716 | E35: ='2015'!R58 -> 20289.16 | F35: =E35/E34-1 -> 0.13688001
A36: 42278 | C36: ='2015'!P59 -> 5222.6136 | D36: =C36/C35-1 -> 0.0027884934 | E36: ='2015'!R59 -> 20224.049 | F36: =E36/E35-1 -> -0.0032091378
A37: 42309 | C37: ='2015'!P60 -> 4808.2381 | D37: =C37/C36-1 -> -0.079342561 | E37: ='2015'!R60 -> 18166.485 | F37: =E37/E36-1 -> -0.10173847
A38: 42339 | C38: ='2015'!L82 -> 4629 | D38: =C38/C37-1 -> -0.037277292 | E38: ='2015'!L84 -> 17927.654 | F38: =E38/E37-1 -> -0.013146796
A39: 42370 | C39: ='2016'!B27 -> 4462.75 | D39: =C39/C38-1 -> -0.035914884 | E39: ='2016'!B28 -> 18027.279 | F39: =E39/E38-1 -> 0.0055570307
A40: 42401 | C40: ='2016'!D27 -> 4595.4762 | D40: =C40/C39-1 -> 0.029740898 | E40: ='2016'!D28 -> 18233.011 | F40: =E40/E39-1 -> 0.0114123
A41: 42430 | C41: 4947.55 | D41: =C41/C40-1 -> 0.076613129 | E41: 18272.78 | F41: =E41/E40-1 -> 0.0021811354
A42: 42461 | C42: ='2016'!H27 -> 4851.3571 | D42: =C42/C41-1 -> -0.019442524 | E42: ='2016'!H28 -> 17299.454 | F42: =E42/E41-1 -> -0.053266419
A43: 42491 | C43: ='2016'!P66 -> 4708.35 | D43: =C43/C42-1 -> -0.02947776 | E43: ='2016'!R66 -> 16669.913 | F43: =E43/E42-1 -> -0.036390816
A44: 42522 | C44: ='2016'!L27 -> 4635.1818 | D44: =C44/C43-1 -> -0.01554009 | E44: ='2016'!L28 -> 15898.674 | F44: =E44/E43-1 -> -0.04626536
A45: 42552 | C45: ='2016'!B80 -> 4855.4762 | D45: =C45/C44-1 -> 0.047526587 | E45: ='2016'!B82 -> 15885.176 | F45: =E45/E44-1 -> -0.00084898476
A46: 42583 | C46: ='2016'!D80 -> 4757.9659 | D46: =C46/C45-1 -> -0.020082537 | E46: ='2016'!D82 -> 15271.167 | F46: =E46/E45-1 -> -0.038652926
A47: 42614 | C47: ='2016'!F80 -> 4705.625 | D47: =C47/C46-1 -> -0.01100069 | E47: ='2016'!F82 -> 15323.397 | F47: =E47/E46-1 -> 0.0034201621
A48: 42644 | C48: 4738.18 | D48: =C48/C47-1 -> 0.0069183158 | E48: 15116.67 | F48: =E48/E47-1 -> -0.013490954
A49: 42675 | C49: ='2016'!J80 -> 5443.25 | D49: =C49/C48-1 -> 0.14880608 | E49: ='2016'!J82 -> 18126.022 | F49: =E49/E48-1 -> 0.19907509

Sheet Cotação Dolar
A1: Data | B1: Valor
A2: 42583 | B2: 3.2662
A3: 42584 | B3: 3.249
A4: 42585 | B4: 3.2733
A5: 42586 | B5: 3.2183
A6: 42587 | B6: 3.1859
A7: 42590 | B7: 3.1771
A8: 42591 | B8: 3.1503
A9: 42592 | B9: 3.1302
A10: 42593 | B10: 3.1364
A11: 42594 | B11: 3.1602
A12: 42597 | B12: 3.1672
A13: 42598 | B13: 3.1749
... A24: 42613 | B24: 3.2403
A25: Média Mensal | B25: =AVERAGE(B2:B24) -> 3.2096609
A27: 42614 | B27: 3.2472
A28: 42615 | B28: 3.2431
A29: 42618 | B29: 3.2721
A30: 42619 | B30: 3.2452
A31: 42620 | B31: 3.2452
A32: 42621 | B32: 3.1934
A33: 42622 | B33: 3.2638
A34: 42625 | B34: 3.2854
A35: 42626 | B35: 3.2972
A36: 42627 | B36: 3.3262
A37: 42628 | B37: 3.3326
A38: 42629 | B38: 3.3004
... A48: 42643 | B48: 3.2462
A49: Média Mensal | B49: =AVERAGE(B27:B48) -> 3.2558636
A51: 42646 | B51: 3.2338
A52: 42647 | B52: 3.2203
A53: 42648 | B53: 3.2359
A54: 42648 | B54: 3.2203
A55: 42649 | B55: 3.2359
A56: 42650 | B56: 3.231
A57: 42653 | B57: 3.2134
A58: 42654 | B58: 3.2125
A59: 42655 | B59: feriado
A60: 42656 | B60: 3.2136
A61: 42657 | B61: 3.2087
A62: 42660 | B62: 3.1864
A63: 42661 | B63: 3.1963
A64: 42662 | B64: 3.1874
A65: 42663 | B65: 3.18
A66: 42664 | B66: 3.1605
A67: 42667 | B67: 3.1593
A68: 42668 | B68: 3.1311
A69: 42669 | B69: 3.1193
A70: 42670 | B70: 3.1219
A71: 42671 | B71: 3.1429
A72: 42674 | B72: 3.1815
A73: Média Mensal | B73: =AVERAGE(B51:B72) -> 3.1900952
A75: 42675 | B75: 3.1811
A76: 42676 | B76: feriado
A77: 42677 | B77: 3.2053
A78: 42678 | B78: 3.231
A79: 42681 | B79: 3.2449
A80: 42682 | B80: 3.2024
A81: 42683 | B81: 3.2024
A82: 42684 | B82: 3.2258
A83: 42685 | B83: 3.3104
A84: 42688 | B84: 3.4377
A85: 42689 | B85: feriado
A86: 42690 | B86: 3.4446
A87: 42691 | B87: 3.4183
A88: 42692 | B88: 3.4052
A89: 42695 | B89: 3.3917
A90: Média Mensal | B90: =AVERAGE(B75:B89) -> 3.3000615

Sheet 2018
A1: Cobre LME Prices 2018 US$/Ton | O1: MÉDIAS
A2: Janeiro 2018 | C2: Fevereiro 2018 | E2: Março 2018 | G2: Abril 2018 | I2: Maio 2018 | K2: Junho 2018 | P2: US$ | Q2: Var (%) | R2: R$ | S2: Var Mês (%) | T2: Acumulado/Ano
B3: Cash | D3: Cash | F3: Cash | H3: Cash | J3: Cash | L3: Cash | O3: 41275 | P3: 8049.2455 | Q3: 0.010884092 | R3: 16364.921 | S3: -0.010958324
A4: 2 | B4: 7181 | C4: 1 | D4: 7027 | E4: 1 | F4: 6852 | G4: 3 | H4: 6756 | I4: 1 | J4: 6777.5 | K4: 1 | L4: 6814 | O4: 41306 | P4: 8070.475 | Q4: 0.0026374578 | R4: 15912.556 | S4: -0.027642381
A5: 3 | B5: 7115.5 | C5: 2 | D5: 7066 | E5: 2 | F5: 6883 | G5: 4 | H5: 6625 | I5: 2 | J5: 6785 | K5: 4 | L5: 6935 | O5: 41334 | P5: 7662.4 | Q5: -0.050563938 | R5: 15212.929 | S5: -0.043966954
A6: 4 | B6: 7202.5 | C6: 5 | D6: 7050 | E6: 5 | F6: 6850 | G6: 5 | H6: 6767 | I6: 3 | J6: 6837 | K6: 5 | L6: 6971 | O6: 41365 | P6: 7203.3571 | Q6: -0.059908496 | R6: 14413.918 | S6: -0.052521859
A7: 5 | B7: 7097 | C7: 6 | D7: 7060 | E7: 6 | F7: 6968.5 | G7: 6 | H7: 6703 | I7: 4 | J7: 6783 | K7: 6 | L7: 7147 | O7: 41395 | P7: 7229.1429 | Q7: 0.0035796801 | R7: 14704.077 | S7: 0.020130469
A8: 8 | B8: 7084.5 | C8: 7 | D8: 7006 | E8: 7 | F8: 6873 | G8: 9 | H8: 6767 | I8: 8 | J8: 6722 | K8: 7 | L8: 7245.5 | O8: 41426 | P8: 7004.05 | Q8: -0.031136867 | R8: 15198.789 | S8: 0.033644542
A9: 9 | B9: 7092 | C9: 8 | D9: 6838 | E9: 8 | F9: 6830 | G9: 10 | H9: 6888 | I9: 9 | J9: 6786 | K9: 8 | L9: 7262.5 | N9: =L8/B25 -> 1.0204211 | O9: 41456 | P9: 6896.9773 | Q9: -0.015287259 | R9: 15536.683 | S9: 0.022231658
A10: 10 | B10: 7140.5 | C10: 9 | D10: 6755 | E10: 9 | F10: 6808 | G10: 11 | H10: 6930.5 | I10: 10 | J10: 6862 | K10: 11 | L10: 7223.5 | O10: 41487 | P10: 7182.2619 | Q10: 0.041363719 | R10: 16802.902 | S10: 0.081498669
A11: 11 | B11: 7123 | C11: 12 | D11: 6786.5 | E11: 12 | F11: 6857 | G11: 12 | H11: 6756 | I11: 11 | J11: 6869 | K11: 12 | L11: 7200.5 | O11: 41518 | P11: 7161.4286 | Q11: -0.0029006647 | R11: 16264.32 | S11: -0.032052874
A12: 12 | B12: 7070.5 | C12: 13 | D12: 6908 | E12: 13 | F12: 6883 | G12: 13 | H12: 6830 | I12: 14 | J12: 6828 | K12: 13 | L12: 7201.5 | O12: 41548 | P12: 7188.7826 | Q12: 0.0038196342 | R12: 15720.43 | S12: -0.033440722
A13: 15 | B13: 7180 | C13: 14 | D13: 6962 | E13: 14 | F13: 7015 | G13: 16 | H13: 6811.5 | I13: 15 | J13: 6822.5 | K13: 14 | L13: 7197 | O13: 41579 | P13: 7066.4048 | Q13: -0.017023445 | R13: 16235.772 | S13: 0.032781659
A14: 16 | B14: 7023 | C14: 15 | D14: 7098 | E14: 15 | F14: 6885.5 | G14: 17 | H14: 6784 | I14: 16 | J14: 6773.5 | K14: 15 | L14: 7136 | O14: 41609 | P14: 7202.95 | Q14: 0.019323156 | R14: 16911.086 | S14: 0.041594231
A15: 17 | B15: 7047 | C15: 16 | D15: 7159 | E15: 16 | F15: 6923 | G15: 18 | H15: 6936 | I15: 17 | J15: 6838 | K15: 18 | L15: 6987 | O15: 41640 | P15: 7294.8864 | Q15: 0.01276371 | R15: 17368.395 | S15: 0.027041961 | T15: 0.027041961
A16: 18 | B16: 7047 | C16: 19 | D16: 7093 | E16: 19 | F16: 6791.5 | G16: 19 | H16: 6942 | I16: 18 | J16: 6783.5 | K16: 19 | L16: 6820 | O16: 41671 | P16: 7152.15 | Q16: -0.019566633 | R16: 17062.884 | S16: -0.017590036 | T16: 0.0089762565
A17: 19 | B17: 7079 | C17: 20 | D17: 7027 | E17: 20 | F17: 6784 | G17: 20 | H17: 6939 | I17: 21 | J17: 6861 | K17: 20 | L17: 6819 | O17: 41699 | P17: 6667.8095 | Q17: -0.067719564 | R17: 15507.991 | S17: -0.0911272 | T17: -0.082968925
A18: 22 | B18: 7049 | C18: 21 | D18: 7003 | E18: 21 | F18: 6675 | G18: 23 | H18: 6923 | I18: 22 | J18: 6931.5 | K18: 21 | L18: 6801 | O18: 41730 | P18: 6670.825 | Q18: 0.0004522439 | R18: 14896.619 | S18: -0.039423035 | T18: -0.11912107
A19: 23 | B19: 6905 | C19: 22 | D19: 7032 | E19: 22 | F19: 6746.5 | G19: 24 | H19: 6987 | I19: 23 | J19: 6800 | K19: 22 | L19: 6811 | O19: 41760 | P19: 6883.875 | Q19: 0.031937579 | R19: 15289.775 | S19: 0.02639226 | T19: -0.095872687
A20: 24 | B20: 6943 | C20: 23 | D20: 7073.5 | E20: 23 | F20: 6658 | G20: 25 | H20: 6960.5 | I20: 24 | J20: 6835 | K20: 25 | L20: 6783 | O20: 41791 | P20: 6806.0952 | Q20: -0.011298834 | R20: 15206.178 | S20: -0.0054674959 | T20: -0.100816
A21: 25 | B21: 7112 | C21: 26 | D21: 7111 | E21: 26 | F21: 6500 | G21: 26 | H21: 6885.5 | I21: 25 | J21: 6886 | K21: 26 | L21: 6712 | O21: 41821 | P21: 7104.8478 | Q21: 0.043894859 | R21: 15807.576 | S21: 0.03954958 | T21: -0.06525365
A22: 26 | B22: 7063.5 | C22: 27 | D22: 7028 | E22: 27 | F22: 6641.5 | G22: 27 | H22: 6797 | I22: 29 | J22: 6840.5 | K22: 27 | L22: 6688 | O22: 41852 | P22: 7000.55 | Q22: -0.014679811 | R22: 15880.048 | S22: 0.0045846177 | T22: -0.060968195
A23: 29 | B23: 7062 | C23: 28 | D23: 6953 | E23: 28 | F23: 6601.5 | G23: 30 | H23: 6783 | I23: 30 | J23: 6810 | K23: 28 | L23: 6650 | O23: 41883 | P23: 6872.2273 | Q23: -0.018330378 | R23: 16046.651 | S23: 0.010491345 | T23: -0.051116488
A24: 30 | B24: 7049 | E24: 29 | F24: 6685 | I24: 31 | J24: 6825 | K24: 29 | L24: 6646 | O24: 41913 | P24: 6739.1957 | Q24: -0.019357861 | R24: 16515.747 | S24: 0.029233272 | T24: -0.023377518
A25: 31 | B25: 7100.5 | E25: 30
O26: 41944 | P26: 6701.135 | Q26: -0.005647655 | R26: 17154.906 | S26: 0.038699965 | T26: 0.014417737
A27: =B28/'2017'!L65-1 -> 0.041042652 | C27: =D28/B28-1 -> -0.011086466 | E27: =F28/D28-1 -> -0.029426447 | G27: =H28/F28-1 -> 0.0062962911 | I27: =J28/H28-1 -> -0.0024618836 | K27: =L28/J28-1 -> 0.019507036 | O27: 41974 | P27: 6422.9524 | Q27: -0.041512762 | R27: 16968.798 | S27: -0.010848658 | T27: 0.0034126658
A28: MM | B28: =AVERAGE(B4:B25) -> 7080.2955 | C28: MM | D28: =AVERAGE(D4:D23) -> 7001.8 | E28: MM | F28: =AVERAGE(F4:F25) -> 6795.7619 | G28: MM | H28: =AVERAGE(H4:H24) -> 6838.55 | I28: MM | J28: =AVERAGE(J4:J25) -> 6821.7143 | K28: MM | L28: =AVERAGE(L4:L24) -> 6954.7857 | O28: 42005 | P28: 5791.175 | Q28: -0.098362458 | R28: 15271.908 | S28: -0.10000062 | T28: -0.10000062
A29: MM R$ | B29: =B28*A30 -> 22736.245 | C29: MM R$ | D29: =D28*C30 -> 22711.038 | E29: MM R$ | F29: =F28*E30 -> 22341.747 | G29: MM R$ | H29: =H28*G30 -> 23302.359 | I29: MM R$ | J29: =J28*I30 -> 24721.21 | K29: MM R$ | L29: =L28*K30 -> 26117.307 | O29: 42036 | P29: 5702.075 | Q29: -0.015385479 | R29: 16059.837 | S29: 0.051593399 | T29: -0.053566592
A30: 3.2112 | B30: =B29/'2017'!L67-1 -> 0.014597155 | C30: 3.2436 | D30: =D29/B29-1 -> -0.0011086388 | E30: 3.2876 | F30: =F29/D29-1 -> -0.016260447 | G30: 3.4075 | H30: =H29/F29-1 -> 0.042996293 | I30: 3.6239 | J30: =J29/H29-1 -> 0.06088874 | K30: 3.7553 | L30: =L29/J29-1 -> 0.056473626 | O30: 42064 | P30: 5919.9048 | Q30: 0.038201841 | R30: 18601.525 | S30: 0.15826359 | T30: 0.096219358
A31: Cobre LME Prices 2018 US$/Ton | O31: MÉDIAS
A32: Julho 2018 | C32: Agosto 2018 | E32: Setembro 2018 | G32: Outubro 2018 | I32: Novembro 2018 | K32: Dezembro 2018 | O32: 42125 | P32: 6300.6053 | Q32: 0.04514038 | R32: 19242.048 | S32: 0.045653962 | T32: 0.13396651
B33: Cash | D33: Cash | F33: Cash | H33: Cash | J33: Cash | L33: Cash | O33: 42156 | P33: 5833.6136 | Q33: -0.074118534 | R33: 18168.79 | S33: -0.055776744 | T33: 0.070717548
A34: Média | B34: #DIV/0! | C34: Média | D34: #DIV/0! | E34: Média | F34: #DIV/0! | G34: Média | H34: #DIV/0! | I34: Média | J34: #DIV/0! | K34: Média | L34: #DIV/0! | O34: 42675 | T34: #DIV/0!
A35: MM | B35: #DIV/0! | C35: MM | D35: #DIV/0! | E35: MM | F35: #DIV/0! | G35: MM | H35: #DIV/0! | I35: MM | J35: #DIV/0! | K35: MM | L35: #DIV/0! | O35: 42705 | T35: #DIV/0!
A36: #DIV/0! | C36: #DIV/0! | E36: #DIV/0! | G36: #DIV/0! | I36: #DIV/0! | K36: #DIV/0! | O36: 42736 | T36: #DIV/0!
A37: MM R$ | B37: #DIV/0! | C37: MM R$ | D37: #DIV/0! | E37: MM R$ | F37: #DIV/0! | G37: MM R$ | H37: #DIV/0! | I37: MM R$ | J37: #DIV/0! | K37: MM R$ | L37: #DIV/0! | O37: 42767 | T37: #DIV/0!
B38: #DIV/0! | D38: #DIV/0! | F38: #DIV/0! | H38: #DIV/0! | J38: #DIV/0! | L38: #DIV/0! | O38: 42795 | T38: #DIV/0!
A39: Julho 2016 | C39: Agosto 2016 | E39: Setembro 2016 | G39: Outubro 2016 | I39: Novembro 2016 | K39: Dezembro 2016 | O39: 42826 | T39: #DIV/0!
B40: Cash | D40: Cash | F40: Cash | H40: Cash | J40: Cash | L40: Cash | O40: 42856 | T40: #DIV/0!
A41: 2 | B41: 6595 | C41: 1 | D41: 6137 | E41: 3 | F41: 5951 | G41: 1 | H41: 6172 | I41: 1 | J41: 6070 | K41: 3 | L41: 6307 | O41: 42186 | P41: 5456.913 | Q41: -0.064574142 | R41: 17564.712 | S41: =R41/R33-1 -> -0.033248113 | T41: 0.03511821
A42: 3 | B42: 6584.5 | C42: 2 | D42: 6063 | E42: 4 | F42: 5823 | G42: 2 | H42: 6274 | I42: 2 | J42: 6255 | K42: 4 | L42: 6278 | O42: 42217 | P42: 5088.925 | Q42: -0.067435204 | R42: 17846.351 | S42: =R42/R41-1 -> 0.016034387 | T42: 0.051715696
A43: 4 | B43: 6459 | C43: 3 | D43: 6167 | E43: 5 | F43: 5850 | G43: 3 | H43: 6275 | I43: 5 | J43: 6239 | K43: 5 | L43: 6162 | O43: 42248 | P43: 5208.0909 | Q43: 0.023416716 | R43: 20289.16 | S43: =R43/R42-1 -> 0.13688001 | T43: 0.19567455
A44: 5 | B44: 6399.5 | C44: 6 | D44: 6040 | E44: 6 | F44: 5940 | G44: 4 | H44: 6310 | I44: 6 | J44: 6205 | K44: 6 | L44: 6112 | O44: 42278 | P44: 5222.6136 | Q44: 0.0027884934 | R44: 20224.049 | S44: =R44/R43-1 -> -0.0032091378 | T44: 0.19183746
A45: 6 | B45: 6326 | C45: 7 | D45: 6132 | E45: 7 | F45: 5883 | G45: 5 | H45: 6182.5 | I45: 7 | J45: 6210 | K45: 7 | L45: 6173 | O45: 42309 | P45: 4808.2381 | Q45: -0.079342561 | R45: 18166.485 | S45: =R45/R44-1 -> -0.10173847 | T45: 0.07058174
A46: 9 | B46: 6383 | C46: 8 | D46: 6113 | E46: 10 | F46: 5840.5 | G46: 8 | H46: 6169 | I46: 8 | J46: 6137 | K46: 10 | L46: 6112 | O46: 42339 | P46: 4629 | Q46: -0.037277292 | R46: 17927.654 | S46: =R46/R45-1 -> -0.013146796 | T46: =R46/R27-1 -> 0.05650702
A47: 10 | B47: 6308 | C47: 9 | D47: 6247 | E47: 11 | F47: 5849 | G47: 9 | H47: 6219 | I47: 9 | J47: 6088 | K47: 11 | L47: 6163 | O47: 42370 | P47: =B28 -> 7080.2955 | Q47: =P47/P46-1 -> 0.52955184 | R47: =B29 -> 22736.245 | S47: =R47/R46-1 -> 0.26822197 | T47: =R47/$R$46-1 -> 0.26822197
A48: 11 | B48: 6182 | C48: 10 | D48: 6120 | E48: 12 | F48: 5891 | G48: 10 | H48: 6294 | I48: 12 | J48: 6083.5 | K48: 12 | L48: 6151 | O48: 42401 | P48: =D28 -> 7001.8 | Q48: =P48/P47-1 -> -0.011086466 | R48: =D29 -> 22711.038 | S48: =R48/R47-1 -> -0.0011086388 | T48: =R48/$R$46-1 -> 0.26681597
A49: 12 | B49: 6173 | C49: 13 | D49: 6081 | E49: 13 | F49: 5991 | G49: 11 | H49: 6155 | I49: 13 | J49: 6130 | K49: 13 | L49: 6196 | O49: 42430 | P49: =F28 -> 6795.7619 | Q49: =P49/P48-1 -> -0.029426447 | R49: =F29 -> 22341.747 | S49: =R49/R48-1 -> -0.016260447 | T49: =R49/$R$46-1 -> 0.24621697
A50: 13 | B50: 6166 | C50: 14 | D50: 6059 | E50: 14 | F50: 5946.5 | G50: 12 | H50: 6325 | I50: 14 | J50: 6106 | K50: 14 | L50: 6104 | O50: 42461 | P50: =H28 -> 6838.55 | Q50: =P50/P49-1 -> 0.0062962911 | R50: =H29 -> 23302.359 | S50: =R50/R49-1 -> 0.042996293 | T50: =R50/$R$46-1 -> 0.29979968
A51: 16 | B51: 6143 | C51: 15 | D51: 5843 | E51: 17 | F51: 5860 | G51: 15 | H51: 6296 | I51: 15 | J51: 6188 | K51: 17 | L51: 6095.5 | O51: 42491 | P51: =J28 -> 6821.7143 | Q51: =P51/P50-1 -> -0.0024618836 | R51: =J29 -> 24721.21 | S51: =R51/R50-1 -> 0.06088874 | T51: =R51/R46-1 -> 0.37894285
A52: 17 | B52: 6141.5 | C52: 16 | D52: 5860 | E52: 18 | F52: 6003 | G52: 16 | H52: 6202 | I52: 16 | J52: 6181 | K52: 18 | L52: 6043 | O52: 42522 | P52: =L28 -> 6954.7857 | Q52: =P52/P51-1 -> 0.019507036 | R52: =L29 -> 26117.307 | S52: =R52/R51-1 -> 0.056473626 | T52: =R52/R46-1 -> 0.45681675
A53: 18 | B53: 6068 | C53: 17 | D53: 5844 | E53: 19 | F53: 6057 | G53: 17 | H53: 6249 | I53: 19 | J53: 6260 | K53: 19 | L53: 5987 | O53: 42552 | P53: =B65 -> 6248.1818 | Q53: =P53/P52-1 -> -0.10159966 | R53: =B67 -> 23951.78 | S53: =R53/R52-1 -> -0.082915387 | T53: =R53/R46-1 -> 0.33602423
A54: 19 | B54: 5982 | C54: 20 | D54: 5963 | E54: 20 | F54: 6057 | G54: 18 | H54: 6147 | I54: 20 | J54: 6262 | K54: 20 | L54: 6015 | O54: 42583 | P54: =D65 -> 6039.75 | Q54: =P54/P53-1 -> -0.033358795 | R54: =D67 -> 23734.406 | S54: =R54/R53-1 -> -0.0090755094 | T54: =R54/R46-1 -> 0.32389912
A55: 20 | B55: 6073 | C55: 21 | D55: 6025.5 | E55: 21 | F55: 6203 | G55: 19 | H55: 6191.5 | I55: 21 | J55: 6242 | K55: 21 | L55: 5987 | O55: 42614 | P55: =F65 -> 6020.025 | Q55: =P55/P54-1 -> -0.0032658637 | R55: =F67 -> 24823.573 | S55: =R55/R54-1 -> 0.045889816 | T55: =R55/R46-1 -> 0.38465261
A56: 23 | B56: 6153 | C56: 22 | D56: 6000 | E56: 24 | F56: 6320 | G56: 22 | H56: 6284 | I56: 22 | J56: 6246 | K56: 24 | L56: 5931.5 | O56: 42644 | P56: =H65 -> 6215.8913 | Q56: =P56/P55-1 -> 0.032535796 | R56: =H67 -> 23361.806 | S56: =R56/R55-1 -> -0.058886253 | T56: =R56/R46-1 -> 0.30311561
A57: 24 | B57: 6167 | C57: 23 | D57: 5910.5 | E57: 25 | F57: 6276 | G57: 23 | H57: 6167.5 | I57: 23 | J57: 6210 | K57: 27 | L57: 5990 | O57: 42675 | P57: =J65 -> 6193 | Q57: =P57/P56-1 -> -0.0036827067 | R57: =J67 -> 23446.698 | S57: =R57/R56-1 -> 0.0036337996 | T57: =R57/R46-1 -> 0.30785087
A58: 25 | B58: 6252 | C58: 24 | D58: 6001 | E58: 26 | F58: 6257.5 | G58: 24 | H58: 6215 | I58: 26 | J58: 6246 | K58: 28 | L58: 6018 | O58: Acumulado 2016 | P58: =P57/P46-1 -> 0.33786995 | Q58: Dolar | S58: =R57/R46-1 -> 0.30785087 | T58: Reais
A59: 26 | B59: 6255 | C59: 28 | D59: 6118 | E59: 27 | F59: 6222 | G59: 25 | H59: 6210 | I59: 27 | J59: 6169.5 | K59: 31 | L59: 5965
A60: 27 | B60: 6251.5 | C60: 29 | D60: 6065 | E60: 28 | F60: 6180 | G60: 26 | H60: 6159 | I60: 28 | J60: 6198
A61: 30 | B61: 6185 | C61: 30 | D61: 6066.5 | G61: 29 | H61: 6260 | I61: 29 | J61: 6282
A62: 31 | B62: 6213 | C62: 31 | D62: 6019 | G62: 30 | H62: 6136 | I62: 30 | J62: 6238
G63: 31 | H63: 6073
A64: =B65/L28-1 -> -0.10159966 | C64: =D65/B65-1 -> -0.033358795 | E64: =F65/D65-1 -> -0.0032658637 | G64: =H65/F65-1 -> 0.032535796 | I64: =J65/H65-1 -> -0.0036827067 | K64: =L65/J65-1 -> -0.015951796
A65: MM | B65: =AVERAGE(B41:B62) -> 6248.1818 | C65: MM | D65: =AVERAGE(D41:D63) -> 6039.75 | E65: MM | F65: =AVERAGE(F41:F60) -> 6020.025 | G65: MM | H65: =AVERAGE(H41:H63) -> 6215.8913 | I65: MM | J65: =AVERAGE(J41:J62) -> 6193 | K65: MM | L65: =AVERAGE(L41:L59) -> 6094.2105
A67: MM R$ | B67: =B65*A68 -> 23951.78 | C67: MM R$ | D67: =D65*C68 -> 23734.406 | E67: MM R$ | F67: =F65*E68 -> 24823.573 | G67: MM R$ | H67: =H65*G68 -> 23361.806 | I67: MM R$ | J67: =J65*I68 -> 23446.698 | K67: MM R$ | L67: =L65*K68 -> 23672.961
A68: 3.8334 | B68: =B67/L29-1 -> -0.082915387 | C68: 3.9297 | D68: =D67/B67-1 -> -0.0090755094 | E68: 4.1235 | F68: =F67/D67-1 -> 0.045889816 | G68: 3.7584 | H68: =H67/F67-1 -> -0.058886253 | I68: 3.786 | J68: =J67/H67-1 -> 0.0036337996 | K68: 3.8845 | L68: =L67/J67-1 -> 0.0096500919 | U68: 3.7584091 | V68: dólar medio banco central out/18
E71: VARIAÇÃO COBRE LME - REAIS

Sheet 2019
A1: Cobre LME Prices 2019 US$/Ton | O1: MÉDIAS
A2: Janeiro 2019 | C2: Fevereiro 2019 | E2: Março 2019 | G2: Abril 2019 | I2: Maio 2019 | K2: Junho 2019 | P2: US$ | Q2: Var (%) | R2: R$ | S2: Var Mês (%) | T2: Acumulado/Ano
B3: Cash | D3: Cash | F3: Cash | H3: Cash | J3: Cash | L3: Cash | O3: 41275 | P3: 8049.2455 | Q3: 0.010884092 | R3: 16364.921 | S3: -0.010958324
A4: 2 | B4: 5839 | C4: 1 | D4: 6097.5 | E4: 1 | F4: 6572 | G4: 1 | H4: 6498 | I4: 1 | J4: 6398 | K4: 3 | L4: 5796 | O4: 41306 | P4: 8070.475 | Q4: 0.0026374578 | R4: 15912.556 | S4: -0.027642381
A5: 3 | B5: 5811 | C5: 4 | D5: 6076.5 | E5: 2 | F5: 6420 | G5: 2 | H5: 6431 | I5: 2 | J5: 6214 | K5: 4 | L5: 5804 | O5: 41334 | P5: 7662.4 | Q5: -0.050563938 | R5: 15212.929 | S5: -0.043966954
A6: 4 | B6: 5840 | C6: 5 | D6: 6174 | E6: 5 | F6: 6553.5 | G6: 3 | H6: 6483 | I6: 3 | J6: 6180 | K6: 5 | L6: 5832.5 | O6: 41365 | P6: 7203.3571 | Q6: -0.059908496 | R6: 14413.918 | S6: -0.052521859
A7: 7 | B7: 5889.5 | C7: 6 | D7: 6210 | E7: 6 | F7: 6505 | G7: 4 | H7: 6444 | I7: 7 | J7: 6174 | K7: 6 | L7: 5805 | O7: 41395 | P7: 7229.1429 | Q7: 0.0035796801 | R7: 14704.077 | S7: 0.020130469
A8: 8 | B8: 5904.5 | C8: 7 | D8: 6227 | E8: 7 | F8: 6458 | G8: 5 | H8: 6419 | I8: 8 | J8: 6103 | K8: 7 | L8: 5770 | O8: 41426 | P8: 7004.05 | Q8: -0.031136867 | R8: 15198.789 | S8: 0.033644542
A9: 9 | B9: 5964 | C9: 8 | D9: 6207 | E9: 8 | F9: 6398.5 | G9: 8 | H9: 6432.5 | I9: 9 | J9: 6112 | K9: 10 | L9: 5788 | O9: 41456 | P9: 6896.9773 | Q9: -0.015287259 | R9: 15536.683 | S9: 0.022231658
A10: 10 | B10: 5908.5 | C10: 11 | D10: 6148 | E10: 11 | F10: 6435 | G10: 9 | H10: 6498 | I10: 10 | J10: 6135.5 | K10: 11 | L10: 5905 | O10: 41487 | P10: 7182.2619 | Q10: 0.041363719 | R10: 16802.902 | S10: 0.081498669
A11: 11 | B11: 5926.5 | C11: 12 | D11: 6102 | E11: 12 | F11: 6510 | G11: 10 | H11: 6447 | I11: 13 | J11: 6042.5 | K11: 12 | L11: 5828.5 | O11: 41518 | P11: 7161.4286 | Q11: -0.0029006647 | R11: 16264.32 | S11: -0.032052874
A12: 14 | B12: 5861 | C12: 13 | D12: 6120 | E12: 13 | F12: 6529 | G12: 11 | H12: 6432.5 | I12: 14 | J12: 6007 | K12: 13 | L12: 5797.5 | O12: 41548 | P12: 7188.7826 | Q12: 0.0038196342 | R12: 15720.43 | S12: -0.033440722
A13: 15 | B13: 5882 | C13: 14 | D13: 6178.5 | E13: 14 | F13: 6409 | G13: 12 | H13: 6490 | I13: 15 | J13: 6002 | K13: 14 | L13: 5805.5 | O13: 41579 | P13: 7066.4048 | Q13: -0.017023445 | R13: 16235.772 | S13: 0.032781659
A14: 16 | B14: 5911 | C14: 15 | D14: 6190 | E14: 15 | F14: 6410 | G14: 15 | H14: 6456 | I14: 16 | J14: 6089 | K14: 17 | L14: 5756 | O14: 41609 | P14: 7202.95 | Q14: 0.019323156 | R14: 16911.086 | S14: 0.041594231
A15: 17 | B15: 5933 | C15: 16 | D15: 6269.5 | E15: 18 | F15: 6492 | G15: 16 | H15: 6460 | I15: 17 | J15: 6025 | K15: 18 | L15: 5848.5 | O15: 41640 | P15: 7294.8864 | Q15: 0.01276371 | R15: 17368.395 | S15: 0.027041961 | T15: 0.027041961
A16: 18 | B16: 6022 | C16: 19 | D16: 6246.5 | E16: 19 | F16: 6500 | G16: 17 | H16: 6509 | I16: 20 | J16: 5985 | K16: 19 | L16: 5895 | O16: 41671 | P16: 7152.15 | Q16: -0.019566633 | R16: 17062.884 | S16: -0.017590036 | T16: 0.0089762565
A17: 21 | B17: 5951.5 | C17: 20 | D17: 6351.5 | E17: 20 | F17: 6487 | G17: 18 | H17: 6448 | I17: 21 | J17: 6004 | K17: 20 | L17: 5962 | O17: 41699 | P17: 6667.8095 | Q17: -0.067719564 | R17: 15507.991 | S17: -0.0911272 | T17: -0.082968925
A18: 22 | B18: 5926.5 | C18: 21 | D18: 6391 | E18: 21 | F18: 6520 | G18: 23 | H18: 6430 | I18: 22 | J18: 5920 | K18: 21 | L18: 5941 | O18: 41730 | P18: 6670.825 | Q18: 0.0004522439 | R18: 14896.619 | S18: -0.039423035 | T18: -0.11912107
A19: 23 | B19: 5920.5 | C19: 22 | D19: 6449 | E19: 22 | F19: 6375 | G19: 24 | H19: 6437.5 | I19: 23 | J19: 5860 | K19: 24 | L19: 5917 | O19: 41760 | P19: 6883.875 | Q19: 0.031937579 | R19: 15289.775 | S19: 0.02639226 | T19: -0.095872687
A20: 24 | B20: 5885 | C20: 25 | D20: 6546 | E20: 25 | F20: 6328 | G20: 25 | H20: 6375.5 | I20: 24 | J20: 5919 | K20: 25 | L20: 5985.5 | O20: 41791 | P20: 6806.0952 | Q20: -0.011298834 | R20: 15206.178 | S20: -0.0054674959 | T20: -0.100816
A21: 25 | B21: 5901 | C21: 26 | D21: 6471 | E21: 26 | F21: 6361 | G21: 26 | H21: 6393 | I21: 28 | J21: 5956.5 | K21: 26 | L21: 6006 | O21: 41821 | P21: 7104.8478 | Q21: 0.043894859 | R21: 15807.576 | S21: 0.03954958 | T21: -0.06525365
A22: 28 | B22: 5996 | C22: 27 | D22: 6533 | E22: 27 | F22: 6338.5 | G22: 27 | H22: 6376 | I22: 29 | J22: 5864.5 | K22: 27 | L22: 5953.5 | O22: 41852 | P22: 7000.55 | Q22: -0.014679811 | R22: 15880.048 | S22: 0.0045846177 | T22: -0.060968195
A23: 29 | B23: 6007 | C23: 28 | D23: 6572 | E23: 28 | F23: 6385 | G23: 30 | H23: 6442 | I23: 30 | J23: 5780.5 | K23: 28 | L23: 5972 | O23: 41883 | P23: 6872.2273 | Q23: -0.018330378 | R23: 16046.651 | S23: 0.010491345 | T23: -0.051116488
A24: 30 | B24: 6077 | E24: 29 | F24: 6485 | I24: 31 | O24: 41913 | P24: 6739.1957 | Q24: -0.019357861 | R24: 16515.747 | S24: 0.029233272 | T24: -0.023377518
A25: 31 | B25: 6148 | E25: 30
O26: 41944 | P26: 6701.135 | Q26: -0.005647655 | R26: 17154.906 | S26: 0.038699965 | T26: 0.014417737
A27: =B28/'2018'!L65-1 -> -0.026613422 | C27: =D28/B28-1 -> 0.058323659 | E27: =F28/D28-1 -> 0.027560339 | G27: =H28/F28-1 -> -0.00091827432 | I27: =J28/H28-1 -> -0.063075049 | K27: =L28/J28-1 -> -0.028177178 | O27: 41974 | P27: 6422.9524 | Q27: -0.041512762 | R27: 16968.798 | S27: -0.010848658 | T27: 0.0034126658
A28: MM | B28: =AVERAGE(B4:B25) -> 5932.0227 | C28: MM | D28: =AVERAGE(D4:D23) -> 6278 | E28: MM | F28: =AVERAGE(F4:F25) -> 6451.0238 | G28: MM | H28: =AVERAGE(H4:H24) -> 6445.1 | I28: MM | J28: =AVERAGE(J4:J25) -> 6038.575 | K28: MM | L28: =AVERAGE(L4:L24) -> 5868.425 | O28: 42005 | P28: 5791.175 | Q28: -0.098362458 | R28: 15271.908 | S28: -0.10000062 | T28: -0.10000062
A29: MM R$ | B29: =B28*A30 -> 22195.256 | C29: MM R$ | D29: =D28*C30 -> 23376.761 | E29: MM R$ | F29: =F28*E30 -> 24760.32 | G29: MM R$ | H29: =H28*G30 -> 25095.93 | I29: MM R$ | J29: =J28*I30 -> 24164.566 | K29: MM R$ | L29: =L28*K30 -> 22678.528 | O29: 42036 | P29: 5702.075 | Q29: -0.015385479 | R29: 16059.837 | S29: 0.051593399 | T29: -0.053566592
A30: 3.7416 | B30: =A30/'2018'!K68-1 -> -0.036787231 | C30: 3.7236 | D30: =D29/B29-1 -> 0.053232301 | E30: 3.8382 | F30: =F29/D29-1 -> 0.059185222 | G30: 3.8938 | H30: =H29/F29-1 -> 0.013554381 | I30: 4.0017 | J30: =J29/H29-1 -> -0.037112185 | K30: 3.8645 | L30: =L29/J29-1 -> -0.06149654 | O30: 42064 | P30: 5919.9048 | Q30: 0.038201841 | R30: 18601.525 | S30: 0.15826359 | T30: 0.096219358
A31: Cobre LME Prices 2019 US$/Ton | O31: MÉDIAS
A32: Julho 2019 | C32: Agosto 2019 | E32: Setembro 2019 | G32: Outubro 2019 | I32: Novembro 2019 | K32: Dezembro 2019 | O32: 42125 | P32: 6300.6053 | Q32: 0.04514038 | R32: 19242.048 | S32: 0.045653962 | T32: 0.13396651
B33: Cash | D33: Cash | F33: Cash | H33: Cash | J33: Cash | L33: Cash | O33: 42156 | P33: 5833.6136 | Q33: -0.074118534 | R33: 18168.79 | S33: -0.055776744 | T33: 0.070717548
A34: Média | B34: #DIV/0! | C34: Média | D34: #DIV/0! | E34: Média | F34: #DIV/0! | G34: Média | H34: #DIV/0! | I34: Média | J34: #DIV/0! | K34: Média | L34: #DIV/0! | O34: 42675 | T34: #DIV/0!
A35: MM | B35: #DIV/0! | C35: MM | D35: #DIV/0! | E35: MM | F35: #DIV/0! | G35: MM | H35: #DIV/0! | I35: MM | J35: #DIV/0! | K35: MM | L35: #DIV/0! | O35: 42705 | T35: #DIV/0!
A36: #DIV/0! | C36: #DIV/0! | E36: #DIV/0! | G36: #DIV/0! | I36: #DIV/0! | K36: #DIV/0! | O36: 42736 | T36: #DIV/0!
A37: MM R$ | B37: #DIV/0! | C37: MM R$ | D37: #DIV/0! | E37: MM R$ | F37: #DIV/0! | G37: MM R$ | H37: #DIV/0! | I37: MM R$ | J37: #DIV/0! | K37: MM R$ | L37: #DIV/0! | O37: 42767 | T37: #DIV/0!
B38: #DIV/0! | D38: #DIV/0! | F38: #DIV/0! | H38: #DIV/0! | J38: #DIV/0! | L38: #DIV/0! | O38: 42795 | T38: #DIV/0!
A39: Julho 2016 | C39: Agosto 2016 | E39: Setembro 2016 | G39: Outubro 2016 | I39: Novembro 2016 | K39: Dezembro 2016 | O39: 42826 | T39: #DIV/0!
B40: Cash | D40: Cash | F40: Cash | H40: Cash | J40: Cash | L40: Cash | O40: 42856 | T40: #DIV/0!
A41: 2 | B41: 5999 | C41: 1 | D41: 5876 | E41: 3 | F41: 5610.5 | G41: 1 | H41: 5610 | I41: 1 | J41: 5797 | K41: 2 | L41: 5855.5 | O41: 42186 | P41: 5456.913 | Q41: -0.064574142 | R41: 17564.712 | S41: =R41/R33-1 -> -0.033248113 | T41: 0.03511821
A42: 3 | B42: 5910 | C42: 2 | D42: 5769 | E42: 4 | F42: 5537 | G42: 2 | H42: 5629 | I42: 4 | J42: 5846.5 | K42: 3 | L42: 5812 | O42: 42217 | P42: 5088.925 | Q42: -0.067435204 | R42: 17846.351 | S42: =R42/R41-1 -> 0.016034387 | T42: 0.051715696
A43: 4 | B43: 5900 | C43: 5 | D43: 5647 | E43: 5 | F43: 5777 | G43: 3 | H43: 5626 | I43: 5 | J43: 5880 | K43: 4 | L43: 5823 | O43: 42248 | P43: 5208.0909 | Q43: 0.023416716 | R43: 20289.16 | S43: =R43/R42-1 -> 0.13688001 | T43: 0.19567455
A44: 5 | B44: 5857 | C44: 6 | D44: 5667 | E44: 6 | F44: 5787.5 | G44: 4 | H44: 5599 | I44: 6 | J44: 5913.5 | K44: 5 | L44: 5855 | O44: 42278 | P44: 5222.6136 | Q44: 0.0027884934 | R44: 20224.049 | S44: =R44/R43-1 -> -0.0032091378 | T44: 0.19183746
A45: 8 | B45: 5912 | C45: 7 | D45: 5673.5 | E45: 9 | F45: 5771 | G45: 7 | H45: 5626 | I45: 7 | J45: 5941 | K45: 6 | L45: 5867.5 | O45: 42309 | P45: 4808.2381 | Q45: -0.079342561 | R45: 18166.485 | S45: =R45/R44-1 -> -0.10173847 | T45: 0.07058174
A46: 9 | B46: 5805 | C46: 8 | D46: 5723 | E46: 10 | F46: 5738 | G46: 8 | H46: 5650.5 | I46: 8 | J46: 5951.5 | K46: 9 | L46: 5985 | O46: 42339 | P46: 4629 | Q46: -0.037277292 | R46: 17927.654 | S46: =R46/R45-1 -> -0.013146796 | T46: =R46/R27-1 -> 0.05650702
A47: 10 | B47: 5862.5 | C47: 9 | D47: 5744 | E47: 11 | F47: 5765 | G47: 9 | H47: 5660 | I47: 11 | J47: 5857 | K47: 10 | L47: 6055 | O47: 42370 | P47: =B28 -> 5932.0227 | Q47: =P47/P46-1 -> 0.28149119 | R47: =B29 -> 22195.256 | S47: =R47/R46-1 -> 0.23804577 | T47: =R47/$R$46-1 -> 0.23804577
A48: 11 | B48: 5925 | C48: 12 | D48: 5724.5 | E48: 12 | F48: 5842.5 | G48: 10 | H48: 5698.5 | I48: 12 | J48: 5838 | K48: 11 | L48: 6083 | O48: 42401 | P48: =D28 -> 6278 | Q48: =P48/P47-1 -> 0.058323659 | R48: =D29 -> 23376.761 | S48: =R48/R47-1 -> 0.053232301 | T48: =R48/$R$46-1 -> 0.30394979
A49: 12 | B49: 5950 | C49: 13 | D49: 5697 | E49: 13 | F49: 5870 | G49: 11 | H49: 5763 | I49: 13 | J49: 5823 | K49: 12 | L49: 6097 | O49: 42430 | P49: =F28 -> 6451.0238 | Q49: =P49/P48-1 -> 0.027560339 | R49: =F29 -> 24760.32 | S49: =R49/R48-1 -> 0.059185222 | T49: =R49/$R$46-1 -> 0.38112435
A50: 15 | B50: 5997.5 | C50: 14 | D50: 5732 | E50: 14 | F50: 5877 | G50: 14 | H50: 5718.5 | I50: 14 | J50: 5835 | K50: 13 | L50: 6154 | O50: 42461 | P50: =H28 -> 6445.1 | Q50: =P50/P49-1 -> -0.00091827432 | R50: =H29 -> 25095.93 | S50: =R50/R49-1 -> 0.013554381 | T50: =R50/$R$46-1 -> 0.39984463
A51: 16 | B51: 5959 | C51: 15 | D51: 5696.5 | E51: 17 | F51: 5762 | G51: 15 | H51: 5745 | I51: 15 | J51: 5812 | K51: 16 | L51: 6155.5 | O51: 42491 | P51: =J28 -> 6038.575 | Q51: =P51/P50-1 -> -0.063075049 | R51: =J29 -> 24164.566 | S51: =R51/R50-1 -> -0.037112185 | T51: =R51/R46-1 -> 0.34789334
A52: 17 | B52: 5922 | C52: 16 | D52: 5710 | E52: 18 | F52: 5745 | G52: 16 | H52: 5684 | I52: 18 | J52: 5828 | K52: 17 | L52: 6175 | O52: 42522 | P52: =L28 -> 5868.425 | Q52: =P52/P51-1 -> -0.028177178 | R52: =L29 -> 22678.528 | S52: =R52/R51-1 -> -0.06149654 | T52: =R52/R46-1 -> 0.26500256
A53: 18 | B53: 5948 | C53: 19 | D53: 5755.5 | E53: 19 | F53: 5758.5 | G53: 17 | H53: 5726.5 | I53: 19 | J53: 5821.5 | K53: 18 | L53: 6126.5 | O53: 42552 | P53: =B65 -> 5943.6429 | Q53: =P53/P52-1 -> 0.012817384 | R53: =B67 -> 22478.263 | S53: =R53/R52-1 -> -0.0088306211 | T53: =R53/R46-1 -> 0.25383181
A54: 19 | B54: 6066 | C54: 20 | D54: 5698 | E54: 20 | F54: 5777.5 | G54: 18 | H54: 5751 | I54: 20 | J54: 5873 | K54: 19 | L54: 6161 | O54: 42583 | P54: =D65 -> 5707.9762 | Q54: =P54/P53-1 -> -0.039650207 | R54: =D67 -> 22946.064 | S54: =R54/R53-1 -> 0.020811277 | T54: =R54/R46-1 -> 0.27992565
A55: 22 | B55: 6007.5 | C55: 21 | D55: 5696.5 | E55: 23 | F55: 5695 | G55: 21 | H55: 5820 | I55: 21 | J55: 5813 | K55: 20 | L55: 6155.5 | O55: 42614 | P55: =F65 -> 5749.6 | Q55: =P55/P54-1 -> 0.0072922185 | R55: =F67 -> 23690.077 | S55: =R55/R54-1 -> 0.03242441 | T55: =R55/R46-1 -> 0.32142648
A56: 23 | B56: 5968.5 | C56: 22 | D56: 5668 | E56: 24 | F56: 5761 | G56: 22 | H56: 5794 | I56: 22 | J56: 5834 | K56: 23 | L56: 6153 | O56: 42644 | P56: =H65 -> 5742.8913 | Q56: =P56/P55-1 -> -0.0011668108 | R56: =H67 -> 23511.397 | S56: =R56/R55-1 -> -0.0075423934 | T56: =R56/R46-1 -> 0.31145976
A57: 24 | B57: 5980 | C57: 23 | D57: 5675 | E57: 25 | F57: 5718.5 | G57: 23 | H57: 5773 | I57: 25 | J57: 5872.5 | K57: 24 | L57: 6184.5 | O57: 42675 | P57: =J65 -> 5859.6905 | Q57: =P57/P56-1 -> 0.020338043 | R57: =J67 -> 24345.403 | S57: =R57/R56-1 -> 0.035472393 | T57: =R57/R46-1 -> 0.35798038
A58: 25 | B58: 6010 | C58: 27 | D58: 5662 | E58: 26 | F58: 5757 | G58: 24 | H58: 5869 | I58: 26 | J58: 5856 | K58: 27 | L58: 6211 | O58: Acumulado 2016 | P58: =P57/P46-1 -> 0.2658653 | Q58: Dolar | S58: =R57/R46-1 -> 0.35798038 | T58: Reais
A59: 26 | B59: 5945 | C59: 28 | D59: 5653 | E59: 27 | F59: 5714 | G59: 25 | H59: 5867.5 | I59: 27 | J59: 5925.5 | K59: 30 | L59: 6183.5
A60: 27 | B60: 5949.5 | C60: 29 | D60: 5722 | E60: 30 | F60: 5728 | G60: 28 | H60: 5888.5 | I60: 28 | J60: 5881.5 | K60: 31 | L60: 6156
A61: 30 | B61: 5943 | C61: 30 | D61: 5678 | G61: 29 | H61: 5879.5 | I61: 29 | J61: 5854
A62: 31 | G62: 30 | H62: 5883
G63: 31 | H63: 5825
A64: =B65/L28-1 -> 0.012817384 | C64: =D65/B65-1 -> -0.039650207 | E64: =F65/D65-1 -> 0.0072922185 | G64: =H65/F65-1 -> -0.0011668108 | I64: =J65/H65-1 -> 0.020338043 | K64: =L65/J65-1 -> 0.034598163
A65: MM | B65: =AVERAGE(B41:B62) -> 5943.6429 | C65: MM | D65: =AVERAGE(D41:D63) -> 5707.9762 | E65: MM | F65: =AVERAGE(F41:F60) -> 5749.6 | G65: MM | H65: =AVERAGE(H41:H63) -> 5742.8913 | I65: MM | J65: =AVERAGE(J41:J62) -> 5859.6905 | K65: MM | L65: =AVERAGE(L41:L60) -> 6062.425
A67: MM R$ | B67: =B65*A68 -> 22478.263 | C67: MM R$ | D67: =D65*C68 -> 22946.064 | E67: MM R$ | F67: =F65*E68 -> 23690.077 | G67: MM R$ | H67: =H65*G68 -> 23511.397 | I67: MM R$ | J67: =J65*I68 -> 24345.403 | K67: MM R$ | L67: =L65*K68 -> 24910.042
A68: 3.7819 | B68: =B67/L29-1 -> -0.0088306211 | C68: 4.02 | D68: =D67/B67-1 -> 0.020811277 | E68: 4.1203 | F68: =F67/D67-1 -> 0.03242441 | G68: 4.094 | H68: =H67/F67-1 -> -0.0075423934 | I68: 4.154725 | J68: =J67/H67-1 -> 0.035472393 | K68: 4.1089238 | L68: =L67/J67-1 -> 0.023192876
E71: VARIAÇÃO COBRE LME - REAIS

Sheet Planilha3
A1: 4.2261
A2: 43802 | B2: A | C2: 4.2002 | D2: 4.2008
A3: 43803 | B3: A | C3: 4.192 | D3: 4.1926
A4: 43804 | B4: A | C4: 4.213 | D4: 4.2136
A5: 43805 | B5: A | C5: 4.1777 | D5: 4.1783
A6: 43808 | B6: A | C6: 4.1497 | D6: 4.1503
A7: 43809 | B7: A | C7: 4.1421 | D7: 4.1427
A8: 43810 | B8: A | C8: 4.1147 | D8: 4.1153
A9: 43811 | B9: A | C9: 4.1086 | D9: 4.1092
A10: 43812 | B10: A | C10: 4.0943 | D10: 4.0949
A11: 43815 | B11: A | C11: 4.0795 | D11: 4.0801
A12: 43816 | B12: A | C12: 4.0681 | D12: 4.0687
A13: 43817 | B13: A | C13: 4.0542 | D13: 4.0548
... A21: 43830 | B21: A | C21: 4.0301 | D21: 4.0307
D22: =AVERAGE(D2:D21) -> 4.103765

Sheet 2020
A1: Cobre LME Prices 2019 US$/Ton | O1: MÉDIAS
A2: Janeiro 2020 | C2: Fevereiro 2020 | E2: Março 2020 | G2: Abril 2020 | I2: Maio 2020 | K2: Junho 2020 | P2: US$ | Q2: Var (%) | R2: R$ | S2: Var Mês (%) | T2: Acumulado/Ano
B3: Cash | D3: Cash | F3: Cash | H3: Cash | J3: Cash | L3: Cash | O3: 41275 | P3: 8049.2455 | Q3: 0.010884092 | R3: 16364.921 | S3: -0.010958324
A4: 2 | B4: 6165.5 | C4: 3 | D4: 5595 | E4: 2 | F4: 5640 | G4: 1 | H4: 4772 | I4: 1 | J4: 5061 | K4: 1 | L4: 5376.5 | O4: 41306 | P4: 8070.475 | Q4: 0.0026374578 | R4: 15912.556 | S4: -0.027642381
A5: 3 | B5: 6077 | C5: 4 | D5: 5652 | E5: 3 | F5: 5668 | G5: 2 | H5: 4821.5 | I5: 4 | J5: 5058 | K5: 2 | L5: 5463 | O5: 41334 | P5: 7662.4 | Q5: -0.050563938 | R5: 15212.929 | S5: -0.043966954
A6: 6 | B6: 6097.5 | C6: 5 | D6: 5714 | E6: 4 | F6: 5694.5 | G6: 3 | H6: 4863.5 | I6: 5 | J6: 5111.5 | K6: 3 | L6: 5499 | O6: 41365 | P6: 7203.3571 | Q6: -0.059908496 | R6: 14413.918 | S6: -0.052521859
A7: 7 | B7: 6134.5 | C7: 6 | D7: 5726 | E7: 5 | F7: 5667.5 | G7: 6 | H7: 4867 | I7: 6 | J7: 5199.5 | K7: 4 | L7: 5452.5 | O7: 41395 | P7: 7229.1429 | Q7: 0.0035796801 | R7: 14704.077 | S7: 0.020130469
A8: 8 | B8: 6154 | C8: 7 | D8: 5653 | E8: 6 | F8: 5624 | G8: 7 | H8: 5067.5 | I8: 7 | J8: 5227.5 | K8: 5 | L8: 5588 | O8: 41426 | P8: 7004.05 | Q8: -0.031136867 | R8: 15198.789 | S8: 0.033644542
A9: 9 | B9: 6156 | C9: 10 | D9: 5659.5 | E9: 9 | F9: 5483 | G9: 8 | H9: 4976 | I9: 11 | J9: 5231 | K9: 8 | L9: 5659 | O9: 41456 | P9: 6896.9773 | Q9: -0.015287259 | R9: 15536.683 | S9: 0.022231658
A10: 10 | B10: 6157 | C10: 11 | D10: 5696 | E10: 10 | F10: 5598 | G10: 9 | H10: 4963.5 | I10: 12 | J10: 5234 | K10: 9 | L10: 5680.5 | O10: 41487 | P10: 7182.2619 | Q10: 0.041363719 | R10: 16802.902 | S10: 0.081498669
A11: 13 | B11: 6177 | C11: 12 | D11: 5747 | E11: 11 | F11: 5552 | G11: 14 | H11: 5119 | I11: 13 | J11: 5212.5 | K11: 10 | L11: 5801 | O11: 41518 | P11: 7161.4286 | Q11: -0.0029006647 | R11: 16264.32 | S11: -0.032052874
A12: 14 | B12: 6247 | C12: 13 | D12: 5716 | E12: 12 | F12: 5386.5 | G12: 15 | H12: 5054.5 | I12: 14 | J12: 5155.5 | K12: 11 | L12: 5801.5 | O12: 41548 | P12: 7188.7826 | Q12: 0.0038196342 | R12: 15720.43 | S12: -0.033440722
A13: 15 | B13: 6232 | C13: 14 | D13: 5737 | E13: 13 | F13: 5530.5 | G13: 16 | H13: 5098.5 | I13: 15 | J13: 5165 | K13: 12 | L13: 5785.5 | O13: 41579 | P13: 7066.4048 | Q13: -0.017023445 | R13: 16235.772 | S13: 0.032781659
A14: 16 | B14: 6300.5 | C14: 17 | D14: 5802 | E14: 16 | F14: 5211 | G14: 17 | H14: 5175.5 | I14: 18 | J14: 5249.5 | K14: 15 | L14: 5646 | O14: 41609 | P14: 7202.95 | Q14: 0.019323156 | R14: 16911.086 | S14: 0.041594231
A15: 17 | B15: 6276.5 | C15: 18 | D15: 5728 | E15: 17 | F15: 5205 | G15: 20 | H15: 5169.5 | I15: 19 | J15: 5314 | K15: 16 | L15: 5759.5 | O15: 41640 | P15: 7294.8864 | Q15: 0.01276371 | R15: 17368.395 | S15: 0.027041961 | T15: 0.027041961
A16: 20 | B16: 6245 | C16: 19 | D16: 5745.5 | E16: 18 | F16: 4860.5 | G16: 21 | H16: 4994.5 | I16: 20 | J16: 5330 | K16: 17 | L16: 5734 | O16: 41671 | P16: 7152.15 | Q16: -0.019566633 | R16: 17062.884 | S16: -0.017590036 | T16: 0.0089762565
A17: 21 | B17: 6158.5 | C17: 20 | D17: 5730 | E17: 19 | F17: 4685 | G17: 22 | H17: 5034 | I17: 21 | J17: 5387 | K17: 18 | L17: 5799 | O17: 41699 | P17: 6667.8095 | Q17: -0.067719564 | R17: 15507.991 | S17: -0.0911272 | T17: -0.082968925
A18: 22 | B18: 6103.5 | C18: 21 | D18: 5702 | E18: 20 | F18: 4855 | G18: 23 | H18: 5120.5 | I18: 22 | J18: 5242.5 | K18: 19 | L18: 5835.5 | O18: 41730 | P18: 6670.825 | Q18: 0.0004522439 | R18: 14896.619 | S18: -0.039423035 | T18: -0.11912107
A19: 23 | B19: 6050 | C19: 24 | D19: 5657.5 | E19: 23 | F19: 4617.5 | G19: 24 | H19: 5118 | I19: 26 | J19: 5341.5 | K19: 22 | L19: 5825 | O19: 41760 | P19: 6883.875 | Q19: 0.031937579 | R19: 15289.775 | S19: 0.02639226 | T19: -0.095872687
A20: 24 | B20: 5968 | C20: 25 | D20: 5663.5 | E20: 24 | F20: 4789.5 | G20: 27 | H20: 5165.5 | I20: 27 | J20: 5308.5 | K20: 23 | L20: 5895 | O20: 41791 | P20: 6806.0952 | Q20: -0.011298834 | R20: 15206.178 | S20: -0.0054674959 | T20: -0.100816
A21: 27 | B21: 5779 | C21: 26 | D21: 5614 | E21: 25 | F21: 4754 | G21: 28 | H21: 5169.5 | I21: 28 | J21: 5278.5 | K21: 24 | L21: 5871 | O21: 41821 | P21: 7104.8478 | Q21: 0.043894859 | R21: 15807.576 | S21: 0.03954958 | T21: -0.06525365
A22: 28 | B22: 5715 | C22: 27 | D22: 5618 | E22: 26 | F22: 4775.5 | G22: 29 | H22: 5184 | I22: 29 | J22: 5332.5 | K22: 25 | L22: 5880.5 | O22: 41852 | P22: 7000.55 | Q22: -0.014679811 | R22: 15880.048 | S22: 0.0045846177 | T22: -0.060968195
A23: 29 | B23: 5698 | C23: 28 | D23: 5573 | E23: 27 | F23: 4774 | G23: 30 | H23: 5231 | K23: 26 | L23: 5985.5 | O23: 41883 | P23: 6872.2273 | Q23: -0.018330378 | R23: 16046.651 | S23: 0.010491345 | T23: -0.051116488
A24: 30 | B24: 5621 | E24: 30 | F24: 4763 | K24: 29 | L24: 5957 | O24: 41913 | P24: 6739.1957 | Q24: -0.019357861 | R24: 16515.747 | S24: 0.029233272 | T24: -0.023377518
A25: 31 | B25: 5570 | E25: 31 | F25: 4797 | K25: 30 | L25: 6038
O26: 41944 | P26: 6701.135 | Q26: -0.005647655 | R26: 17154.906 | S26: 0.038699965 | T26: 0.014417737
A27: =B28/'2018'!L65-1 -> -0.0073850387 | C27: =D28/B28-1 -> -0.059967314 | E27: =F28/D28-1 -> -0.089294407 | G27: =H28/F28-1 -> -0.025186297 | I27: =J28/H28-1 -> 0.036727162 | K27: =L28/J28-1 -> 0.097203233 | O27: 41974 | P27: 6422.9524 | Q27: -0.041512762 | R27: 16968.798 | S27: -0.010848658 | T27: 0.0034126658
A28: MM | B28: =AVERAGE(B4:B25) -> 6049.2045 | C28: MM | D28: =AVERAGE(D4:D23) -> 5686.45 | E28: MM | F28: =AVERAGE(F4:F25) -> 5178.6818 | G28: MM | H28: =AVERAGE(H4:H24) -> 5048.25 | I28: MM | J28: =AVERAGE(J4:J22) -> 5233.6579 | K28: MM | L28: =AVERAGE(L4:L25) -> 5742.3864 | O28: 42005 | P28: 5791.175 | Q28: -0.098362458 | R28: 15271.908 | S28: -0.10000062 | T28: -0.10000062
A29: MM R$ | B29: =B28*A30 -> 25097.545 | C29: MM R$ | D29: =D28*C30 -> 24681.468 | E29: MM R$ | F29: =F28*E30 -> 25126.964 | G29: MM R$ | H29: =H28*G30 -> 26881.426 | I29: MM R$ | J29: =J28*I30 -> 29517.831 | K29: MM R$ | L29: =L28*K30 -> 29837.412 | O29: 42036 | P29: 5702.075 | Q29: -0.015385479 | R29: 16059.837 | S29: 0.051593399 | T29: -0.053566592
A30: 4.1489 | B30: =A30/'2019'!K68-1 -> 0.0097291146 | C30: 4.3404 | D30: =D29/B29-1 -> -0.016578401 | E30: 4.852 | F30: =F29/D29-1 -> 0.018049842 | G30: 5.3249 | H30: =H29/F29-1 -> 0.069823884 | I30: 5.64 | J30: =J29/H29-1 -> 0.098075305 | K30: 5.1959952 | L30: =L29/J29-1 -> 0.010826733 | O30: 42064 | P30: 5919.9048 | Q30: 0.038201841 | R30: 18601.525 | S30: 0.15826359 | T30: 0.096219358
A31: 3 | O31: MÉDIAS
A32: Julho 2020 | C32: Agosto 2020 | E32: Setembro 2020 | G32: Outubro 2020 | I32: Novembro 2020 | K32: Dezembro 2020 | O32: 42125 | P32: 6300.6053 | Q32: 0.04514038 | R32: 19242.048 | S32: 0.045653962 | T32: 0.13396651
B33: Cash | D33: Cash | F33: Cash | H33: Cash | J33: Cash | L33: Cash | O33: 42156 | P33: 5833.6136 | Q33: -0.074118534 | R33: 18168.79 | S33: -0.055776744 | T33: 0.070717548
A34: Média | B34: #DIV/0! | C34: Média | D34: #DIV/0! | E34: Média | F34: #DIV/0! | G34: Média | H34: #DIV/0! | I34: Média | J34: #DIV/0! | K34: Média | L34: #DIV/0! | O34: 42675 | T34: #DIV/0!
A35: MM | B35: #DIV/0! | C35: MM | D35: #DIV/0! | E35: MM | F35: #DIV/0! | G35: MM | H35: #DIV/0! | I35: MM | J35: #DIV/0! | K35: MM | L35: #DIV/0! | O35: 42705 | T35: #DIV/0!
A36: #DIV/0! | C36: #DIV/0! | E36: #DIV/0! | G36: #DIV/0! | I36: #DIV/0! | K36: #DIV/0! | O36: 42736 | T36: #DIV/0!
A37: MM R$ | B37: #DIV/0! | C37: MM R$ | D37: #DIV/0! | E37: MM R$ | F37: #DIV/0! | G37: MM R$ | H37: #DIV/0! | I37: MM R$ | J37: #DIV/0! | K37: MM R$ | L37: #DIV/0! | O37: 42767 | T37: #DIV/0!
B38: #DIV/0! | D38: #DIV/0! | F38: #DIV/0! | H38: #DIV/0! | J38: #DIV/0! | L38: #DIV/0! | O38: 42795 | T38: #DIV/0!
A39: Julho 2016 | C39: Agosto 2016 | E39: Setembro 2016 | G39: Outubro 2016 | I39: Novembro 2016 | K39: Dezembro 2016 | O39: 42826 | T39: #DIV/0!
B40: Cash | D40: Cash | F40: Cash | H40: Cash | J40: Cash | L40: Cash | O40: 42856 | T40: #DIV/0!
A41: 1 | B41: 6016.5 | C41: 3 | D41: 6441 | E41: 1 | F41: 6788.5 | G41: 1 | H41: 6614 | I41: 2 | J41: 6712.5 | K41: 1 | L41: 7644 | O41: =#REF! -> #REF! | P41: =#REF! -> #REF! | Q41: =#REF! -> #REF! | R41: =#REF! -> #REF! | S41: =#REF! -> #REF! | T41: =#REF! -> #REF!
A42: 2 | B42: 6080 | C42: 4 | D42: 6440 | E42: 2 | F42: 6719 | G42: 2 | H42: 6409.5 | I42: 3 | J42: 6791.5 | K42: 2 | L42: 7616.5 | O42: =#REF! -> #REF! | P42: =#REF! -> #REF! | Q42: =#REF! -> #REF! | R42: =#REF! -> #REF! | S42: =#REF! -> #REF! | T42: =#REF! -> #REF!
A43: 3 | B43: 6022.5 | C43: 5 | D43: 6525.5 | E43: 3 | F43: 6613 | G43: 5 | H43: 6507.5 | I43: 4 | J43: 6748 | K43: 3 | L43: 7679 | O43: =#REF! -> #REF! | P43: =#REF! -> #REF! | Q43: =#REF! -> #REF! | R43: =#REF! -> #REF! | S43: =#REF! -> #REF! | T43: =#REF! -> #REF!
A44: 6 | B44: 6112 | C44: 6 | D44: 6453.5 | E44: 4 | F44: 6678 | G44: 6 | H44: 6509 | I44: 5 | J44: 6798 | K44: 4 | L44: 7741.5 | O44: =#REF! -> #REF! | P44: =#REF! -> #REF! | Q44: =#REF! -> #REF! | R44: =#REF! -> #REF! | S44: =#REF! -> #REF! | T44: =#REF! -> #REF!
A45: 7 | B45: 6086 | C45: 7 | D45: 6437 | E45: 7 | F45: 6790.5 | G45: 7 | H45: 6525 | I45: 6 | J45: 6938.5 | K45: 7 | L45: 7656.5 | O45: =#REF! -> #REF! | P45: =#REF! -> #REF! | Q45: =#REF! -> #REF! | R45: =#REF! -> #REF! | S45: =#REF! -> #REF! | T45: =#REF! -> #REF!
A46: 8 | B46: 6194 | C46: 10 | D46: 6363 | E46: 8 | F46: 6767.5 | G46: 8 | H46: 6611.5 | I46: 9 | J46: 7034 | K46: 8 | L46: 7635 | O46: =#REF! -> #REF! | P46: =#REF! -> #REF! | Q46: =#REF! -> #REF! | R46: =#REF! -> #REF! | S46: =#REF! -> #REF! | T46: =#REF! -> #REF!
A47: 9 | B47: 6339.5 | C47: 11 | D47: 6356.5 | E47: 9 | F47: 6709 | G47: 9 | H47: 6740.5 | I47: 10 | J47: 6865.5 | K47: 9 | L47: 7704.5 | O47: =#REF! -> #REF! | P47: =#REF! -> #REF! | Q47: =#REF! -> #REF! | R47: =#REF! -> #REF! | S47: =#REF! -> #REF! | T47: =#REF! -> #REF!
A48: 10 | B48: 6322.5 | C48: 12 | D48: 6379 | E48: 10 | F48: 6710.5 | G48: 12 | H48: 6769 | I48: 11 | J48: 6912.5 | K48: 10 | L48: 7712 | O48: =#REF! -> #REF! | P48: =#REF! -> #REF! | Q48: =#REF! -> #REF! | R48: =#REF! -> #REF! | S48: =#REF! -> #REF! | T48: =#REF! -> #REF!
A49: 13 | B49: 6545 | C49: 13 | D49: 6380 | E49: 11 | F49: 6757.5 | G49: 13 | H49: 6699.5 | I49: 12 | J49: 6904 | K49: 11 | L49: 7741 | O49: =#REF! -> #REF! | P49: =#REF! -> #REF! | Q49: =#REF! -> #REF! | R49: =#REF! -> #REF! | S49: =#REF! -> #REF! | T49: =#REF! -> #REF!
A50: 14 | B50: 6489.5 | C50: 14 | D50: 6342.5 | E50: 14 | F50: 6788 | G50: 14 | H50: 6702 | I50: 13 | J50: 6926 | K50: 14 | L50: 7763 | O50: =#REF! -> #REF! | P50: =#REF! -> #REF! | Q50: =#REF! -> #REF! | R50: =#REF! -> #REF! | S50: =#REF! -> #REF! | T50: =#REF! -> #REF!
A51: 15 | B51: 6507 | C51: 17 | D51: 6439.5 | E51: 15 | F51: 6813.5 | G51: 15 | H51: 6683.5 | I51: 16 | J51: 7113 | K51: 15 | L51: 7753 | O51: =#REF! -> #REF! | P51: =#REF! -> #REF! | Q51: =#REF! -> #REF! | R51: =#REF! -> #REF! | S51: =#REF! -> #REF! | T51: =#REF! -> #REF!
A52: 16 | B52: 6385 | C52: 18 | D52: 6492.5 | E52: 16 | F52: 6776 | G52: 16 | H52: 6728 | I52: 17 | J52: 7050 | K52: 16 | L52: 7823 | O52: =#REF! -> #REF! | P52: =#REF! -> #REF! | Q52: =#REF! -> #REF! | R52: =#REF! -> #REF! | S52: =#REF! -> #REF! | T52: =#REF! -> #REF!
... A60: 28 | B60: 6399.5 | C60: 28 | D60: 6728 | E60: 28 | F60: 6571.5 | G60: 28 | H60: 6694.5 | I60: 27 | J60: 7462 | K60: 30 | L60: 7803.5 | O60: =#REF! -> #REF! | P60: =#REF! -> #REF! | Q60: =#REF! -> #REF! | R60: =#REF! -> #REF! | S60: =#REF! -> #REF! | T60: =#REF! -> #REF!
A61: 29 | B61: 6475 | C61: 31 | E61: 29 | F61: 6546 | G61: 29 | H61: 6692 | I61: 30 | J61: 7674.5 | K61: 31 | L61: 7741.5 | O61: =#REF! -> #REF! | P61: =#REF! -> #REF! | Q61: =#REF! -> #REF! | R61: =#REF! -> #REF! | S61: =#REF! -> #REF! | T61: =#REF! -> #REF!
A62: 30 | B62: 6433.5 | E62: 30 | F62: 6610 | G62: 30 | H62: 6694.5 | O62: =#REF! -> #REF! | P62: =#REF! -> #REF! | Q62: =#REF! -> #REF! | R62: =#REF! -> #REF! | S62: =#REF! -> #REF! | T62: =#REF! -> #REF!
A63: 31 | B63: 6446.5 | O63: =#REF! -> #REF! | P63: =#REF! -> #REF! | Q63: =#REF! -> #REF! | R63: =#REF! -> #REF! | S63: =#REF! -> #REF! | T63: =#REF! -> #REF!
A64: =B65/L28-1 -> 0.10646698 | C64: =D65/B65-1 -> 0.022496775 | E64: =F65/D65-1 -> 0.033178383 | G64: =H65/F65-1 -> -0.0014119368 | I64: =J65/H65-1 -> 0.053806963 | K64: =L65/J65-1 -> 0.097942453 | O64: =#REF! -> #REF! | P64: =#REF! -> #REF! | Q64: =#REF! -> #REF! | R64: =#REF! -> #REF! | S64: =#REF! -> #REF! | T64: =#REF! -> #REF!
A65: MM | B65: =AVERAGE(B41:B63) -> 6353.7609 | C65: MM | D65: =AVERAGE(D41:D63) -> 6496.7 | E65: MM | F65: =AVERAGE(F41:F62) -> 6712.25 | G65: MM | H65: =AVERAGE(H41:H63) -> 6702.7727 | I65: MM | J65: =AVERAGE(J41:J62) -> 7063.4286 | K65: MM | L65: =AVERAGE(L41:L61) -> 7755.2381 | O65: =#REF! -> #REF! | P65: =#REF! -> #REF! | Q65: =#REF! -> #REF! | R65: =#REF! -> #REF! | S65: =#REF! -> #REF! | T65: =#REF! -> #REF!
A67: MM R$ | B67: =B65*A68 -> 33545.288 | C67: MM R$ | D67: =D65*C68 -> 35476.097 | E67: MM R$ | F67: =F65*E68 -> 36027.331 | G67: MM R$ | H67: =H65*G68 -> 37706.384 | I67: MM R$ | J67: =J65*I68 -> 38457.543 | K67: MM R$ | L67: =L65*K68 -> 39900.277
A68: 5.2795957 | B68: =B67/L29-1 -> 0.12426936 | C68: 5.4606333 | D68: =D67/B67-1 -> 0.057558257 | E68: 5.3674 | F68: =F67/D67-1 -> 0.015538183 | G68: 5.6254905 | H68: =H67/F67-1 -> 0.046604993 | I68: 5.4446 | J68: =J67/H67-1 -> 0.01992127 | K68: 5.1449455 | L68: =L67/J67-1 -> 0.037514975
E71: VARIAÇÃO COBRE LME - REAIS

Sheet Planilha2
A1: 6137.7 | B1: 3.7675 | C1: =B1*A1 -> 23123.785 | D1: 0.805 | E1: =C1*D1 -> 18614.647 | F1: 0.046 | G1: =E1*(1+F1) -> 19470.92 | H1: =G1/0.7875 -> 24724.978
A2: 6244 | B2: 3.7729 | C2: =B2*A2 -> 23557.988 | D2: 0.805 | E2: =C2*D2 -> 18964.18 | F2: 0.046 | G2: =E2*(1+F2) -> 19836.532 | H2: =G2/0.7875 -> 25189.247 | I2: =H2/1000 -> 25.189247

Sheet 2022
A1: Cobre LME Prices 2021 US$/Ton | O1: MÉDIAS
A2: Janeiro 2021 | C2: Fevereiro 2021 | E2: Março 2021 | G2: Abril 2021 | I2: Maio 2021 | K2: Junho 2021 | P2: US$ | Q2: Var (%) | R2: R$ | S2: Var Mês (%) | T2: Acumulado/Ano
B3: Cash | D3: Cash | F3: Cash | H3: Cash | J3: Cash | L3: Cash | O3: 41275 | P3: 8049.2455 | Q3: 0.010884092 | R3: 16364.921 | S3: -0.010958324
A4: 4 | B4: ='[1]2021_Base RPA'!$F$67 -> FERIADO | C4: 1 | D4: =IF('[1]2021_Base RPA'!$F87="","",'[1]2021_Base RPA'!$F87) -> 9700 | E4: 1 | F4: =IF('[1]2021_Base RPA'!$F107="","",'[1]2021_Base RPA'!$F107) -> 9974 | G4: 1 | H4: =IF('[1]2021_Base RPA'!$F130="","",'[1]2021_Base RPA'!$F130) -> 10246 | I4: 2 | J4: =IF('[1]2021_Base RPA'!$F151="","",'[1]2021_Base RPA'!$F151) -> FERIADO | K4: 1 | L4: =IF('[1]2021_Base RPA'!$F173="","",'[1]2021_Base RPA'!$F173) -> 9450 | O4: 41306 | P4: 8070.475 | Q4: 0.0026374578 | R4: 15912.556 | S4: -0.027642381
A5: 5 | B5: ='[1]2021_Base RPA'!$F68 -> 9773 | C5: 2 | D5: =IF('[1]2021_Base RPA'!$F88="","",'[1]2021_Base RPA'!$F88) -> 9875 | E5: 2 | F5: =IF('[1]2021_Base RPA'!$F108="","",'[1]2021_Base RPA'!$F108) -> 10257 | G5: 4 | H5: =IF('[1]2021_Base RPA'!$F131="","",'[1]2021_Base RPA'!$F131) -> 10300.5 | I5: 3 | J5: =IF('[1]2021_Base RPA'!$F152="","",'[1]2021_Base RPA'!$F152) -> 9510 | K5: 2 | L5: =IF('[1]2021_Base RPA'!$F174="","",'[1]2021_Base RPA'!$F174) -> FERIADO | O5: 41334 | P5: 7662.4 | Q5: -0.050563938 | R5: 15212.929 | S5: -0.043966954
A6: 6 | B6: ='[1]2021_Base RPA'!$F69 -> 9563 | C6: 3 | D6: =IF('[1]2021_Base RPA'!$F89="","",'[1]2021_Base RPA'!$F89) -> 9780 | E6: 3 | F6: =IF('[1]2021_Base RPA'!$F109="","",'[1]2021_Base RPA'!$F109) -> 10465 | G6: 5 | H6: =IF('[1]2021_Base RPA'!$F132="","",'[1]2021_Base RPA'!$F132) -> 10425 | I6: 4 | J6: =IF('[1]2021_Base RPA'!$F153="","",'[1]2021_Base RPA'!$F153) -> 9473 | K6: 3 | L6: =IF('[1]2021_Base RPA'!$F175="","",'[1]2021_Base RPA'!$F175) -> FERIADO | O6: 41365 | P6: 7203.3571 | Q6: -0.059908496 | R6: 14413.918 | S6: -0.052521859
A7: 7 | B7: =IF('[1]2021_Base RPA'!$F70="","",'[1]2021_Base RPA'!$F70) -> 9610 | C7: 4 | D7: =IF('[1]2021_Base RPA'!$F90="","",'[1]2021_Base RPA'!$F90) -> 9870 | E7: 4 | F7: =IF('[1]2021_Base RPA'!$F110="","",'[1]2021_Base RPA'!$F110) -> 10465 | G7: 6 | H7: =IF('[1]2021_Base RPA'!$F133="","",'[1]2021_Base RPA'!$F133) -> 10349.5 | I7: 5 | J7: =IF('[1]2021_Base RPA'!$F154="","",'[1]2021_Base RPA'!$F154) -> 9540 | K7: 6 | L7: =IF('[1]2021_Base RPA'!$F176="","",'[1]2021_Base RPA'!$F176) -> 9711 | O7: 41395 | P7: 7229.1429 | Q7: 0.0035796801 | R7: 14704.077 | S7: 0.020130469
A8: 10 | B8: =IF('[1]2021_Base RPA'!$F71="","",'[1]2021_Base RPA'!$F71) -> 9664.5 | C8: 7 | D8: =IF('[1]2021_Base RPA'!$F91="","",'[1]2021_Base RPA'!$F91) -> 9849 | E8: 7 | F8: =IF('[1]2021_Base RPA'!$F111="","",'[1]2021_Base RPA'!$F111) -> 10729 | G8: 7 | H8: =IF('[1]2021_Base RPA'!$F134="","",'[1]2021_Base RPA'!$F134) -> 10291 | I8: 6 | J8: =IF('[1]2021_Base RPA'!$F155="","",'[1]2021_Base RPA'!$F155) -> 9427.5 | K8: 7 | L8: =IF('[1]2021_Base RPA'!$F177="","",'[1]2021_Base RPA'!$F177) -> 9610 | O8: 41426 | P8: 7004.05 | Q8: -0.031136867 | R8: 15198.789 | S8: 0.033644542
A9: 11 | B9: =IF('[1]2021_Base RPA'!$F72="","",'[1]2021_Base RPA'!$F72) -> 9660 | C9: 8 | D9: =IF('[1]2021_Base RPA'!$F92="","",'[1]2021_Base RPA'!$F92) -> 9755 | E9: 8 | F9: =IF('[1]2021_Base RPA'!$F112="","",'[1]2021_Base RPA'!$F112) -> 10170 | G9: 8 | H9: =IF('[1]2021_Base RPA'!$F135="","",'[1]2021_Base RPA'!$F135) -> 10385 | I9: 9 | J9: =IF('[1]2021_Base RPA'!$F156="","",'[1]2021_Base RPA'!$F156) -> 9159 | K9: 8 | L9: =IF('[1]2021_Base RPA'!$F178="","",'[1]2021_Base RPA'!$F178) -> 9690 | O9: 41456 | P9: 6896.9773 | Q9: -0.015287259 | R9: 15536.683 | S9: 0.022231658
A10: 12 | B10: =IF('[1]2021_Base RPA'!$F73="","",'[1]2021_Base RPA'!$F73) -> 9943 | C10: 9 | D10: =IF('[1]2021_Base RPA'!$F93="","",'[1]2021_Base RPA'!$F93) -> 9880 | E10: 9 | F10: =IF('[1]2021_Base RPA'!$F113="","",'[1]2021_Base RPA'!$F113) -> 10050 | G10: 11 | H10: =IF('[1]2021_Base RPA'!$F136="","",'[1]2021_Base RPA'!$F136) -> 10235 | I10: 10 | J10: =IF('[1]2021_Base RPA'!$F157="","",'[1]2021_Base RPA'!$F157) -> 9345 | K10: 9 | L10: =IF('[1]2021_Base RPA'!$F179="","",'[1]2021_Base RPA'!$F179) -> 9628 | O10: 41487 | P10: 7182.2619 | Q10: 0.041363719 | R10: 16802.902 | S10: 0.081498669
A11: 13 | B11: =IF('[1]2021_Base RPA'!$F74="","",'[1]2021_Base RPA'!$F74) -> 9971 | C11: 10 | D11: =IF('[1]2021_Base RPA'!$F94="","",'[1]2021_Base RPA'!$F94) -> 10219.5 | E11: 10 | F11: =IF('[1]2021_Base RPA'!$F114="","",'[1]2021_Base RPA'!$F114) -> 10143 | G11: 12 | H11: =IF('[1]2021_Base RPA'!$F137="","",'[1]2021_Base RPA'!$F137) -> 10200 | I11: 11 | J11: =IF('[1]2021_Base RPA'!$F158="","",'[1]2021_Base RPA'!$F158) -> 9365 | K11: 10 | L11: =IF('[1]2021_Base RPA'!$F180="","",'[1]2021_Base RPA'!$F180) -> 9536.5 | O11: 41518 | P11: 7161.4286 | Q11: -0.0029006647 | R11: 16264.32 | S11: -0.032052874
A12: 14 | B12: =IF('[1]2021_Base RPA'!$F75="","",'[1]2021_Base RPA'!$F75) -> 9895 | C12: 11 | D12: =IF('[1]2021_Base RPA'!$F95="","",'[1]2021_Base RPA'!$F95) -> 10039 | E12: 11 | F12: =IF('[1]2021_Base RPA'!$F115="","",'[1]2021_Base RPA'!$F115) -> 10140 | G12: 13 | H12: =IF('[1]2021_Base RPA'!$F138="","",'[1]2021_Base RPA'!$F138) -> 10290 | I12: 12 | J12: =IF('[1]2021_Base RPA'!$F159="","",'[1]2021_Base RPA'!$F159) -> 9018 | K12: 13 | L12: =IF('[1]2021_Base RPA'!$F181="","",'[1]2021_Base RPA'!$F181) -> 9289 | O12: 41548 | P12: 7188.7826 | Q12: 0.0038196342 | R12: 15720.43 | S12: -0.033440722
A13: 17 | B13: =IF('[1]2021_Base RPA'!$F76="","",'[1]2021_Base RPA'!$F76) -> 9674 | C13: 14 | D13: =IF('[1]2021_Base RPA'!$F96="","",'[1]2021_Base RPA'!$F96) -> 9877 | E13: 14 | F13: =IF('[1]2021_Base RPA'!$F116="","",'[1]2021_Base RPA'!$F116) -> 9875 | G13: 14 | H13: =IF('[1]2021_Base RPA'!$F139="","",'[1]2021_Base RPA'!$F139) -> 10276 | I13: 13 | J13: =IF('[1]2021_Base RPA'!$F160="","",'[1]2021_Base RPA'!$F160) -> 9063 | K13: 14 | L13: =IF('[1]2021_Base RPA'!$F182="","",'[1]2021_Base RPA'!$F182) -> 9262.5 | O13: 41579 | P13: 7066.4048 | Q13: -0.017023445 | R13: 16235.772 | S13: 0.032781659
A14: 18 | B14: =IF('[1]2021_Base RPA'!$F77="","",'[1]2021_Base RPA'!$F77) -> 9705 | C14: 15 | D14: =IF('[1]2021_Base RPA'!$F97="","",'[1]2021_Base RPA'!$F97) -> 10015 | E14: 15 | F14: =IF('[1]2021_Base RPA'!$F117="","",'[1]2021_Base RPA'!$F117) -> 9824 | G14: 15 | H14: =IF('[1]2021_Base RPA'!$F140="","",'[1]2021_Base RPA'!$F140) -> FERIADO | I14: 16 | J14: =IF('[1]2021_Base RPA'!$F161="","",'[1]2021_Base RPA'!$F161) -> 9265 | K14: 15 | L14: =IF('[1]2021_Base RPA'!$F183="","",'[1]2021_Base RPA'!$F183) -> 9256 | O14: 41609 | P14: 7202.95 | Q14: 0.019323156 | R14: 16911.086 | S14: 0.041594231
A15: 19 | B15: =IF('[1]2021_Base RPA'!$F78="","",'[1]2021_Base RPA'!$F78) -> 9799 | C15: 16 | D15: =IF('[1]2021_Base RPA'!$F98="","",'[1]2021_Base RPA'!$F98) -> 10045 | E15: 16 | F15: =IF('[1]2021_Base RPA'!$F118="","",'[1]2021_Base RPA'!$F118) -> 10100 | G15: 18 | H15: =IF('[1]2021_Base RPA'!$F141="","",'[1]2021_Base RPA'!$F141) -> FERIADO | I15: 17 | J15: =IF('[1]2021_Base RPA'!$F162="","",'[1]2021_Base RPA'!$F162) -> 9394 | K15: 16 | L15: =IF('[1]2021_Base RPA'!$F184="","",'[1]2021_Base RPA'!$F184) -> 9100 | O15: 41640 | P15: 7294.8864 | Q15: 0.01276371 | R15: 17368.395 | S15: 0.027041961 | T15: 0.027041961
A16: 20 | B16: =IF('[1]2021_Base RPA'!$F79="","",'[1]2021_Base RPA'!$F79) -> 9920 | C16: 17 | D16: =IF('[1]2021_Base RPA'!$F99="","",'[1]2021_Base RPA'!$F99) -> 10005 | E16: 17 | F16: =IF('[1]2021_Base RPA'!$F119="","",'[1]2021_Base RPA'!$F119) -> FERIADO | G16: 19 | H16: =IF('[1]2021_Base RPA'!$F142="","",'[1]2021_Base RPA'!$F142) -> 10380.5 | I16: 18 | J16: =IF('[1]2021_Base RPA'!$F163="","",'[1]2021_Base RPA'!$F163) -> 9264 | K16: 17 | L16: =IF('[1]2021_Base RPA'!$F185="","",'[1]2021_Base RPA'!$F185) -> 9100 | O16: 41671 | P16: 7152.15 | Q16: -0.019566633 | R16: 17062.884 | S16: -0.017590036 | T16: 0.0089762565
A17: 21 | B17: =IF('[1]2021_Base RPA'!$F80="","",'[1]2021_Base RPA'!$F80) -> 9965 | C17: 18 | D17: =IF('[1]2021_Base RPA'!$F100="","",'[1]2021_Base RPA'!$F100) -> 10010 | E17: 18 | F17: =IF('[1]2021_Base RPA'!$F120="","",'[1]2021_Base RPA'!$F120) -> 10247 | G17: 20 | H17: =IF('[1]2021_Base RPA'!$F143="","",'[1]2021_Base RPA'!$F143) -> 10210 | I17: 19 | J17: =IF('[1]2021_Base RPA'!$F164="","",'[1]2021_Base RPA'!$F164) -> 9286 | K17: 20 | L17: =IF('[1]2021_Base RPA'!$F186="","",'[1]2021_Base RPA'!$F186) -> 8870 | O17: 41699 | P17: 6667.8095 | Q17: -0.067719564 | R17: 15507.991 | S17: -0.0911272 | T17: -0.082968925
A18: 24 | B18: =IF('[1]2021_Base RPA'!$F81="","",'[1]2021_Base RPA'!$F81) -> 9799.5 | C18: 19 | D18: =IF('[1]2021_Base RPA'!$F101="","",'[1]2021_Base RPA'!$F101) -> 9959.5 | E18: 21 | F18: =IF('[1]2021_Base RPA'!$F121="","",'[1]2021_Base RPA'!$F121) -> 10172 | G18: 21 | H18: =IF('[1]2021_Base RPA'!$F144="","",'[1]2021_Base RPA'!$F144) -> 10267 | I18: 20 | J18: =IF('[1]2021_Base RPA'!$F165="","",'[1]2021_Base RPA'!$F165) -> 9475 | K18: 21 | L18: =IF('[1]2021_Base RPA'!$F187="","",'[1]2021_Base RPA'!$F187) -> 8995 | O18: 41730 | P18: 6670.825 | Q18: 0.0004522439 | R18: 14896.619 | S18: -0.039423035 | T18: -0.11912107
A19: 25 | B19: =IF('[1]2021_Base RPA'!$F82="","",'[1]2021_Base RPA'!$F82) -> 9743 | C19: 22 | D19: =IF('[1]2021_Base RPA'!$F102="","",'[1]2021_Base RPA'!$F102) -> 10018 | E19: 22 | F19: =IF('[1]2021_Base RPA'!$F122="","",'[1]2021_Base RPA'!$F122) -> 10340 | G19: 22 | H19: =IF('[1]2021_Base RPA'!$F145="","",'[1]2021_Base RPA'!$F145) -> 10230 | I19: 23 | J19: =IF('[1]2021_Base RPA'!$F166="","",'[1]2021_Base RPA'!$F166) -> 9499.5 | K19: 22 | L19: =IF('[1]2021_Base RPA'!$F188="","",'[1]2021_Base RPA'!$F188) -> 8727 | O19: 41760 | P19: 6883.875 | Q19: 0.031937579 | R19: 15289.775 | S19: 0.02639226 | T19: -0.095872687
A20: 26 | B20: =IF('[1]2021_Base RPA'!$F83="","",'[1]2021_Base RPA'!$F83) -> 9960 | C20: 23 | D20: =IF('[1]2021_Base RPA'!$F103="","",'[1]2021_Base RPA'!$F103) -> 10003 | E20: 23 | F20: =IF('[1]2021_Base RPA'!$F123="","",'[1]2021_Base RPA'!$F123) -> 10310 | G20: 25 | H20: =IF('[1]2021_Base RPA'!$F146="","",'[1]2021_Base RPA'!$F146) -> 9917 | I20: 24 | J20: =IF('[1]2021_Base RPA'!$F167="","",'[1]2021_Base RPA'!$F167) -> 9459.5 | K20: 23 | L20: =IF('[1]2021_Base RPA'!$F189="","",'[1]2021_Base RPA'!$F189) -> 8575 | O20: 41791 | P20: 6806.0952 | Q20: -0.011298834 | R20: 15206.178 | S20: -0.0054674959 | T20: -0.100816
A21: 27 | B21: =IF('[1]2021_Base RPA'!$F84="","",'[1]2021_Base RPA'!$F84) -> 9870 | C21: 24 | D21: =IF('[1]2021_Base RPA'!$F104="","",'[1]2021_Base RPA'!$F104) -> 9982 | E21: 24 | F21: =IF('[1]2021_Base RPA'!$F124="","",'[1]2021_Base RPA'!$F124) -> 10420 | G21: 26 | H21: =IF('[1]2021_Base RPA'!$F147="","",'[1]2021_Base RPA'!$F147) -> 9911.5 | I21: 25 | J21: =IF('[1]2021_Base RPA'!$F168="","",'[1]2021_Base RPA'!$F168) -> 9285 | K21: 24 | L21: =IF('[1]2021_Base RPA'!$F190="","",'[1]2021_Base RPA'!$F190) -> 8280 | O21: 41821 | P21: 7104.8478 | Q21: 0.043894859 | R21: 15807.576 | S21: 0.03954958 | T21: -0.06525365
A22: 28 | B22: =IF('[1]2021_Base RPA'!$F85="","",'[1]2021_Base RPA'!$F85) -> 9677 | C22: 25 | D22: =IF('[1]2021_Base RPA'!$F105="","",'[1]2021_Base RPA'!$F105) -> 9918 | E22: 25 | F22: =IF('[1]2021_Base RPA'!$F125="","",'[1]2021_Base RPA'!$F125) -> 10278 | G22: 27 | H22: =IF('[1]2021_Base RPA'!$F148="","",'[1]2021_Base RPA'!$F148) -> 9905 | I22: 26 | J22: =IF('[1]2021_Base RPA'!$F169="","",'[1]2021_Base RPA'!$F169) -> 9358 | K22: 27 | L22: =IF('[1]2021_Base RPA'!$F191="","",'[1]2021_Base RPA'!$F191) -> 8352 | O22: 41852 | P22: 7000.55 | Q22: -0.014679811 | R22: 15880.048 | S22: 0.0045846177 | T22: -0.060968195
A23: 31 | B23: =IF('[1]2021_Base RPA'!$F86="","",'[1]2021_Base RPA'!$F86) -> 9615 | C23: 28 | D23: =IF('[1]2021_Base RPA'!$F106="","",'[1]2021_Base RPA'!$F106) -> 9972 | E23: 28 | F23: =IF('[1]2021_Base RPA'!$F126="","",'[1]2021_Base RPA'!$F126) -> 10225 | G23: 28 | H23: =IF('[1]2021_Base RPA'!$F149="","",'[1]2021_Base RPA'!$F149) -> 9810 | I23: 27 | J23: =IF('[1]2021_Base RPA'!$F170="","",'[1]2021_Base RPA'!$F170) -> 9382 | K23: 28 | L23: =IF('[1]2021_Base RPA'!$F192="","",'[1]2021_Base RPA'!$F192) -> 8500 | O23: 41883 | P23: 6872.2273 | Q23: -0.018330378 | R23: 16046.651 | S23: 0.010491345 | T23: -0.051116488
E24: 29 | F24: =IF('[1]2021_Base RPA'!$F127="","",'[1]2021_Base RPA'!$F127) -> 10348 | G24: 29 | H24: =IF('[1]2021_Base RPA'!$F150="","",'[1]2021_Base RPA'!$F150) -> 9820 | I24: 30 | J24: =IF('[1]2021_Base RPA'!$F171="","",'[1]2021_Base RPA'!$F171) -> 9520 | K24: 29 | L24: =IF('[1]2021_Base RPA'!$F193="","",'[1]2021_Base RPA'!$F193) -> 8445 | O24: 41913 | P24: 6739.1957 | Q24: -0.019357861 | R24: 16515.747 | S24: 0.029233272 | T24: -0.023377518
E25: 30 | F25: =IF('[1]2021_Base RPA'!$F128="","",'[1]2021_Base RPA'!$F128) -> 10390 | G25: 30 | H25: =IF('[1]2021_Base RPA'!$F151="","",'[1]2021_Base RPA'!$F151) -> FERIADO | I25: 31 | J25: =IF('[1]2021_Base RPA'!$F172="","",'[1]2021_Base RPA'!$F172) -> 9500 | K25: 30 | L25: =IF('[1]2021_Base RPA'!$F194="","",'[1]2021_Base RPA'!$F194) -> 8240
E26: 31 | F26: =IF('[1]2021_Base RPA'!$F129="","",'[1]2021_Base RPA'!$F129) -> 10336.5 | O26: 41944 | P26: 6701.135 | Q26: -0.005647655 | R26: 17154.906 | S26: 0.038699965 | T26: 0.014417737
A27: =B28/'2020'!L65-1 -> 0.26099491 | C27: =D28/B28-1 -> 0.016287869 | E27: =F28/D28-1 -> 0.030227872 | G27: =H28/F28-1 -> -0.0056154199 | I27: =J28/H28-1 -> -0.080554639 | K27: =L28/J28-1 -> -0.035305473 | O27: 41974 | P27: 6422.9524 | Q27: -0.041512762 | R27: 16968.798 | S27: -0.010848658 | T27: 0.0034126658
A28: MM | B28: =AVERAGE(B4:B24) -> 9779.3158 | C28: MM | D28: =AVERAGE(D4:D23) -> 9938.6 | E28: MM | F28: =AVERAGE(F4:F26) -> 10239.023 | G28: MM | H28: =AVERAGE(H4:H24) -> 10181.526 | I28: MM | J28: =AVERAGE(J4:J25) -> 9361.3571 | K28: MM | L28: =AVERAGE(L4:L25) -> 9030.85 | O28: 42005 | P28: 5791.175 | Q28: -0.098362458 | R28: 15271.908 | S28: -0.10000062 | T28: -0.10000062
A29: MM R$ | B29: =B28*A30 -> 54066.561 | C29: MM R$ | D29: =D28*C30 -> 51612.342 | E29: MM R$ | F29: =F28*E30 -> 50784.139 | G29: MM R$ | H29: =H28*G30 -> 48574.484 | I29: MM R$ | J29: =J28*I30 -> 46348.48 | K29: MM R$ | L29: =L28*K30 -> 45593.235 | O29: 42036 | P29: 5702.075 | Q29: -0.015385479 | R29: 16059.837 | S29: 0.051593399 | T29: -0.053566592
A30: =AVERAGE('[1]2021_Base RPA'!$B$67:$B$86) -> 5.528665 | B30: =A30/'2021'!K68-1 -> -0.021579877 | C30: =AVERAGE('[1]2021_Base RPA'!$B$87:$B$106) -> 5.19312 | D30: =D29/B29-1 -> -0.045392539 | E30: =AVERAGE('[1]2021_Base RPA'!$B$107:$B$129) -> 4.9598619 | F30: =F29/D29-1 -> -0.01604662 | G30: =AVERAGE('[1]2021_Base RPA'!$B$130:$B$151) -> 4.770845 | H30: =H29/F29-1 -> -0.043510728 | I30: =AVERAGE('[1]2021_Base RPA'!$B$152:$B$172) -> 4.9510429 | J30: =J29/H29-1 -> -0.045826601 | K30: =AVERAGE('[1]2021_Base RPA'!$B$173:$B$194) -> 5.0486095 | L30: =L29/J29-1 -> -0.016294927 | O30: 42064 | P30: 5919.9048 | Q30: 0.038201841 | R30: 18601.525 | S30: 0.15826359 | T30: 0.096219358
A31: Cobre LME Prices 2021 US$/Ton | O31: MÉDIAS
A32: Julho 2021 | C32: Agosto 2021 | E32: Setembro 2021 | G32: Outubro 2021 | I32: Novembro 2021 | K32: Dezembro 2021 | O32: 42125 | P32: 6300.6053 | Q32: 0.04514038 | R32: 19242.048 | S32: 0.045653962 | T32: 0.13396651
B33: Cash | D33: Cash | F33: Cash | H33: Cash | J33: Cash | L33: Cash | O33: 42156 | P33: 5833.6136 | Q33: -0.074118534 | R33: 18168.79 | S33: -0.055776744 | T33: 0.070717548
A34: Média | B34: #DIV/0! | C34: Média | D34: #DIV/0! | E34: Média | F34: #DIV/0! | G34: Média | H34: #DIV/0! | I34: Média | J34: #DIV/0! | K34: Média | L34: #DIV/0! | O34: 42675 | T34: #DIV/0!
A35: MM | B35: #DIV/0! | C35: MM | D35: #DIV/0! | E35: MM | F35: #DIV/0! | G35: MM | H35: #DIV/0! | I35: MM | J35: #DIV/0! | K35: MM | L35: #DIV/0! | O35: 42705 | T35: #DIV/0!
A36: #DIV/0! | C36: #DIV/0! | E36: #DIV/0! | G36: #DIV/0! | I36: #DIV/0! | K36: #DIV/0! | O36: 42736 | T36: #DIV/0!
A37: MM R$ | B37: #DIV/0! | C37: MM R$ | D37: #DIV/0! | E37: MM R$ | F37: #DIV/0! | G37: MM R$ | H37: #DIV/0! | I37: MM R$ | J37: #DIV/0! | K37: MM R$ | L37: #DIV/0! | O37: 42767 | T37: #DIV/0!
B38: #DIV/0! | D38: #DIV/0! | F38: #DIV/0! | H38: #DIV/0! | J38: #DIV/0! | L38: #DIV/0! | O38: 42795 | T38: #DIV/0!
A39: Julho 2016 | C39: Agosto 2016 | E39: Setembro 2016 | G39: Outubro 2016 | I39: Novembro 2016 | K39: Dezembro 2016 | O39: 42826 | T39: #DIV/0!
B40: Cash | D40: Cash | F40: Cash | H40: Cash | J40: Cash | L40: Cash | O40: 42856 | T40: #DIV/0!
A41: 1 | B41: =IF('[1]2021_Base RPA'!$F195="","",'[1]2021_Base RPA'!$F195) -> 7975 | C41: 1 | D41: =IF('[1]2021_Base RPA'!$F216="","",'[1]2021_Base RPA'!$F216) -> 7929.5 | E41: 1 | F41: =IF('[1]2021_Base RPA'!$F239="","",'[1]2021_Base RPA'!$F239) -> 7701 | G41: 3 | H41: =IF('[1]2021_Base RPA'!$F261="","",'[1]2021_Base RPA'!$F261) -> 7522 | I41: 1 | J41: =IF('[1]2021_Base RPA'!$F282="","",'[1]2021_Base RPA'!$F282) -> 7740 | K41: 1 | L41: =IF('[1]2021_Base RPA'!$F303="","",'[1]2021_Base RPA'!$F303) -> 8341 | O41: =#REF! -> #REF! | P41: =#REF! -> #REF! | Q41: =#REF! -> #REF! | R41: =#REF! -> #REF! | S41: =#REF! -> #REF! | T41: =#REF! -> #REF!
A42: 4 | B42: =IF('[1]2021_Base RPA'!$F196="","",'[1]2021_Base RPA'!$F196) -> 8034 | C42: 2 | D42: =IF('[1]2021_Base RPA'!$F217="","",'[1]2021_Base RPA'!$F217) -> 7818 | E42: 2 | F42: =IF('[1]2021_Base RPA'!$F240="","",'[1]2021_Base RPA'!$F240) -> 7585 | G42: 4 | H42: =IF('[1]2021_Base RPA'!$F262="","",'[1]2021_Base RPA'!$F262) -> 7595.5 | I42: 2 | J42: =IF('[1]2021_Base RPA'!$F283="","",'[1]2021_Base RPA'!$F283) -> 7700 | K42: 2 | L42: =IF('[1]2021_Base RPA'!$F304="","",'[1]2021_Base RPA'!$F304) -> 8439.5 | O42: =#REF! -> #REF! | P42: =#REF! -> #REF! | Q42: =#REF! -> #REF! | R42: =#REF! -> #REF! | S42: =#REF! -> #REF! | T42: =#REF! -> #REF! | U42: =261+21 -> 282
A43: 5 | B43: =IF('[1]2021_Base RPA'!$F197="","",'[1]2021_Base RPA'!$F197) -> 7806 | C43: 3 | D43: =IF('[1]2021_Base RPA'!$F218="","",'[1]2021_Base RPA'!$F218) -> 7773 | E43: 3 | F43: =IF('[1]2021_Base RPA'!$F241="","",'[1]2021_Base RPA'!$F241) -> 7652 | G43: 5 | H43: =IF('[1]2021_Base RPA'!$F263="","",'[1]2021_Base RPA'!$F263) -> 7660 | I43: 3 | J43: =IF('[1]2021_Base RPA'!$F284="","",'[1]2021_Base RPA'!$F284) -> 7509 | K43: 5 | L43: =IF('[1]2021_Base RPA'!$F305="","",'[1]2021_Base RPA'!$F305) -> 8355 | O43: =#REF! -> #REF! | P43: =#REF! -> #REF! | Q43: =#REF! -> #REF! | R43: =#REF! -> #REF! | S43: =#REF! -> #REF! | T43: =#REF! -> #REF!
A44: 6 | B44: =IF('[1]2021_Base RPA'!$F198="","",'[1]2021_Base RPA'!$F198) -> 7525 | C44: 4 | D44: =IF('[1]2021_Base RPA'!$F219="","",'[1]2021_Base RPA'!$F219) -> 7640 | E44: 6 | F44: =IF('[1]2021_Base RPA'!$F242="","",'[1]2021_Base RPA'!$F242) -> 7705 | G44: 6 | H44: =IF('[1]2021_Base RPA'!$F264="","",'[1]2021_Base RPA'!$F264) -> 7743 | I44: 4 | J44: =IF('[1]2021_Base RPA'!$F285="","",'[1]2021_Base RPA'!$F285) -> 7900 | K44: 6 | L44: =IF('[1]2021_Base RPA'!$F306="","",'[1]2021_Base RPA'!$F306) -> 8333 | O44: =#REF! -> #REF! | P44: =#REF! -> #REF! | Q44: =#REF! -> #REF! | R44: =#REF! -> #REF! | S44: =#REF! -> #REF! | T44: =#REF! -> #REF!
A45: 7 | B45: =IF('[1]2021_Base RPA'!$F199="","",'[1]2021_Base RPA'!$F199) -> 7833 | C45: 5 | D45: =IF('[1]2021_Base RPA'!$F220="","",'[1]2021_Base RPA'!$F220) -> 7830 | E45: 7 | F45: =IF('[1]2021_Base RPA'!$F243="","",'[1]2021_Base RPA'!$F243) -> 7728 | G45: 7 | H45: =IF('[1]2021_Base RPA'!$F265="","",'[1]2021_Base RPA'!$F265) -> 7574.5 | I45: 7 | J45: =IF('[1]2021_Base RPA'!$F286="","",'[1]2021_Base RPA'!$F286) -> 7953.5 | K45: 7 | L45: =IF('[1]2021_Base RPA'!$F307="","",'[1]2021_Base RPA'!$F307) -> 8536.5 | O45: =#REF! -> #REF! | P45: =#REF! -> #REF! | Q45: =#REF! -> #REF! | R45: =#REF! -> #REF! | S45: =#REF! -> #REF! | T45: =#REF! -> #REF!
A46: 8 | B46: =IF('[1]2021_Base RPA'!$F200="","",'[1]2021_Base RPA'!$F200) -> 7785 | C46: 8 | D46: =IF('[1]2021_Base RPA'!$F221="","",'[1]2021_Base RPA'!$F221) -> 7834 | E46: 8 | F46: =IF('[1]2021_Base RPA'!$F244="","",'[1]2021_Base RPA'!$F244) -> 7905 | G46: 10 | H46: =IF('[1]2021_Base RPA'!$F266="","",'[1]2021_Base RPA'!$F266) -> 7650 | I46: 8 | J46: =IF('[1]2021_Base RPA'!$F287="","",'[1]2021_Base RPA'!$F287) -> 7972 | K46: 8 | L46: =IF('[1]2021_Base RPA'!$F308="","",'[1]2021_Base RPA'!$F308) -> 8490 | O46: =#REF! -> #REF! | P46: =#REF! -> #REF! | Q46: =#REF! -> #REF! | R46: =#REF! -> #REF! | S46: =#REF! -> #REF! | T46: =#REF! -> #REF!
A47: 11 | B47: =IF('[1]2021_Base RPA'!$F201="","",'[1]2021_Base RPA'!$F201) -> 7622 | C47: 9 | D47: =IF('[1]2021_Base RPA'!$F222="","",'[1]2021_Base RPA'!$F222) -> 7971 | E47: 9 | F47: =IF('[1]2021_Base RPA'!$F245="","",'[1]2021_Base RPA'!$F245) -> 7984 | G47: 11 | H47: =IF('[1]2021_Base RPA'!$F267="","",'[1]2021_Base RPA'!$F267) -> 7585 | I47: 9 | J47: =IF('[1]2021_Base RPA'!$F288="","",'[1]2021_Base RPA'!$F288) -> 8033 | K47: 9 | L47: =IF('[1]2021_Base RPA'!$F309="","",'[1]2021_Base RPA'!$F309) -> 8370.5 | O47: =#REF! -> #REF! | P47: =#REF! -> #REF! | Q47: =#REF! -> #REF! | R47: =#REF! -> #REF! | S47: =#REF! -> #REF! | T47: =#REF! -> #REF!
A48: 12 | B48: =IF('[1]2021_Base RPA'!$F202="","",'[1]2021_Base RPA'!$F202) -> 7370 | C48: 10 | D48: =IF('[1]2021_Base RPA'!$F223="","",'[1]2021_Base RPA'!$F223) -> 7975 | E48: 10 | F48: =IF('[1]2021_Base RPA'!$F246="","",'[1]2021_Base RPA'!$F246) -> 8024 | G48: 12 | H48: =IF('[1]2021_Base RPA'!$F268="","",'[1]2021_Base RPA'!$F268) -> 7625 | I48: 10 | J48: =IF('[1]2021_Base RPA'!$F289="","",'[1]2021_Base RPA'!$F289) -> 8060 | K48: 12 | L48: =IF('[1]2021_Base RPA'!$F310="","",'[1]2021_Base RPA'!$F310) -> 8380 | O48: =#REF! -> #REF! | P48: =#REF! -> #REF! | Q48: =#REF! -> #REF! | R48: =#REF! -> #REF! | S48: =#REF! -> #REF! | T48: =#REF! -> #REF!
A49: 13 | B49: =IF('[1]2021_Base RPA'!$F203="","",'[1]2021_Base RPA'!$F203) -> 7265 | C49: 11 | D49: =IF('[1]2021_Base RPA'!$F224="","",'[1]2021_Base RPA'!$F224) -> 8138 | E49: 13 | F49: =IF('[1]2021_Base RPA'!$F247="","",'[1]2021_Base RPA'!$F247) -> 8225 | G49: 13 | H49: =IF('[1]2021_Base RPA'!$F269="","",'[1]2021_Base RPA'!$F269) -> 7662 | I49: 11 | J49: =IF('[1]2021_Base RPA'!$F290="","",'[1]2021_Base RPA'!$F290) -> 8440 | K49: 13 | L49: =IF('[1]2021_Base RPA'!$F311="","",'[1]2021_Base RPA'!$F311) -> 8414 | O49: =#REF! -> #REF! | P49: =#REF! -> #REF! | Q49: =#REF! -> #REF! | R49: =#REF! -> #REF! | S49: =#REF! -> #REF! | T49: =#REF! -> #REF!
A50: 14 | B50: =IF('[1]2021_Base RPA'!$F204="","",'[1]2021_Base RPA'!$F204) -> 7215.5 | C50: 12 | D50: =IF('[1]2021_Base RPA'!$F225="","",'[1]2021_Base RPA'!$F225) -> 8060 | E50: 14 | F50: =IF('[1]2021_Base RPA'!$F248="","",'[1]2021_Base RPA'!$F248) -> 7860 | G50: 14 | H50: =IF('[1]2021_Base RPA'!$F270="","",'[1]2021_Base RPA'!$F270) -> 7687.5 | I50: 14 | J50: =IF('[1]2021_Base RPA'!$F291="","",'[1]2021_Base RPA'!$F291) -> 8345 | K50: 14 | L50: =IF('[1]2021_Base RPA'!$F312="","",'[1]2021_Base RPA'!$F312) -> 8414 | O50: =#REF! -> #REF! | P50: =#REF! -> #REF! | Q50: =#REF! -> #REF! | R50: =#REF! -> #REF! | S50: =#REF! -> #REF! | T50: =#REF! -> #REF!
A51: 15 | B51: =IF('[1]2021_Base RPA'!$F205="","",'[1]2021_Base RPA'!$F205) -> 6998 | C51: 15 | D51: =IF('[1]2021_Base RPA'!$F226="","",'[1]2021_Base RPA'!$F226) -> 7865 | E51: 15 | F51: =IF('[1]2021_Base RPA'!$F249="","",'[1]2021_Base RPA'!$F249) -> 7805.5 | G51: 17 | H51: =IF('[1]2021_Base RPA'!$F271="","",'[1]2021_Base RPA'!$F271) -> 7710 | I51: 15 | J51: =IF('[1]2021_Base RPA'!$F292="","",'[1]2021_Base RPA'!$F292) -> 8342.5 | K51: 15 | L51: =IF('[1]2021_Base RPA'!$F313="","",'[1]2021_Base RPA'!$F313) -> 8329 | O51: =#REF! -> #REF! | P51: =#REF! -> #REF! | Q51: =#REF! -> #REF! | R51: =#REF! -> #REF! | S51: =#REF! -> #REF! | T51: =#REF! -> #REF!
A52: 18 | B52: =IF('[1]2021_Base RPA'!$F206="","",'[1]2021_Base RPA'!$F206) -> 7318 | C52: 16 | D52: =IF('[1]2021_Base RPA'!$F227="","",'[1]2021_Base RPA'!$F227) -> 7991 | E52: 16 | F52: =IF('[1]2021_Base RPA'!$F250="","",'[1]2021_Base RPA'!$F250) -> 7790 | G52: 18 | H52: =IF('[1]2021_Base RPA'!$F272="","",'[1]2021_Base RPA'!$F272) -> 7535 | I52: 16 | J52: =IF('[1]2021_Base RPA'!$F293="","",'[1]2021_Base RPA'!$F293) -> 8314 | K52: 16 | L52: =IF('[1]2021_Base RPA'!$F314="","",'[1]2021_Base RPA'!$F314) -> 8301 | O52: =#REF! -> #REF! | P52: =#REF! -> #REF! | Q52: =#REF! -> #REF! | R52: =#REF! -> #REF! | S52: =#REF! -> #REF! | T52: =#REF! -> #REF!
A53: 19 | B53: =IF('[1]2021_Base RPA'!$F207="","",'[1]2021_Base RPA'!$F207) -> 7280.5 | C53: 17 | D53: =IF('[1]2021_Base RPA'!$F228="","",'[1]2021_Base RPA'!$F228) -> 7953 | E53: 17 | F53: =IF('[1]2021_Base RPA'!$F251="","",'[1]2021_Base RPA'!$F251) -> 7770 | G53: 19 | H53: =IF('[1]2021_Base RPA'!$F273="","",'[1]2021_Base RPA'!$F273) -> 7415 | I53: 17 | J53: =IF('[1]2021_Base RPA'!$F294="","",'[1]2021_Base RPA'!$F294) -> 8153 | K53: 19 | L53: =IF('[1]2021_Base RPA'!$F315="","",'[1]2021_Base RPA'!$F315) -> 8326 | O53: =#REF! -> #REF! | P53: =#REF! -> #REF! | Q53: =#REF! -> #REF! | R53: =#REF! -> #REF! | S53: =#REF! -> #REF! | T53: =#REF! -> #REF!
A54: 20 | B54: =IF('[1]2021_Base RPA'!$F208="","",'[1]2021_Base RPA'!$F208) -> 7370 | C54: 18 | D54: =IF('[1]2021_Base RPA'!$F229="","",'[1]2021_Base RPA'!$F229) -> 8015 | E54: 20 | F54: =IF('[1]2021_Base RPA'!$F252="","",'[1]2021_Base RPA'!$F252) -> 7795 | G54: 20 | H54: =IF('[1]2021_Base RPA'!$F274="","",'[1]2021_Base RPA'!$F274) -> 7585 | I54: 18 | J54: =IF('[1]2021_Base RPA'!$F295="","",'[1]2021_Base RPA'!$F295) -> 8046.5 | K54: 20 | L54: =IF('[1]2021_Base RPA'!$F316="","",'[1]2021_Base RPA'!$F316) -> 8344.5 | O54: =#REF! -> #REF! | P54: =#REF! -> #REF! | Q54: =#REF! -> #REF! | R54: =#REF! -> #REF! | S54: =#REF! -> #REF! | T54: =#REF! -> #REF!
... A61: 29 | B61: =IF('[1]2021_Base RPA'!$F215="","",'[1]2021_Base RPA'!$F215) -> 7800 | C61: 29 | D61: =IF('[1]2021_Base RPA'!$F236="","",'[1]2021_Base RPA'!$F236) -> FERIADO | E61: 29 | F61: =IF('[1]2021_Base RPA'!$F259="","",'[1]2021_Base RPA'!$F259) -> 7660 | G61: 31 | H61: =IF('[1]2021_Base RPA'!$F281="","",'[1]2021_Base RPA'!$F281) -> 7520 | I61: 30 | J61: =IF('[1]2021_Base RPA'!$F302="","",'[1]2021_Base RPA'!$F302) -> FERIADO | K61: 29 | L61: =IF('[1]2021_Base RPA'!$F323="","",'[1]2021_Base RPA'!$F323) -> FERIADO | O61: =#REF! -> #REF! | P61: =#REF! -> #REF! | Q61: =#REF! -> #REF! | R61: =#REF! -> #REF! | S61: =#REF! -> #REF! | T61: =#REF! -> #REF!
A62: 30 | C62: 30 | D62: =IF('[1]2021_Base RPA'!$F237="","",'[1]2021_Base RPA'!$F237) -> 7909.5 | E62: 30 | F62: =IF('[1]2021_Base RPA'!$F260="","",'[1]2021_Base RPA'!$F260) -> 7646 | O62: =#REF! -> #REF! | P62: =#REF! -> #REF! | Q62: =#REF! -> #REF! | R62: =#REF! -> #REF! | S62: =#REF! -> #REF! | T62: =#REF! -> #REF!
A63: 31 | C63: 31 | D63: =IF('[1]2021_Base RPA'!$F238="","",'[1]2021_Base RPA'!$F238) -> 7719 | O63: =#REF! -> #REF! | P63: =#REF! -> #REF! | Q63: =#REF! -> #REF! | R63: =#REF! -> #REF! | S63: =#REF! -> #REF! | T63: =#REF! -> #REF!
A64: =B65/L28-1 -> -0.16637072 | C64: =D65/B65-1 -> 0.057265838 | E64: =F65/D65-1 -> -0.028465127 | G64: =H65/F65-1 -> -0.01469638 | I64: =J65/H65-1 -> 0.052359145 | K64: =L65/J65-1 -> 0.045401533 | O64: =#REF! -> #REF! | P64: =#REF! -> #REF! | Q64: =#REF! -> #REF! | R64: =#REF! -> #REF! | S64: =#REF! -> #REF! | T64: =#REF! -> #REF!
A65: MM | B65: =AVERAGE(B41:B63) -> 7528.381 | C65: MM | D65: =AVERAGE(D41:D63) -> 7959.5 | E65: MM | F65: =AVERAGE(F41:F62) -> 7732.9318 | G65: MM | H65: =AVERAGE(H41:H63) -> 7619.2857 | I65: MM | J65: =AVERAGE(J41:J62) -> 8018.225 | K65: MM | L65: =AVERAGE(L41:L61) -> 8382.2647 | O65: =#REF! -> #REF! | P65: =#REF! -> #REF! | Q65: =#REF! -> #REF! | R65: =#REF! -> #REF! | S65: =#REF! -> #REF! | T65: =#REF! -> #REF!
A67: MM R$ | B67: =B65*A68 -> 40408.406 | C67: MM R$ | D67: =D65*C68 -> 40933.286 | E67: MM R$ | F67: =F65*E68 -> 40492.393 | G67: MM R$ | H67: =H65*G68 -> 39998.926 | I67: MM R$ | J67: =J65*I68 -> 42271.576 | K67: MM R$ | L67: =L65*K68 -> 44023.375
A68: =AVERAGE('[1]2021_Base RPA'!$B$195:$B$215) -> 5.3674762 | B68: =B67/L29-1 -> -0.11371928 | C68: =AVERAGE('[1]2021_Base RPA'!$B$216:$B$238) -> 5.1426957 | D68: =D67/B67-1 -> 0.01298939 | E68: =AVERAGE('[1]2021_Base RPA'!$B$239:$B$260) -> 5.2363571 | F68: =F67/D67-1 -> -0.010771021 | G68: =AVERAGE('[1]2021_Base RPA'!$B$261:$B$281) -> 5.249695 | H68: =H67/F67-1 -> -0.012186651 | I68: =AVERAGE('[1]2021_Base RPA'!$B$282:$B$302) -> 5.2719368 | J68: =J67/H67-1 -> 0.056817767 | K68: =AVERAGE('[1]2021_Base RPA'!$B$303:$B$323) -> 5.2519667 | L68: =L67/J67-1 -> 0.041441536
E71: VARIAÇÃO COBRE LME - REAIS

Sheet 2021
A1: Cobre LME Prices 2021 US$/Ton | O1: MÉDIAS
A2: Janeiro 2021 | C2: Fevereiro 2021 | E2: Março 2021 | G2: Abril 2021 | I2: Maio 2021 | K2: Junho 2021 | P2: US$ | Q2: Var (%) | R2: R$ | S2: Var Mês (%) | T2: Acumulado/Ano
B3: Cash | D3: Cash | F3: Cash | H3: Cash | J3: Cash | L3: Cash | O3: 41275 | P3: 8049.2455 | Q3: 0.010884092 | R3: 16364.921 | S3: -0.010958324
A4: 4 | B4: 7918.5 | C4: 1 | D4: 7827 | E4: 1 | F4: 9198 | G4: 1 | H4: 8768 | I4: 4 | J4: 9961 | K4: 1 | L4: 10212.5 | O4: 41306 | P4: 8070.475 | Q4: 0.0026374578 | R4: 15912.556 | S4: -0.027642381
A5: 5 | B5: 7914 | C5: 2 | D5: 7755.5 | E5: 2 | F5: 9213.5 | G5: 6 | H5: 8984.5 | I5: 5 | J5: 9991.5 | K5: 2 | L5: 10117.5 | O5: 41334 | P5: 7662.4 | Q5: -0.050563938 | R5: 15212.929 | S5: -0.043966954
A6: 6 | B6: 8129.5 | C6: 3 | D6: 7832.5 | E6: 3 | F6: 9266 | G6: 7 | H6: 8981.5 | I6: 6 | J6: 10025.5 | K6: 3 | L6: 9967 | O6: 41365 | P6: 7203.3571 | Q6: -0.059908496 | R6: 14413.918 | S6: -0.052521859
A7: 7 | B7: 8036.5 | C7: 4 | D7: 7833.5 | E7: 4 | F7: 8786.5 | G7: 8 | H7: 9001.5 | I7: 7 | J7: 10361 | K7: 4 | L7: 9852 | O7: 41395 | P7: 7229.1429 | Q7: 0.0035796801 | R7: 14704.077 | S7: 0.020130469
A8: 8 | B8: 8146 | C8: 5 | D8: 7936.5 | E8: 5 | F8: 9021.5 | G8: 9 | H8: 8993 | I8: 10 | J8: 10742.5 | K8: 7 | L8: 9848 | O8: 41426 | P8: 7004.05 | Q8: -0.031136867 | R8: 15198.789 | S8: 0.033644542
A9: 11 | B9: 7951.5 | C9: 8 | D9: 8007 | E9: 9 | F9: 8895 | G9: 12 | H9: 8901 | I9: 11 | J9: 10528 | K9: 8 | L9: 9978.5 | O9: 41456 | P9: 6896.9773 | Q9: -0.015287259 | R9: 15536.683 | S9: 0.022231658
A10: 12 | B10: 7983 | C10: 9 | D10: 8146.5 | E10: 10 | F10: 8939 | G10: 13 | H10: 8904 | I10: 12 | J10: 10537 | K10: 9 | L10: 9877 | O10: 41487 | P10: 7182.2619 | Q10: 0.041363719 | R10: 16802.902 | S10: 0.081498669
A11: 13 | B11: 7960.5 | C11: 10 | D11: 8279.5 | E11: 11 | F11: 9062.5 | G11: 14 | H11: 9011 | I11: 13 | J11: 10253.5 | K11: 10 | L11: 9808.5 | O11: 41518 | P11: 7161.4286 | Q11: -0.0029006647 | R11: 16264.32 | S11: -0.032052874
A12: 14 | B12: 8002.5 | C12: 11 | D12: 8292 | E12: 12 | F12: 9052.5 | G12: 15 | H12: 9187.5 | I12: 14 | J12: 10212 | K12: 11 | L12: 10029 | O12: 41548 | P12: 7188.7826 | Q12: 0.0038196342 | R12: 15720.43 | S12: -0.033440722
A13: 15 | B13: 7979.5 | C13: 12 | D13: 8270.5 | E13: 15 | F13: 9145.5 | G13: 16 | H13: 9336 | I13: 17 | J13: 10257 | K13: 14 | L13: 9900 | O13: 41579 | P13: 7066.4048 | Q13: -0.017023445 | R13: 16235.772 | S13: 0.032781659
A14: 18 | B14: 7972.5 | C14: 15 | D14: 8416.5 | E14: 16 | F14: 8965.5 | G14: 19 | H14: 9415 | I14: 18 | J14: 10465 | K14: 15 | L14: 9552.5 | O14: 41609 | P14: 7202.95 | Q14: 0.019323156 | R14: 16911.086 | S14: 0.041594231
A15: 19 | B15: 7986.5 | C15: 16 | D15: 8439.5 | E15: 17 | F15: 9027 | G15: 20 | H15: 9396.5 | I15: 19 | J15: 10114.5 | K15: 16 | L15: 9508 | O15: 41640 | P15: 7294.8864 | Q15: 0.01276371 | R15: 17368.395 | S15: 0.027041961 | T15: 0.027041961
A16: 20 | B16: 8014.5 | C16: 17 | D16: 8413.5 | E16: 18 | F16: 9090 | G16: 21 | H16: 9382.5 | I16: 20 | J16: 10086 | K16: 17 | L16: 9427.5 | O16: 41671 | P16: 7152.15 | Q16: -0.019566633 | R16: 17062.884 | S16: -0.017590036 | T16: 0.0089762565
A17: 21 | B17: 8051 | C17: 18 | D17: 8650 | E17: 19 | F17: 9036 | G17: 22 | H17: 9475.5 | I17: 21 | J17: 10011 | K17: 18 | L17: 9206 | O17: 41699 | P17: 6667.8095 | Q17: -0.067719564 | R17: 15507.991 | S17: -0.0911272 | T17: -0.082968925
A18: 22 | B18: 7872 | C18: 19 | D18: 8806.5 | E18: 22 | F18: 9097.5 | G18: 23 | H18: 9545.5 | I18: 24 | J18: 9868 | K18: 21 | L18: 9042.5 | O18: 41730 | P18: 6670.825 | Q18: 0.0004522439 | R18: 14896.619 | S18: -0.039423035 | T18: -0.11912107
A19: 25 | B19: 7984.5 | C19: 22 | D19: 9067.5 | E19: 23 | F19: 9016.5 | G19: 26 | H19: 9758 | I19: 25 | J19: 9943 | K19: 22 | L19: 9190.5 | O19: 41760 | P19: 6883.875 | Q19: 0.031937579 | R19: 15289.775 | S19: 0.02639226 | T19: -0.095872687
A20: 26 | B20: 7957 | C20: 23 | D20: 9158 | E20: 24 | F20: 9016 | G20: 27 | H20: 9898.5 | I20: 26 | J20: 9965 | K20: 23 | L20: 9289.5 | O20: 41791 | P20: 6806.0952 | Q20: -0.011298834 | R20: 15206.178 | S20: -0.0054674959 | T20: -0.100816
A21: 27 | B21: 7895 | C21: 24 | D21: 9286 | E21: 25 | F21: 8781 | G21: 28 | H21: 9832.5 | I21: 27 | J21: 10032.5 | K21: 24 | L21: 9390.5 | O21: 41821 | P21: 7104.8478 | Q21: 0.043894859 | R21: 15807.576 | S21: 0.03954958 | T21: -0.06525365
A22: 28 | B22: 7778.5 | C22: 25 | D22: 9614.5 | E22: 26 | F22: 8929 | G22: 29 | H22: 9990 | I22: 28 | J22: 10159.5 | K22: 25 | L22: 9432.5 | O22: 41852 | P22: 7000.55 | Q22: -0.014679811 | R22: 15880.048 | S22: 0.0045846177 | T22: -0.060968195
A23: 29 | B23: 7877 | C23: 26 | D23: 9172.5 | E23: 29 | F23: 8942.5 | G23: 30 | H23: 9949 | K23: 28 | L23: 9333.5 | O23: 41883 | P23: 6872.2273 | Q23: -0.018330378 | R23: 16046.651 | S23: 0.010491345 | T23: -0.051116488
E24: 30 | F24: 8788.5 | K24: 29 | L24: 9225.5 | O24: 41913 | P24: 6739.1957 | Q24: -0.019357861 | R24: 16515.747 | S24: 0.029233272 | T24: -0.023377518
E25: 31 | F25: 8850.5 | K25: 30 | L25: 9385
O26: 41944 | P26: 6701.135 | Q26: -0.005647655 | R26: 17154.906 | S26: 0.038699965 | T26: 0.014417737
A27: =B28/'2020'!L65-1 -> 0.027756969 | C27: =D28/B28-1 -> 0.06144533 | E27: =F28/D28-1 -> 0.064443077 | G27: =H28/F28-1 -> 0.036655058 | I27: =J28/H28-1 -> 0.090982433 | K27: =L28/J28-1 -> -0.055763199 | O27: 41974 | P27: 6422.9524 | Q27: -0.041512762 | R27: 16968.798 | S27: -0.010848658 | T27: 0.0034126658
A28: MM | B28: =AVERAGE(B4:B24) -> 7970.5 | C28: MM | D28: =AVERAGE(D4:D23) -> 8460.25 | E28: MM | F28: =AVERAGE(F4:F25) -> 9005.4545 | G28: MM | H28: =AVERAGE(H4:H24) -> 9335.55 | I28: MM | J28: =AVERAGE(J4:J22) -> 10184.921 | K28: MM | L28: =AVERAGE(L4:L25) -> 9616.9773 | O28: 42005 | P28: 5791.175 | Q28: -0.098362458 | R28: 15271.908 | S28: -0.10000062 | T28: -0.10000062
A29: MM R$ | B29: =B28*A30 -> 42686.81 | C29: MM R$ | D29: =D28*C30 -> 45819.821 | E29: MM R$ | F29: =F28*E30 -> 50840.724 | G29: MM R$ | H29: =H28*G30 -> 51919.988 | I29: MM R$ | J29: =J28*I30 -> 53882.791 | K29: MM R$ | L29: =L28*K30 -> 48385.944 | O29: 42036 | P29: 5702.075 | Q29: -0.015385479 | R29: 16059.837 | S29: 0.051593399 | T29: -0.053566592
A30: 5.3556 | B30: =B29/'2020'!L67-1 -> 0.06983743 | C30: 5.4158944 | D30: =D29/B29-1 -> 0.073395299 | E30: 5.6455478 | F30: =F29/D29-1 -> 0.10957929 | G30: 5.561535 | H30: =H29/F29-1 -> 0.021228331 | I30: 5.2904476 | J30: =J29/H29-1 -> 0.037804386 | K30: 5.0313048 | L30: =L29/J29-1 -> -0.1020149 | O30: 42064 | P30: 5919.9048 | Q30: 0.038201841 | R30: 18601.525 | S30: 0.15826359 | T30: 0.096219358
A31: Cobre LME Prices 2021 US$/Ton | O31: MÉDIAS
A32: Julho 2021 | C32: Agosto 2021 | E32: Setembro 2021 | G32: Outubro 2021 | I32: Novembro 2021 | K32: Dezembro 2021 | O32: 42125 | P32: 6300.6053 | Q32: 0.04514038 | R32: 19242.048 | S32: 0.045653962 | T32: 0.13396651
B33: Cash | D33: Cash | F33: Cash | H33: Cash | J33: Cash | L33: Cash | O33: 42156 | P33: 5833.6136 | Q33: -0.074118534 | R33: 18168.79 | S33: -0.055776744 | T33: 0.070717548
A34: Média | B34: #DIV/0! | C34: Média | D34: #DIV/0! | E34: Média | F34: #DIV/0! | G34: Média | H34: #DIV/0! | I34: Média | J34: #DIV/0! | K34: Média | L34: #DIV/0! | O34: 42675 | T34: #DIV/0!
A35: MM | B35: #DIV/0! | C35: MM | D35: #DIV/0! | E35: MM | F35: #DIV/0! | G35: MM | H35: #DIV/0! | I35: MM | J35: #DIV/0! | K35: MM | L35: #DIV/0! | O35: 42705 | T35: #DIV/0!
A36: #DIV/0! | C36: #DIV/0! | E36: #DIV/0! | G36: #DIV/0! | I36: #DIV/0! | K36: #DIV/0! | O36: 42736 | T36: #DIV/0!
A37: MM R$ | B37: #DIV/0! | C37: MM R$ | D37: #DIV/0! | E37: MM R$ | F37: #DIV/0! | G37: MM R$ | H37: #DIV/0! | I37: MM R$ | J37: #DIV/0! | K37: MM R$ | L37: #DIV/0! | O37: 42767 | T37: #DIV/0!
B38: #DIV/0! | D38: #DIV/0! | F38: #DIV/0! | H38: #DIV/0! | J38: #DIV/0! | L38: #DIV/0! | O38: 42795 | T38: #DIV/0!
A39: Julho 2016 | C39: Agosto 2016 | E39: Setembro 2016 | G39: Outubro 2016 | I39: Novembro 2016 | K39: Dezembro 2016 | O39: 42826 | T39: #DIV/0!
B40: Cash | D40: Cash | F40: Cash | H40: Cash | J40: Cash | L40: Cash | O40: 42856 | T40: #DIV/0!
A41: 1 | B41: 9342 | C41: 2 | D41: 9737 | E41: 1 | F41: 9312 | G41: 1 | H41: 9113 | I41: 1 | J41: 9875 | K41: 1 | L41: 9571 | O41: =#REF! -> #REF! | P41: =#REF! -> #REF! | Q41: =#REF! -> #REF! | R41: =#REF! -> #REF! | S41: =#REF! -> #REF! | T41: =#REF! -> #REF!
A42: 2 | B42: 9296.5 | C42: 3 | D42: 9583.5 | E42: 2 | F42: 9347 | G42: 4 | H42: 9267.5 | I42: 2 | J42: 9817 | K42: 2 | L42: 9520 | O42: =#REF! -> #REF! | P42: =#REF! -> #REF! | Q42: =#REF! -> #REF! | R42: =#REF! -> #REF! | S42: =#REF! -> #REF! | T42: =#REF! -> #REF!
A43: 5 | B43: 9432 | C43: 4 | D43: 9503 | E43: 3 | F43: 9361 | G43: 5 | H43: 9091.5 | I43: 3 | J43: 9825 | K43: 3 | L43: 9513 | O43: =#REF! -> #REF! | P43: =#REF! -> #REF! | Q43: =#REF! -> #REF! | R43: =#REF! -> #REF! | S43: =#REF! -> #REF! | T43: =#REF! -> #REF!
A44: 6 | B44: 9528 | C44: 5 | D44: 9429 | E44: 6 | F44: 9401.25 | G44: 6 | H44: 9096 | I44: 4 | J44: 9785 | K44: 6 | L44: 9526 | O44: =#REF! -> #REF! | P44: =#REF! -> #REF! | Q44: =#REF! -> #REF! | R44: =#REF! -> #REF! | S44: =#REF! -> #REF! | T44: =#REF! -> #REF!
A45: 7 | B45: 9451.5 | C45: 6 | D45: 9529.5 | E45: 7 | F45: 9324.5 | G45: 7 | H45: 9177 | I45: 5 | J45: 9740 | K45: 7 | L45: 9647 | O45: =#REF! -> #REF! | P45: =#REF! -> #REF! | Q45: =#REF! -> #REF! | R45: =#REF! -> #REF! | S45: =#REF! -> #REF! | T45: =#REF! -> #REF!
A46: 8 | B46: 9264.5 | C46: 9 | D46: 9311.5 | E46: 8 | F46: 9255.5 | G46: 8 | H46: 9246 | I46: 8 | J46: 9885 | K46: 8 | L46: 9555.5 | O46: =#REF! -> #REF! | P46: =#REF! -> #REF! | Q46: =#REF! -> #REF! | R46: =#REF! -> #REF! | S46: =#REF! -> #REF! | T46: =#REF! -> #REF!
A47: 9 | B47: 9437.5 | C47: 10 | D47: 9409.5 | E47: 9 | F47: 9356.25 | G47: 11 | H47: 9527 | I47: 9 | J47: 10002 | K47: 9 | L47: 9578 | O47: =#REF! -> #REF! | P47: =#REF! -> #REF! | Q47: =#REF! -> #REF! | R47: =#REF! -> #REF! | S47: =#REF! -> #REF! | T47: =#REF! -> #REF!
A48: 12 | B48: 9347 | C48: 11 | D48: 9421 | E48: 10 | F48: 9514.75 | G48: 12 | H48: 9585 | I48: 10 | J48: 9791 | K48: 10 | L48: 9543 | O48: =#REF! -> #REF! | P48: =#REF! -> #REF! | Q48: =#REF! -> #REF! | R48: =#REF! -> #REF! | S48: =#REF! -> #REF! | T48: =#REF! -> #REF!
A49: 13 | B49: 9310 | C49: 12 | D49: 9508.5 | E49: 13 | F49: 9626.5 | G49: 13 | H49: 9661 | I49: 11 | J49: 9850 | K49: 13 | L49: 9500 | O49: =#REF! -> #REF! | P49: =#REF! -> #REF! | Q49: =#REF! -> #REF! | R49: =#REF! -> #REF! | S49: =#REF! -> #REF! | T49: =#REF! -> #REF!
A50: 14 | B50: 9309 | C50: 13 | D50: 9429.5 | E50: 14 | F50: 9407 | G50: 14 | H50: 9971 | I50: 12 | J50: 9854.5 | K50: 14 | L50: 9485 | O50: =#REF! -> #REF! | P50: =#REF! -> #REF! | Q50: =#REF! -> #REF! | R50: =#REF! -> #REF! | S50: =#REF! -> #REF! | T50: =#REF! -> #REF!
A51: 15 | B51: 9347 | C51: 16 | D51: 9377 | E51: 15 | F51: 9488.5 | G51: 15 | H51: 10555 | I51: 15 | J51: 9845 | K51: 15 | L51: 9290 | O51: =#REF! -> #REF! | P51: =#REF! -> #REF! | Q51: =#REF! -> #REF! | R51: =#REF! -> #REF! | S51: =#REF! -> #REF! | T51: =#REF! -> #REF!
A52: 16 | B52: 9396.5 | C52: 17 | D52: 9346.5 | E52: 16 | F52: 9392 | G52: 18 | H52: 10500 | I52: 16 | J52: 9680 | K52: 16 | L52: 9506 | O52: =#REF! -> #REF! | P52: =#REF! -> #REF! | Q52: =#REF! -> #REF! | R52: =#REF! -> #REF! | S52: =#REF! -> #REF! | T52: =#REF! -> #REF!
... A60: 28 | B60: 9697 | C60: 31 | D60: 9462.5 | E60: 28 | F60: 9263 | G60: 28 | H60: 9860 | I60: 26 | J60: 9630 | K60: 30 | L60: 9715 | O60: =#REF! -> #REF! | P60: =#REF! -> #REF! | Q60: =#REF! -> #REF! | R60: =#REF! -> #REF! | S60: =#REF! -> #REF! | T60: =#REF! -> #REF!
A61: 29 | B61: 9781 | E61: 29 | F61: 9227 | G61: 29 | H61: 9955 | I61: 29 | J61: 9751 | K61: 31 | L61: 9692 | O61: =#REF! -> #REF! | P61: =#REF! -> #REF! | Q61: =#REF! -> #REF! | R61: =#REF! -> #REF! | S61: =#REF! -> #REF! | T61: =#REF! -> #REF!
A62: 30 | B62: 9747.5 | E62: 30 | F62: 9041 | G62: 30 | I62: 30 | J62: 9605 | O62: =#REF! -> #REF! | P62: =#REF! -> #REF! | Q62: =#REF! -> #REF! | R62: =#REF! -> #REF! | S62: =#REF! -> #REF! | T62: =#REF! -> #REF!
A63: 31 | O63: =#REF! -> #REF! | P63: =#REF! -> #REF! | Q63: =#REF! -> #REF! | R63: =#REF! -> #REF! | S63: =#REF! -> #REF! | T63: =#REF! -> #REF!
A64: =B65/L28-1 -> -0.019069023 | C64: =D65/B65-1 -> -0.0078830967 | E64: =F65/D65-1 -> -0.0037673088 | G64: =H65/F65-1 -> 0.048749008 | I64: =J65/H65-1 -> -0.0013317715 | K64: =L65/J65-1 -> -0.022033511 | O64: =#REF! -> #REF! | P64: =#REF! -> #REF! | Q64: =#REF! -> #REF! | R64: =#REF! -> #REF! | S64: =#REF! -> #REF! | T64: =#REF! -> #REF!
A65: MM | B65: =AVERAGE(B41:B63) -> 9433.5909 | C65: MM | D65: =AVERAGE(D41:D63) -> 9359.225 | E65: MM | F65: =AVERAGE(F41:F62) -> 9323.9659 | G65: MM | H65: =AVERAGE(H41:H63) -> 9778.5 | I65: MM | J65: =AVERAGE(J41:J62) -> 9765.4773 | K65: MM | L65: =AVERAGE(L41:L61) -> 9550.3095 | O65: =#REF! -> #REF! | P65: =#REF! -> #REF! | Q65: =#REF! -> #REF! | R65: =#REF! -> #REF! | S65: =#REF! -> #REF! | T65: =#REF! -> #REF!
A67: MM R$ | B67: =B65*A68 -> 48639.852 | C67: MM R$ | D67: =D65*C68 -> 49146.439 | E67: MM R$ | F67: =F65*E68 -> 49222.06 | G67: MM R$ | H67: =H65*G68 -> 54166.778 | I67: MM R$ | J67: =J65*I68 -> 54259.531 | K67: MM R$ | L67: =L65*K68 -> 53965.021
A68: 5.1560273 | B68: =B67/L29-1 -> 0.0052475666 | C68: 5.2511227 | D68: =D67/B67-1 -> 0.010415063 | E68: 5.2790905 | F68: =F67/D67-1 -> 0.0015386776 | G68: 5.539375 | H68: =H67/F67-1 -> 0.10045737 | I68: =AVERAGE('[1]2021_Base RPA'!$B$21:$B$42) -> 5.55626 | J68: =J67/H67-1 -> 0.0017123469 | K68: 5.6506043 | L68: =L67/J67-1 -> -0.0054278065
E71: VARIAÇÃO COBRE LME - REAIS

Sheet 2023
A1: Cobre LME Prices 2021 US$/Ton | O1: MÉDIAS
A2: Janeiro 2023 | C2: Fevereiro 2023 | E2: Março 2023 | G2: Abril 2023 | I2: Maio 2023 | K2: Junho 2023 | P2: US$ | Q2: Var (%) | R2: R$ | S2: Var Mês (%) | T2: Acumulado/Ano
B3: Cash | D3: Cash | F3: Cash | H3: Cash | J3: Cash | L3: Cash | O3: 41275 | P3: 8049.2455 | Q3: 0.010884092 | R3: 16364.921 | S3: -0.010958324
A4: 2 | B4: FERIADO | C4: 1 | D4: =IF('[1]2021_Base RPA'!$F341="","",'[1]2021_Base RPA'!$F341) -> 9175 | E4: 1 | F4: =IF('[1]2021_Base RPA'!$F361="","",'[1]2021_Base RPA'!$F361) -> 9066 | G4: 3 | H4: =IF('[1]2021_Base RPA'!$F384="","",'[1]2021_Base RPA'!$F384) -> 8965.5 | I4: 2 | J4: =IF('[1]2021_Base RPA'!$F403="","",'[1]2021_Base RPA'!$F403) -> 8573 | K4: 1 | L4: =IF('[1]2021_Base RPA'!$F425="","",'[1]2021_Base RPA'!$F425) -> 8211
A5: 3 | B5: 8390 | C5: 2 | D5: =IF('[1]2021_Base RPA'!$F342="","",'[1]2021_Base RPA'!$F342) -> 9114 | E5: 2 | F5: =IF('[1]2021_Base RPA'!$F362="","",'[1]2021_Base RPA'!$F362) -> 8894 | G5: 4 | H5: =IF('[1]2021_Base RPA'!$F385="","",'[1]2021_Base RPA'!$F385) -> 8925 | I5: 3 | J5: =IF('[1]2021_Base RPA'!$F404="","",'[1]2021_Base RPA'!$F404) -> 8486 | K5: 2 | L5: =IF('[1]2021_Base RPA'!$F426="","",'[1]2021_Base RPA'!$F426) -> 8337 | O5: 41306 | P5: 8070.475 | Q5: 0.0026374578 | R5: 15912.556 | S5: -0.027642381
A6: 4 | B6: =IF('[1]2021_Base RPA'!$F324="","",'[1]2021_Base RPA'!$F324) -> 8208 | C6: 3 | D6: =IF('[1]2021_Base RPA'!$F343="","",'[1]2021_Base RPA'!$F343) -> 9060 | E6: 3 | F6: =IF('[1]2021_Base RPA'!$F363="","",'[1]2021_Base RPA'!$F363) -> 8896 | G6: 5 | H6: =IF('[1]2021_Base RPA'!$F386="","",'[1]2021_Base RPA'!$F386) -> 8778 | I6: 4 | J6: =IF('[1]2021_Base RPA'!$F405="","",'[1]2021_Base RPA'!$F405) -> 8539 | K6: 5 | L6: =IF('[1]2021_Base RPA'!$F427="","",'[1]2021_Base RPA'!$F427) -> 8264 | O6: 41334 | P6: 7662.4 | Q6: -0.050563938 | R6: 15212.929 | S6: -0.043966954
A7: 5 | B7: =IF('[1]2021_Base RPA'!$F325="","",'[1]2021_Base RPA'!$F325) -> 8418 | C7: 4 | D7: =IF('[1]2021_Base RPA'!$F344="","",'[1]2021_Base RPA'!$F344) -> 8891 | E7: 6 | F7: =IF('[1]2021_Base RPA'!$F364="","",'[1]2021_Base RPA'!$F364) -> 8945 | G7: 6 | H7: =IF('[1]2021_Base RPA'!$F387="","",'[1]2021_Base RPA'!$F387) -> 8835.5 | I7: 5 | J7: =IF('[1]2021_Base RPA'!$F406="","",'[1]2021_Base RPA'!$F406) -> 8488 | K7: 6 | L7: =IF('[1]2021_Base RPA'!$F428="","",'[1]2021_Base RPA'!$F428) -> 8311 | O7: 41365 | P7: 7203.3571 | Q7: -0.059908496 | R7: 14413.918 | S7: -0.052521859
A8: 6 | B8: =IF('[1]2021_Base RPA'!$F326="","",'[1]2021_Base RPA'!$F326) -> 8362 | C8: 7 | D8: =IF('[1]2021_Base RPA'!$F345="","",'[1]2021_Base RPA'!$F345) -> 8665 | E8: 7 | F8: =IF('[1]2021_Base RPA'!$F365="","",'[1]2021_Base RPA'!$F365) -> 8819 | G8: 7 | H8: =IF('[1]2021_Base RPA'!$F388="","",'[1]2021_Base RPA'!$F388) -> FERIADO | I8: 8 | J8: feriado | K8: 7 | L8: =IF('[1]2021_Base RPA'!$F429="","",'[1]2021_Base RPA'!$F429) -> 8352 | O8: 41395 | P8: 7229.1429 | Q8: 0.0035796801 | R8: 14704.077 | S8: 0.020130469
A9: 9 | B9: =IF('[1]2021_Base RPA'!$F327="","",'[1]2021_Base RPA'!$F327) -> 8720 | C9: 8 | D9: =IF('[1]2021_Base RPA'!$F346="","",'[1]2021_Base RPA'!$F346) -> 9005.5 | E9: 8 | F9: =IF('[1]2021_Base RPA'!$F366="","",'[1]2021_Base RPA'!$F366) -> 8809.5 | G9: 8 | H9: =IF('[1]2021_Base RPA'!$F389="","",'[1]2021_Base RPA'!$F389) -> FERIADO | I9: 9 | J9: =IF('[1]2021_Base RPA'!$F408="","",'[1]2021_Base RPA'!$F408) -> 8583 | K9: 8 | L9: =IF('[1]2021_Base RPA'!$F430="","",'[1]2021_Base RPA'!$F430) -> 8243 | O9: 41426 | P9: 7004.05 | Q9: -0.031136867 | R9: 15198.789 | S9: 0.033644542
A10: 10 | B10: =IF('[1]2021_Base RPA'!$F328="","",'[1]2021_Base RPA'!$F328) -> 8766 | C10: 9 | D10: =IF('[1]2021_Base RPA'!$F347="","",'[1]2021_Base RPA'!$F347) -> 8953 | E10: 9 | F10: =IF('[1]2021_Base RPA'!$F367="","",'[1]2021_Base RPA'!$F367) -> 8807 | G10: 11 | H10: =IF('[1]2021_Base RPA'!$F390="","",'[1]2021_Base RPA'!$F390) -> 8837 | I10: 10 | J10: =IF('[1]2021_Base RPA'!$F409="","",'[1]2021_Base RPA'!$F409) -> 8469 | K10: 9 | L10: =IF('[1]2021_Base RPA'!$F431="","",'[1]2021_Base RPA'!$F431) -> 8367 | O10: 41456 | P10: 6896.9773 | Q10: -0.015287259 | R10: 15536.683 | S10: 0.022231658
A11: 11 | B11: =IF('[1]2021_Base RPA'!$F329="","",'[1]2021_Base RPA'!$F329) -> 8986 | C11: 10 | D11: =IF('[1]2021_Base RPA'!$F348="","",'[1]2021_Base RPA'!$F348) -> 8904 | E11: 10 | F11: =IF('[1]2021_Base RPA'!$F368="","",'[1]2021_Base RPA'!$F368) -> 8750 | G11: 12 | H11: =IF('[1]2021_Base RPA'!$F391="","",'[1]2021_Base RPA'!$F391) -> 8802 | I11: 11 | J11: =IF('[1]2021_Base RPA'!$F410="","",'[1]2021_Base RPA'!$F410) -> 8267 | K11: 12 | L11: =IF('[1]2021_Base RPA'!$F432="","",'[1]2021_Base RPA'!$F432) -> 8286 | O11: 41487 | P11: 7182.2619 | Q11: 0.041363719 | R11: 16802.902 | S11: 0.081498669
A12: 12 | B12: =IF('[1]2021_Base RPA'!$F330="","",'[1]2021_Base RPA'!$F330) -> 9071 | C12: 11 | D12: =IF('[1]2021_Base RPA'!$F349="","",'[1]2021_Base RPA'!$F349) -> 8911 | E12: 13 | F12: =IF('[1]2021_Base RPA'!$F369="","",'[1]2021_Base RPA'!$F369) -> 8650 | G12: 13 | H12: =IF('[1]2021_Base RPA'!$F392="","",'[1]2021_Base RPA'!$F392) -> 9000.5 | I12: 12 | J12: =IF('[1]2021_Base RPA'!$F411="","",'[1]2021_Base RPA'!$F411) -> 8240 | K12: 13 | L12: =IF('[1]2021_Base RPA'!$F433="","",'[1]2021_Base RPA'!$F433) -> 8421 | O12: 41518 | P12: 7161.4286 | Q12: -0.0029006647 | R12: 16264.32 | S12: -0.032052874
A13: 13 | B13: 9107 | C13: 14 | D13: =IF('[1]2021_Base RPA'!$F350="","",'[1]2021_Base RPA'!$F350) -> 8931 | E13: 14 | F13: =IF('[1]2021_Base RPA'!$F370="","",'[1]2021_Base RPA'!$F370) -> 8651 | G13: 14 | H13: =IF('[1]2021_Base RPA'!$F393="","",'[1]2021_Base RPA'!$F393) -> 9080 | I13: 15 | J13: =IF('[1]2021_Base RPA'!$F412="","",'[1]2021_Base RPA'!$F412) -> 8287 | K13: 14 | L13: =IF('[1]2021_Base RPA'!$F434="","",'[1]2021_Base RPA'!$F434) -> 8457 | O13: 41548 | P13: 7188.7826 | Q13: 0.0038196342 | R13: 15720.43 | S13: -0.033440722
A14: 16 | B14: 9145.5 | C14: 15 | D14: =IF('[1]2021_Base RPA'!$F351="","",'[1]2021_Base RPA'!$F351) -> 8825 | E14: 15 | F14: =IF('[1]2021_Base RPA'!$F371="","",'[1]2021_Base RPA'!$F371) -> 8520 | G14: 15 | H14: =IF('[1]2021_Base RPA'!$F394="","",'[1]2021_Base RPA'!$F394) -> 8983 | I14: 16 | J14: =IF('[1]2021_Base RPA'!$F413="","",'[1]2021_Base RPA'!$F413) -> 8076 | K14: 15 | L14: =IF('[1]2021_Base RPA'!$F435="","",'[1]2021_Base RPA'!$F435) -> 8479 | O14: 41579 | P14: 7066.4048 | Q14: -0.017023445 | R14: 16235.772 | S14: 0.032781659
A15: 17 | B15: =IF('[1]2021_Base RPA'!$F332="","",'[1]2021_Base RPA'!$F332) -> 9112 | C15: 16 | D15: =IF('[1]2021_Base RPA'!$F352="","",'[1]2021_Base RPA'!$F352) -> 8892 | E15: 16 | F15: =IF('[1]2021_Base RPA'!$F372="","",'[1]2021_Base RPA'!$F372) -> 8530 | G15: 18 | H15: =IF('[1]2021_Base RPA'!$F395="","",'[1]2021_Base RPA'!$F395) -> 8965 | I15: 17 | J15: =IF('[1]2021_Base RPA'!$F414="","",'[1]2021_Base RPA'!$F414) -> 8176 | K15: 16 | L15: =IF('[1]2021_Base RPA'!$F436="","",'[1]2021_Base RPA'!$F436) -> 8561 | O15: 41609 | P15: 7202.95 | Q15: 0.019323156 | R15: 16911.086 | S15: 0.041594231
A16: 18 | B16: 9036 | C16: 17 | D16: =IF('[1]2021_Base RPA'!$F353="","",'[1]2021_Base RPA'!$F353) -> 8870 | E16: 17 | F16: =IF('[1]2021_Base RPA'!$F373="","",'[1]2021_Base RPA'!$F373) -> FERIADO | G16: 19 | H16: =IF('[1]2021_Base RPA'!$F396="","",'[1]2021_Base RPA'!$F396) -> 8874.5 | I16: 18 | J16: =IF('[1]2021_Base RPA'!$F415="","",'[1]2021_Base RPA'!$F415) -> 8171 | K16: 19 | L16: =IF('[1]2021_Base RPA'!$F437="","",'[1]2021_Base RPA'!$F437) -> 8541 | O16: 41640 | P16: 7294.8864 | Q16: 0.01276371 | R16: 17368.395 | S16: 0.027041961 | T16: 0.027041961
A17: 19 | B17: =IF('[1]2021_Base RPA'!$F334="","",'[1]2021_Base RPA'!$F334) -> 9188 | C17: 18 | D17: =IF('[1]2021_Base RPA'!$F354="","",'[1]2021_Base RPA'!$F354) -> 9015 | E17: 20 | F17: =IF('[1]2021_Base RPA'!$F374="","",'[1]2021_Base RPA'!$F374) -> 8676 | G17: 20 | H17: =IF('[1]2021_Base RPA'!$F397="","",'[1]2021_Base RPA'!$F397) -> 8873 | I17: 19 | J17: =IF('[1]2021_Base RPA'!$F416="","",'[1]2021_Base RPA'!$F416) -> 8221 | K17: 20 | L17: =IF('[1]2021_Base RPA'!$F438="","",'[1]2021_Base RPA'!$F438) -> 8560 | O17: 41671 | P17: 7152.15 | Q17: -0.019566633 | R17: 17062.884 | S17: -0.017590036 | T17: 0.0089762565
A18: 20 | B18: =IF('[1]2021_Base RPA'!$F335="","",'[1]2021_Base RPA'!$F335) -> 9230 | C18: 19 | D18: =IF('[1]2021_Base RPA'!$F355="","",'[1]2021_Base RPA'!$F355) -> 9103.5 | E18: 21 | F18: =IF('[1]2021_Base RPA'!$F375="","",'[1]2021_Base RPA'!$F375) -> 8823 | G18: 21 | H18: =IF('[1]2021_Base RPA'!$F398="","",'[1]2021_Base RPA'!$F398) -> 8815 | I18: 22 | J18: =IF('[1]2021_Base RPA'!$F417="","",'[1]2021_Base RPA'!$F417) -> 8093 | K18: 21 | L18: =IF('[1]2021_Base RPA'!$F439="","",'[1]2021_Base RPA'!$F439) -> 8486 | O18: 41699 | P18: 6667.8095 | Q18: -0.067719564 | R18: 15507.991 | S18: -0.0911272 | T18: -0.082968925
A19: 23 | B19: =IF('[1]2021_Base RPA'!$F336="","",'[1]2021_Base RPA'!$F336) -> 9340 | C19: 22 | D19: =IF('[1]2021_Base RPA'!$F356="","",'[1]2021_Base RPA'!$F356) -> 9060 | E19: 22 | F19: =IF('[1]2021_Base RPA'!$F376="","",'[1]2021_Base RPA'!$F376) -> 8880.5 | G19: 22 | H19: =IF('[1]2021_Base RPA'!$F399="","",'[1]2021_Base RPA'!$F399) -> 8762 | I19: 23 | J19: =IF('[1]2021_Base RPA'!$F418="","",'[1]2021_Base RPA'!$F418) -> 7960 | K19: 22 | L19: =IF('[1]2021_Base RPA'!$F440="","",'[1]2021_Base RPA'!$F440) -> 8670 | O19: 41730 | P19: 6670.825 | Q19: 0.0004522439 | R19: 14896.619 | S19: -0.039423035 | T19: -0.11912107
A20: 24 | B20: 9308 | C20: 23 | D20: =IF('[1]2021_Base RPA'!$F357="","",'[1]2021_Base RPA'!$F357) -> 9059 | E20: 23 | F20: =IF('[1]2021_Base RPA'!$F377="","",'[1]2021_Base RPA'!$F377) -> 8915 | G20: 25 | H20: =IF('[1]2021_Base RPA'!$F400="","",'[1]2021_Base RPA'!$F400) -> 8520.5 | I20: 24 | J20: =IF('[1]2021_Base RPA'!$F419="","",'[1]2021_Base RPA'!$F419) -> 7909 | K20: 23 | L20: =IF('[1]2021_Base RPA'!$F441="","",'[1]2021_Base RPA'!$F441) -> 8488 | O20: 41760 | P20: 6883.875 | Q20: 0.031937579 | R20: 15289.775 | S20: 0.02639226 | T20: -0.095872687
A21: 25 | B21: 9258 | C21: 24 | D21: =IF('[1]2021_Base RPA'!$F358="","",'[1]2021_Base RPA'!$F358) -> 8805 | E21: 24 | F21: =IF('[1]2021_Base RPA'!$F378="","",'[1]2021_Base RPA'!$F378) -> 8926 | G21: 26 | H21: =IF('[1]2021_Base RPA'!$F401="","",'[1]2021_Base RPA'!$F401) -> 8578 | I21: 25 | J21: =IF('[1]2021_Base RPA'!$F420="","",'[1]2021_Base RPA'!$F420) -> 7921 | K21: 26 | L21: =IF('[1]2021_Base RPA'!$F442="","",'[1]2021_Base RPA'!$F442) -> 8435 | O21: 41791 | P21: 6806.0952 | Q21: -0.011298834 | R21: 15206.178 | S21: -0.0054674959 | T21: -0.100816
A22: 26 | B22: =IF('[1]2021_Base RPA'!$F337="","",'[1]2021_Base RPA'!$F337) -> 9287.5 | C22: 25 | D22: =IF('[1]2021_Base RPA'!$F359="","",'[1]2021_Base RPA'!$F359) -> 8749 | E22: 27 | F22: =IF('[1]2021_Base RPA'!$F379="","",'[1]2021_Base RPA'!$F379) -> 8875 | G22: 27 | H22: =IF('[1]2021_Base RPA'!$F402="","",'[1]2021_Base RPA'!$F402) -> 8465 | I22: 26 | J22: =IF('[1]2021_Base RPA'!$F421="","",'[1]2021_Base RPA'!$F421) -> 8082 | K22: 27 | L22: =IF('[1]2021_Base RPA'!$F443="","",'[1]2021_Base RPA'!$F443) -> 8366 | O22: 41821 | P22: 7104.8478 | Q22: 0.043894859 | R22: 15807.576 | S22: 0.03954958 | T22: -0.06525365
A23: 27 | B23: =IF('[1]2021_Base RPA'!$F338="","",'[1]2021_Base RPA'!$F338) -> 9345 | C23: 28 | D23: =IF('[1]2021_Base RPA'!$F360="","",'[1]2021_Base RPA'!$F360) -> 8843 | E23: 28 | F23: =IF('[1]2021_Base RPA'!$F380="","",'[1]2021_Base RPA'!$F380) -> 8933 | G23: 28 | H23: =IF('[1]2021_Base RPA'!$F403="","",'[1]2021_Base RPA'!$F403) -> 8573 | I23: 29 | J23: feriado | K23: 28 | L23: =IF('[1]2021_Base RPA'!$F444="","",'[1]2021_Base RPA'!$F444) -> 8267 | O23: 41852 | P23: 7000.55 | Q23: -0.014679811 | R23: 15880.048 | S23: 0.0045846177 | T23: -0.060968195
A24: 30 | B24: 9227 | E24: 29 | F24: =IF('[1]2021_Base RPA'!$F381="","",'[1]2021_Base RPA'!$F381) -> 9047 | G24: 29 | H24: =IF('[1]2021_Base RPA'!$F404="","",'[1]2021_Base RPA'!$F404) -> 8486 | I24: 30 | J24: =IF('[1]2021_Base RPA'!$F423="","",'[1]2021_Base RPA'!$F423) -> 8122 | K24: 29 | L24: =IF('[1]2021_Base RPA'!$F445="","",'[1]2021_Base RPA'!$F445) -> 8166 | O24: 41883 | P24: 6872.2273 | Q24: -0.018330378 | R24: 16046.651 | S24: 0.010491345 | T24: -0.051116488
A25: 31 | B25: =IF('[1]2021_Base RPA'!$F340="","",'[1]2021_Base RPA'!$F340) -> 9074.5 | E25: 30 | F25: =IF('[1]2021_Base RPA'!$F382="","",'[1]2021_Base RPA'!$F382) -> 9037.5 | G25: 30 | H25: =IF('[1]2021_Base RPA'!$F405="","",'[1]2021_Base RPA'!$F405) -> 8539 | I25: 31 | J25: =IF('[1]2021_Base RPA'!$F424="","",'[1]2021_Base RPA'!$F424) -> 8017 | K25: 30 | L25: =IF('[1]2021_Base RPA'!$F446="","",'[1]2021_Base RPA'!$F446) -> 8210 | O25: 41913 | P25: 6739.1957 | Q25: -0.019357861 | R25: 16515.747 | S25: 0.029233272 | T25: -0.023377518
E26: 31 | F26: =IF('[1]2021_Base RPA'!$F383="","",'[1]2021_Base RPA'!$F383) -> 8933 | L26: =IF('[1]2021_Base RPA'!$F447="","",'[1]2021_Base RPA'!$F447) -> 8355
O27: 41944 | P27: 6701.135 | Q27: -0.005647655 | R27: 17154.906 | S27: 0.038699965 | T27: 0.014417737
A28: =B29/'2022'!L65-1 -> 0.071306682 | C28: =D29/B29-1 -> -0.0042790971 | E28: =F29/D29-1 -> -0.011847651 | G28: =H29/F29-1 -> -0.0045161674 | I28: =J29/H29-1 -> -0.062563391 | K28: =L29/J29-1 -> 0.016972157 | O28: 41974 | P28: 6422.9524 | Q28: -0.041512762 | R28: 16968.798 | S28: -0.010848658 | T28: 0.0034126658
A29: MM | B29: =AVERAGE(B4:B25) -> 8979.9762 | C29: MM | D29: =AVERAGE(D4:D24) -> 8941.55 | E29: MM | F29: =AVERAGE(F4:F26) -> 8835.6136 | G29: MM | H29: =AVERAGE(H4:H24) -> 8795.7105 | I29: MM | J29: =AVERAGE(J4:J24) -> 8245.4211 | K29: MM | L29: =AVERAGE(L4:L25) -> 8385.3636 | O29: 42005 | P29: 5791.175 | Q29: -0.098362458 | R29: 15271.908 | S29: -0.10000062 | T29: -0.10000062
A30: MM R$ | B30: =B29*A31 -> 46731.896 | C30: MM R$ | D30: =D29*C31 -> 46138.398 | E30: MM R$ | F30: =F29*E31 -> 46025.326 | G30: MM R$ | H30: =H29*G31 -> 44156.692 | I30: MM R$ | J30: =J29*I31 -> 41032.678 | K30: MM R$ | L30: =L29*K31 -> 40677.119 | O30: 42036 | P30: 5702.075 | Q30: -0.015385479 | R30: 16059.837 | S30: 0.051593399 | T30: -0.053566592
A31: =AVERAGE('[1]2021_Base RPA'!$B$323:$B$340) -> 5.2040111 | B31: =A31/'2022'!K68-1 -> -0.009130971 | C31: 5.16 | D31: =D30/B30-1 -> -0.01270006 | E31: =AVERAGE('[1]2021_Base RPA'!$B$361:$B$383) -> 5.2090696 | F31: =F30/D30-1 -> -0.0024507118 | G31: =AVERAGE('[1]2021_Base RPA'!$B$384:$B$402) -> 5.0202529 | H31: =H30/F30-1 -> -0.040600135 | I31: =AVERAGE('[1]2021_Base RPA'!$B$405:$B$424) -> 4.97642 | J31: =J30/H30-1 -> -0.070748357 | K31: =AVERAGE('[1]2021_Base RPA'!$B$425:$B$446) -> 4.8509667 | L31: =L30/J30-1 -> -0.0086652581 | O31: 42064 | P31: 5919.9048 | Q31: 0.038201841 | R31: 18601.525 | S31: 0.15826359 | T31: 0.096219358
A32: Cobre LME Prices 2021 US$/Ton | O32: MÉDIAS
A33: Julho 2023 | C33: Agosto 2023 | E33: Setembro 2023 | G33: Outubro 2023 | I33: Novembro 2023 | K33: Dezembro 2023 | O33: 42125 | P33: 6300.6053 | Q33: 0.04514038 | R33: 19242.048 | S33: 0.045653962 | T33: 0.13396651
B34: Cash | D34: Cash | F34: Cash | H34: Cash | J34: Cash | L34: Cash | O34: 42156 | P34: 5833.6136 | Q34: -0.074118534 | R34: 18168.79 | S34: -0.055776744 | T34: 0.070717548
A35: Média | B35: #DIV/0! | C35: Média | D35: #DIV/0! | E35: Média | F35: #DIV/0! | G35: Média | H35: #DIV/0! | I35: Média | J35: #DIV/0! | K35: Média | L35: #DIV/0! | O35: 42675 | T35: #DIV/0!
A36: MM | B36: #DIV/0! | C36: MM | D36: #DIV/0! | E36: MM | F36: #DIV/0! | G36: MM | H36: #DIV/0! | I36: MM | J36: #DIV/0! | K36: MM | L36: #DIV/0! | O36: 42705 | T36: #DIV/0!
A37: #DIV/0! | C37: #DIV/0! | E37: #DIV/0! | G37: #DIV/0! | I37: #DIV/0! | K37: #DIV/0! | O37: 42736 | T37: #DIV/0!
A38: MM R$ | B38: #DIV/0! | C38: MM R$ | D38: #DIV/0! | E38: MM R$ | F38: #DIV/0! | G38: MM R$ | H38: #DIV/0! | I38: MM R$ | J38: #DIV/0! | K38: MM R$ | L38: #DIV/0! | O38: 42767 | T38: #DIV/0!
B39: #DIV/0! | D39: #DIV/0! | F39: #DIV/0! | H39: #DIV/0! | J39: #DIV/0! | L39: #DIV/0! | O39: 42795 | T39: #DIV/0!
A40: Julho 2016 | C40: Agosto 2016 | E40: Setembro 2016 | G40: Outubro 2016 | I40: Novembro 2016 | K40: Dezembro 2016 | O40: 42826 | T40: #DIV/0!
B41: Cash | D41: Cash | F41: Cash | H41: Cash | J41: Cash | L41: Cash | O41: 42856 | T41: #DIV/0!
A42: 3 | B42: =IF('[1]2021_Base RPA'!$F447="","",'[1]2021_Base RPA'!$F447) -> 8355 | C42: 1 | D42: =IF('[1]2021_Base RPA'!$F468="","",'[1]2021_Base RPA'!$F468) -> 8720.5 | E42: 1 | F42: =IF('[1]2021_Base RPA'!$F491="","",'[1]2021_Base RPA'!$F491) -> 8515 | G42: 2 | H42: =IF('[1]2021_Base RPA'!$F512="","",'[1]2021_Base RPA'!$F512) -> 8100 | I42: 1 | J42: =IF('[2]2021_Base RPA'!$F534="","",'[2]2021_Base RPA'!$F534) -> 8041 | K42: 1 | L42: =IF('[2]2021_Base RPA'!$F534="","",'[2]2021_Base RPA'!$F556) -> 8456 | O42: =#REF! -> #REF! | P42: =#REF! -> #REF! | Q42: =#REF! -> #REF! | R42: =#REF! -> #REF! | S42: =#REF! -> #REF! | T42: =#REF! -> #REF!
A43: 4 | B43: =IF('[1]2021_Base RPA'!$F448="","",'[1]2021_Base RPA'!$F448) -> 8349 | C43: 2 | D43: =IF('[1]2021_Base RPA'!$F469="","",'[1]2021_Base RPA'!$F469) -> 8545 | E43: 4 | F43: =IF('[1]2021_Base RPA'!$F492="","",'[1]2021_Base RPA'!$F492) -> 8405 | G43: 3 | H43: =IF('[1]2021_Base RPA'!$F513="","",'[1]2021_Base RPA'!$F513) -> 7958 | I43: 2 | J43: =IF('[2]2021_Base RPA'!$F535="","",'[2]2021_Base RPA'!$F535) -> 8066 | K43: 4 | L43: =IF('[2]2021_Base RPA'!$F535="","",'[2]2021_Base RPA'!$F557) -> 8417 | O43: =#REF! -> #REF! | P43: =#REF! -> #REF! | Q43: =#REF! -> #REF! | R43: =#REF! -> #REF! | S43: =#REF! -> #REF! | T43: =#REF! -> #REF! | U43: =261+21 -> 282
A44: 5 | B44: =IF('[1]2021_Base RPA'!$F449="","",'[1]2021_Base RPA'!$F449) -> 8251 | C44: 3 | D44: =IF('[1]2021_Base RPA'!$F470="","",'[1]2021_Base RPA'!$F470) -> 8472 | E44: 5 | F44: =IF('[1]2021_Base RPA'!$F493="","",'[1]2021_Base RPA'!$F493) -> 8425 | G44: 4 | H44: =IF('[1]2021_Base RPA'!$F514="","",'[1]2021_Base RPA'!$F514) -> 7910 | I44: 3 | J44: =IF('[2]2021_Base RPA'!$F536="","",'[2]2021_Base RPA'!$F536) -> 8070.5 | K44: 5 | L44: =IF('[2]2021_Base RPA'!$F536="","",'[2]2021_Base RPA'!$F558) -> 8259 | O44: =#REF! -> #REF! | P44: =#REF! -> #REF! | Q44: =#REF! -> #REF! | R44: =#REF! -> #REF! | S44: =#REF! -> #REF! | T44: =#REF! -> #REF!
A45: 6 | B45: =IF('[1]2021_Base RPA'!$F450="","",'[1]2021_Base RPA'!$F450) -> 8280 | C45: 4 | D45: =IF('[1]2021_Base RPA'!$F471="","",'[1]2021_Base RPA'!$F471) -> 8450.5 | E45: 6 | F45: =IF('[1]2021_Base RPA'!$F494="","",'[1]2021_Base RPA'!$F494) -> 8394 | G45: 5 | H45: =IF('[1]2021_Base RPA'!$F515="","",'[1]2021_Base RPA'!$F515) -> 7812 | I45: 6 | J45: =IF('[2]2021_Base RPA'!$F537="","",'[2]2021_Base RPA'!$F537) -> 8136.5 | K45: 6 | L45: =IF('[2]2021_Base RPA'!$F537="","",'[2]2021_Base RPA'!$F559) -> 8297 | O45: =#REF! -> #REF! | P45: =#REF! -> #REF! | Q45: =#REF! -> #REF! | R45: =#REF! -> #REF! | S45: =#REF! -> #REF! | T45: =#REF! -> #REF!
A46: 7 | B46: =IF('[1]2021_Base RPA'!$F451="","",'[1]2021_Base RPA'!$F451) -> 8299 | C46: 7 | D46: =IF('[1]2021_Base RPA'!$F472="","",'[1]2021_Base RPA'!$F472) -> 8495 | E46: 8 | F46: =IF('[1]2021_Base RPA'!$F495="","",'[1]2021_Base RPA'!$F495) -> 8242 | G46: 6 | H46: =IF('[1]2021_Base RPA'!$F516="","",'[1]2021_Base RPA'!$F516) -> 7886 | I46: 7 | J46: =IF('[2]2021_Base RPA'!$F538="","",'[2]2021_Base RPA'!$F538) -> 8068 | K46: 7 | L46: =IF('[2]2021_Base RPA'!$F538="","",'[2]2021_Base RPA'!$F560) -> 8221 | O46: =#REF! -> #REF! | P46: =#REF! -> #REF! | Q46: =#REF! -> #REF! | R46: =#REF! -> #REF! | S46: =#REF! -> #REF! | T46: =#REF! -> #REF!
A47: 10 | B47: =IF('[1]2021_Base RPA'!$F452="","",'[1]2021_Base RPA'!$F452) -> 8286 | C47: 8 | D47: =IF('[1]2021_Base RPA'!$F473="","",'[1]2021_Base RPA'!$F473) -> 8276 | E47: 11 | F47: =IF('[1]2021_Base RPA'!$F497="","",'[1]2021_Base RPA'!$F497) -> 8332 | G47: 9 | H47: =IF('[1]2021_Base RPA'!$F517="","",'[1]2021_Base RPA'!$F517) -> 8015 | I47: 8 | J47: =IF('[2]2021_Base RPA'!$F539="","",'[2]2021_Base RPA'!$F539) -> 8088 | K47: 8 | L47: =IF('[2]2021_Base RPA'!$F539="","",'[2]2021_Base RPA'!$F561) -> 8348 | O47: =#REF! -> #REF! | P47: =#REF! -> #REF! | Q47: =#REF! -> #REF! | R47: =#REF! -> #REF! | S47: =#REF! -> #REF! | T47: =#REF! -> #REF!
A48: 11 | B48: =IF('[1]2021_Base RPA'!$F453="","",'[1]2021_Base RPA'!$F453) -> 8371 | C48: 9 | D48: =IF('[1]2021_Base RPA'!$F474="","",'[1]2021_Base RPA'!$F474) -> 8395 | E48: 12 | F48: =IF('[1]2021_Base RPA'!$F498="","",'[1]2021_Base RPA'!$F498) -> 8337 | G48: 10 | H48: =IF('[1]2021_Base RPA'!$F518="","",'[1]2021_Base RPA'!$F518) -> 7907 | I48: 9 | J48: =IF('[2]2021_Base RPA'!$F540="","",'[2]2021_Base RPA'!$F540) -> 8030.5 | K48: 11 | L48: =IF('[2]2021_Base RPA'!$F540="","",'[2]2021_Base RPA'!$F562) -> 8275.5 | O48: =#REF! -> #REF! | P48: =#REF! -> #REF! | Q48: =#REF! -> #REF! | R48: =#REF! -> #REF! | S48: =#REF! -> #REF! | T48: =#REF! -> #REF!
A49: 12 | B49: =IF('[1]2021_Base RPA'!$F454="","",'[1]2021_Base RPA'!$F454) -> 8367 | C49: 10 | D49: =IF('[1]2021_Base RPA'!$F475="","",'[1]2021_Base RPA'!$F475) -> 8423.5 | E49: 13 | F49: =IF('[1]2021_Base RPA'!$F499="","",'[1]2021_Base RPA'!$F499) -> 8352.5 | G49: 11 | H49: =IF('[1]2021_Base RPA'!$F519="","",'[1]2021_Base RPA'!$F519) -> 7943 | I49: 10 | J49: =IF('[2]2021_Base RPA'!$F541="","",'[2]2021_Base RPA'!$F541) -> 8006 | K49: 12 | L49: =IF('[2]2021_Base RPA'!$F541="","",'[2]2021_Base RPA'!$F563) -> 8272 | O49: =#REF! -> #REF! | P49: =#REF! -> #REF! | Q49: =#REF! -> #REF! | R49: =#REF! -> #REF! | S49: =#REF! -> #REF! | T49: =#REF! -> #REF!
A50: 13 | B50: =IF('[1]2021_Base RPA'!$F455="","",'[1]2021_Base RPA'!$F455) -> 8585 | C50: 11 | D50: =IF('[1]2021_Base RPA'!$F476="","",'[1]2021_Base RPA'!$F476) -> 8242 | E50: 14 | F50: =IF('[1]2021_Base RPA'!$F500="","",'[1]2021_Base RPA'!$F500) -> 8422 | G50: 12 | H50: =IF('[1]2021_Base RPA'!$F520="","",'[1]2021_Base RPA'!$F520) -> 7994 | I50: 13 | J50: =IF('[2]2021_Base RPA'!$F542="","",'[2]2021_Base RPA'!$F542) -> 8014.5 | K50: 13 | L50: =IF('[2]2021_Base RPA'!$F542="","",'[2]2021_Base RPA'!$F564) -> 8205 | O50: =#REF! -> #REF! | P50: =#REF! -> #REF! | Q50: =#REF! -> #REF! | R50: =#REF! -> #REF! | S50: =#REF! -> #REF! | T50: =#REF! -> #REF!
A51: 14 | B51: =IF('[1]2021_Base RPA'!$F456="","",'[1]2021_Base RPA'!$F456) -> 8651 | C51: 14 | D51: =IF('[1]2021_Base RPA'!$F477="","",'[1]2021_Base RPA'!$F477) -> 8242 | E51: 15 | F51: =IF('[1]2021_Base RPA'!$F501="","",'[1]2021_Base RPA'!$F501) -> 8376 | G51: 13 | H51: =IF('[1]2021_Base RPA'!$F521="","",'[1]2021_Base RPA'!$F521) -> 7891 | I51: 14 | J51: =IF('[2]2021_Base RPA'!$F543="","",'[2]2021_Base RPA'!$F543) -> 8081 | K51: 14 | L51: =IF('[2]2021_Base RPA'!$F543="","",'[2]2021_Base RPA'!$F565) -> 8461.5 | O51: =#REF! -> #REF! | P51: =#REF! -> #REF! | Q51: =#REF! -> #REF! | R51: =#REF! -> #REF! | S51: =#REF! -> #REF! | T51: =#REF! -> #REF!
A52: 17 | B52: =IF('[1]2021_Base RPA'!$F457="","",'[1]2021_Base RPA'!$F457) -> 8460 | C52: 15 | D52: =IF('[1]2021_Base RPA'!$F478="","",'[1]2021_Base RPA'!$F478) -> 8126.5 | E52: 18 | F52: =IF('[1]2021_Base RPA'!$F502="","",'[1]2021_Base RPA'!$F502) -> 8319 | G52: 16 | H52: =IF('[1]2021_Base RPA'!$F522="","",'[1]2021_Base RPA'!$F522) -> 7920 | I52: 15 | J52: =IF('[2]2021_Base RPA'!$F544="","",'[2]2021_Base RPA'!$F544) -> 8169 | K52: 15 | L52: =IF('[2]2021_Base RPA'!$F544="","",'[2]2021_Base RPA'!$F566) -> 8471 | O52: =#REF! -> #REF! | P52: =#REF! -> #REF! | Q52: =#REF! -> #REF! | R52: =#REF! -> #REF! | S52: =#REF! -> #REF! | T52: =#REF! -> #REF!
A53: 18 | B53: =IF('[1]2021_Base RPA'!$F458="","",'[1]2021_Base RPA'!$F458) -> 8410 | C53: 16 | D53: =IF('[1]2021_Base RPA'!$F479="","",'[1]2021_Base RPA'!$F479) -> 8132 | E53: 19 | F53: =IF('[1]2021_Base RPA'!$F503="","",'[1]2021_Base RPA'!$F503) -> 8232.5 | G53: 17 | H53: =IF('[1]2021_Base RPA'!$F523="","",'[1]2021_Base RPA'!$F523) -> 7846.5 | I53: 16 | J53: =IF('[2]2021_Base RPA'!$F545="","",'[2]2021_Base RPA'!$F545) -> 8165.5 | K53: 18 | L53: =IF('[2]2021_Base RPA'!$F545="","",'[2]2021_Base RPA'!$F567) -> 8423 | O53: =#REF! -> #REF! | P53: =#REF! -> #REF! | Q53: =#REF! -> #REF! | R53: =#REF! -> #REF! | S53: =#REF! -> #REF! | T53: =#REF! -> #REF!
A54: 19 | B54: =IF('[1]2021_Base RPA'!$F459="","",'[1]2021_Base RPA'!$F459) -> 8354 | C54: 17 | D54: =IF('[1]2021_Base RPA'!$F480="","",'[1]2021_Base RPA'!$F480) -> 8215 | E54: 20 | F54: =IF('[1]2021_Base RPA'!$F504="","",'[1]2021_Base RPA'!$F504) -> 8275 | G54: 18 | H54: =IF('[1]2021_Base RPA'!$F524="","",'[1]2021_Base RPA'!$F524) -> 7947.5 | I54: 17 | J54: =IF('[2]2021_Base RPA'!$F546="","",'[2]2021_Base RPA'!$F546) -> 8141 | K54: 19 | L54: =IF('[2]2021_Base RPA'!$F546="","",'[2]2021_Base RPA'!$F568) -> 8439 | O54: =#REF! -> #REF! | P54: =#REF! -> #REF! | Q54: =#REF! -> #REF! | R54: =#REF! -> #REF! | S54: =#REF! -> #REF! | T54: =#REF! -> #REF!
A55: 20 | B55: =IF('[1]2021_Base RPA'!$F460="","",'[1]2021_Base RPA'!$F460) -> 8543 | C55: 18 | D55: =IF('[1]2021_Base RPA'!$F481="","",'[1]2021_Base RPA'!$F481) -> 8176 | E55: 21 | F55: =IF('[1]2021_Base RPA'!$F505="","",'[1]2021_Base RPA'!$F505) -> 8100.5 | G55: 19 | H55: =IF('[1]2021_Base RPA'!$F525="","",'[1]2021_Base RPA'!$F525) -> 7938 | I55: 20 | J55: =IF('[2]2021_Base RPA'!$F547="","",'[2]2021_Base RPA'!$F547) -> 8247 | K55: 20 | L55: =IF('[2]2021_Base RPA'!$F547="","",'[2]2021_Base RPA'!$F569) -> 8466.5 | O55: =#REF! -> #REF! | P55: =#REF! -> #REF! | Q55: =#REF! -> #REF! | R55: =#REF! -> #REF! | S55: =#REF! -> #REF! | T55: =#REF! -> #REF!
A56: 21 | B56: =IF('[1]2021_Base RPA'!$F461="","",'[1]2021_Base RPA'!$F461) -> 8422 | C56: 21 | D56: =IF('[1]2021_Base RPA'!$F482="","",'[1]2021_Base RPA'!$F482) -> 8239.5 | E56: 22 | F56: =IF('[1]2021_Base RPA'!$F506="","",'[1]2021_Base RPA'!$F506) -> 8187.5 | G56: 20 | H56: =IF('[1]2021_Base RPA'!$F526="","",'[1]2021_Base RPA'!$F526) -> 7876 | I56: 21 | J56: =IF('[2]2021_Base RPA'!$F548="","",'[2]2021_Base RPA'!$F548) -> 8324 | K56: 21 | L56: =IF('[2]2021_Base RPA'!$F548="","",'[2]2021_Base RPA'!$F570) -> 8460 | O56: =#REF! -> #REF! | P56: =#REF! -> #REF! | Q56: =#REF! -> #REF! | R56: =#REF! -> #REF! | S56: =#REF! -> #REF! | T56: =#REF! -> #REF!
A57: 24 | B57: =IF('[1]2021_Base RPA'!$F462="","",'[1]2021_Base RPA'!$F462) -> 8430 | C57: 22 | D57: =IF('[1]2021_Base RPA'!$F483="","",'[1]2021_Base RPA'!$F483) -> 8342 | E57: 25 | F57: =IF('[1]2021_Base RPA'!$F507="","",'[1]2021_Base RPA'!$F507) -> 8102 | G57: 23 | H57: =IF('[1]2021_Base RPA'!$F527="","",'[1]2021_Base RPA'!$F527) -> 7824.5 | I57: 22 | J57: =IF('[2]2021_Base RPA'!$F549="","",'[2]2021_Base RPA'!$F549) -> 8296 | K57: 22 | L57: =IF('[2]2021_Base RPA'!$F549="","",'[2]2021_Base RPA'!$F571) -> 8499 | O57: =#REF! -> #REF! | P57: =#REF! -> #REF! | Q57: =#REF! -> #REF! | R57: =#REF! -> #REF! | S57: =#REF! -> #REF! | T57: =#REF! -> #REF!
A58: 25 | B58: =IF('[1]2021_Base RPA'!$F462="","",'[1]2021_Base RPA'!$F463) -> 8597 | C58: 23 | D58: =IF('[1]2021_Base RPA'!$F484="","",'[1]2021_Base RPA'!$F484) -> 8377.5 | E58: 26 | F58: =IF('[1]2021_Base RPA'!$F508="","",'[1]2021_Base RPA'!$F508) -> 8065 | G58: 24 | H58: =IF('[1]2021_Base RPA'!$F528="","",'[1]2021_Base RPA'!$F528) -> 7900.5 | I58: 23 | J58: =IF('[2]2021_Base RPA'!$F550="","",'[2]2021_Base RPA'!$F550) -> 8307.5 | K58: 27 | L58: =IF('[2]2021_Base RPA'!$F550="","",'[2]2021_Base RPA'!$F572) -> 8511.5 | O58: =#REF! -> #REF! | P58: =#REF! -> #REF! | Q58: =#REF! -> #REF! | R58: =#REF! -> #REF! | S58: =#REF! -> #REF! | T58: =#REF! -> #REF!
A59: 26 | B59: =IF('[1]2021_Base RPA'!$F463="","",'[1]2021_Base RPA'!$F464) -> 8534 | C59: 24 | D59: =IF('[1]2021_Base RPA'!$F485="","",'[1]2021_Base RPA'!$F485) -> 8358.5 | E59: 27 | F59: =IF('[1]2021_Base RPA'!$F509="","",'[1]2021_Base RPA'!$F509) -> 8016.5 | G59: 25 | H59: =IF('[1]2021_Base RPA'!$F529="","",'[1]2021_Base RPA'!$F529) -> 7946 | I59: 24 | J59: =IF('[2]2021_Base RPA'!$F551="","",'[2]2021_Base RPA'!$F551) -> 8300 | K59: 28 | L59: =IF('[2]2021_Base RPA'!$F551="","",'[2]2021_Base RPA'!$F573) -> 8530 | O59: =#REF! -> #REF! | P59: =#REF! -> #REF! | Q59: =#REF! -> #REF! | R59: =#REF! -> #REF! | S59: =#REF! -> #REF! | T59: =#REF! -> #REF!
A60: 27 | B60: =IF('[1]2021_Base RPA'!$F464="","",'[1]2021_Base RPA'!$F465) -> 8578.5 | C60: 25 | D60: =IF('[1]2021_Base RPA'!$F486="","",'[1]2021_Base RPA'!$F486) -> 8381.5 | E60: 28 | F60: =IF('[1]2021_Base RPA'!$F510="","",'[1]2021_Base RPA'!$F510) -> 8111.5 | G60: 26 | H60: =IF('[1]2021_Base RPA'!$F530="","",'[1]2021_Base RPA'!$F530) -> 7939 | I60: 27 | J60: =IF('[2]2021_Base RPA'!$F552="","",'[2]2021_Base RPA'!$F552) -> 8281 | K60: 29 | L60: =IF('[2]2021_Base RPA'!$F552="","",'[2]2021_Base RPA'!$F574) -> 8476 | O60: =#REF! -> #REF! | P60: =#REF! -> #REF! | Q60: =#REF! -> #REF! | R60: =#REF! -> #REF! | S60: =#REF! -> #REF! | T60: =#REF! -> #REF!
A61: 28 | B61: =IF('[1]2021_Base RPA'!$F465="","",'[1]2021_Base RPA'!$F466) -> 8592 | C61: 28 | D61: feriado | E61: 29 | F61: =IF('[1]2021_Base RPA'!$F511="","",'[1]2021_Base RPA'!$F511) -> 8230 | G61: 27 | H61: =IF('[1]2021_Base RPA'!$F531="","",'[1]2021_Base RPA'!$F531) -> 7963.5 | I61: 28 | J61: =IF('[2]2021_Base RPA'!$F553="","",'[2]2021_Base RPA'!$F553) -> 8278 | O61: =#REF! -> #REF! | P61: =#REF! -> #REF! | Q61: =#REF! -> #REF! | R61: =#REF! -> #REF! | S61: =#REF! -> #REF! | T61: =#REF! -> #REF!
A62: 31 | B62: =IF('[1]2021_Base RPA'!$F466="","",'[1]2021_Base RPA'!$F467) -> 8635.5 | C62: 29 | D62: =IF('[1]2021_Base RPA'!$F488="","",'[1]2021_Base RPA'!$F488) -> 8375 | G62: 30 | H62: =IF('[1]2021_Base RPA'!$F532="","",'[1]2021_Base RPA'!$F532) -> 8110 | I62: 29 | J62: =IF('[2]2021_Base RPA'!$F554="","",'[2]2021_Base RPA'!$F554) -> 8384 | O62: =#REF! -> #REF! | P62: =#REF! -> #REF! | Q62: =#REF! -> #REF! | R62: =#REF! -> #REF! | S62: =#REF! -> #REF! | T62: =#REF! -> #REF!
C63: 30 | D63: =IF('[1]2021_Base RPA'!$F489="","",'[1]2021_Base RPA'!$F489) -> 8394.5 | G63: 31 | H63: =IF('[1]2021_Base RPA'!$F533="","",'[1]2021_Base RPA'!$F533) -> 8038 | I63: 30 | J63: =IF('[2]2021_Base RPA'!$F555="","",'[2]2021_Base RPA'!$F555) -> 8332 | O63: =#REF! -> #REF! | P63: =#REF! -> #REF! | Q63: =#REF! -> #REF! | R63: =#REF! -> #REF! | S63: =#REF! -> #REF! | T63: =#REF! -> #REF!
C64: 31 | D64: =IF('[1]2021_Base RPA'!$F490="","",'[1]2021_Base RPA'!$F490) -> 8359.5 | O64: =#REF! -> #REF! | P64: =#REF! -> #REF! | Q64: =#REF! -> #REF! | R64: =#REF! -> #REF! | S64: =#REF! -> #REF! | T64: =#REF! -> #REF!
A65: =B66/L29-1 -> 0.0071403533 | C65: =D66/B66-1 -> -0.011067227 | E65: =F66/D66-1 -> -0.0095515922 | G65: =H66/F66-1 -> -0.040215074 | I65: =J66/H66-1 -> 0.02955077 | K65: =L66/J66-1 -> 0.026933196 | O65: =#REF! -> #REF! | P65: =#REF! -> #REF! | Q65: =#REF! -> #REF! | R65: =#REF! -> #REF! | S65: =#REF! -> #REF! | T65: =#REF! -> #REF!
A66: MM | B66: =AVERAGE(B42:B62) -> 8445.2381 | C66: MM | D66: =AVERAGE(D42:D64) -> 8351.7727 | E66: MM | F66: =AVERAGE(F42:F61) -> 8272 | G66: MM | H66: =AVERAGE(H42:H63) -> 7939.3409 | I66: MM | J66: =AVERAGE(J42:J63) -> 8173.9545 | K66: MM | L66: =AVERAGE(L42:L60) -> 8394.1053 | O66: =#REF! -> #REF! | P66: =#REF! -> #REF! | Q66: =#REF! -> #REF! | R66: =#REF! -> #REF! | S66: =#REF! -> #REF! | T66: =#REF! -> #REF!
A68: MM R$ | B68: =B66*A69 -> 40564.168 | C68: MM R$ | D68: =D66*C69 -> 40948.27 | E68: MM R$ | F68: =F66*E69 -> 40833.818 | G68: MM R$ | H68: =H66*G69 -> 40207.681 | I68: MM R$ | J68: =J66*I69 -> 40045.578 | K68: MM R$ | L68: =L66*K69 -> 41102.936
A69: =AVERAGE('[2]2021_Base RPA'!$B$447:$B$466) -> 4.8032 | B69: =B68/L30-1 -> -0.0027767912 | C69: =AVERAGE('[2]2021_Base RPA'!$B$468:$B$490) -> 4.9029435 | D69: =D68/B68-1 -> 0.0094689976 | E69: =AVERAGE('[2]2021_Base RPA'!$B$491:$B$511) -> 4.93639 | F69: =F68/D68-1 -> -0.0027950276 | G69: =AVERAGE('[2]2021_Base RPA'!B$512:B$533) -> 5.06436 | H69: =H68/F68-1 -> -0.015333799 | I69: =AVERAGE('[2]2021_Base RPA'!$B$534:$B$557) -> 4.8991682 | J69: =J68/H68-1 -> -0.0040316302 | K69: =AVERAGE('[2]2021_Base RPA'!$B$556:$B$576) -> 4.8966429 | L69: =L68/J68-1 -> 0.026403853 | M69: ='[2]2021_Base RPA'!$Q$535 -> 0
E72: VARIAÇÃO COBRE LME - REAIS

Sheet 2024
A1: Cobre LME Prices 2021 US$/Ton | O1: MÉDIAS
A2: Janeiro 2024 | C2: Fevereiro 2024 | E2: Março 2024 | G2: Abril 2024 | I2: Maio 2024 | K2: Junho 2024 | P2: US$ | Q2: Var (%) | R2: R$ | S2: Var Mês (%) | T2: Acumulado/Ano
B3: Cash | D3: Cash | F3: Cash | H3: Cash | J3: Cash | L3: Cash | O3: 41275 | P3: 8049.2455 | Q3: 0.010884092 | R3: 16364.921 | S3: -0.010958324
A4: 2 | B4: =IF('[2]2021_Base RPA'!$F575="","",'[2]2021_Base RPA'!$F575) -> 8430 | C4: 1 | D4: =IF('[2]2021_Base RPA'!$F597="","",'[2]2021_Base RPA'!$F597) -> 8437 | E4: 1 | F4: =IF('[2]2021_Base RPA'!$F618="","",'[2]2021_Base RPA'!$F618) -> 8394 | G4: 1 | H4: =IF('[2]2021_Base RPA'!$F639="","",'[2]2021_Base RPA'!$F639) -> Feriado | I4: 1 | J4: =IF('[2]2021_Base RPA'!$F661="","",'[2]2021_Base RPA'!$F661) -> 9790 | K4: 3 | L4: =IF('[2]2021_Base RPA'!$F684="","",'[2]2021_Base RPA'!$F684) -> 9885.5
A5: 3 | B5: =IF('[2]2021_Base RPA'!$F576="","",'[2]2021_Base RPA'!$F576) -> 8381 | C5: 2 | D5: =IF('[2]2021_Base RPA'!$F598="","",'[2]2021_Base RPA'!$F598) -> 8400 | E5: 4 | F5: =IF('[2]2021_Base RPA'!$F619="","",'[2]2021_Base RPA'!$F619) -> 8437 | G5: 2 | H5: =IF('[2]2021_Base RPA'!$F640="","",'[2]2021_Base RPA'!$F640) -> 8920 | I5: 2 | J5: =IF('[2]2021_Base RPA'!$F662="","",'[2]2021_Base RPA'!$F662) -> 9655 | K5: 4 | L5: =IF('[2]2021_Base RPA'!$F685="","",'[2]2021_Base RPA'!$F685) -> 9858.5 | O5: 41306 | P5: 8070.475 | Q5: 0.0026374578 | R5: 15912.556 | S5: -0.027642381
A6: 4 | B6: =IF('[2]2021_Base RPA'!$F577="","",'[2]2021_Base RPA'!$F577) -> 8375 | C6: 5 | D6: =IF('[2]2021_Base RPA'!$F599="","",'[2]2021_Base RPA'!$F599) -> 8329 | E6: 5 | F6: =IF('[2]2021_Base RPA'!$F620="","",'[2]2021_Base RPA'!$F620) -> 8429.5 | G6: 3 | H6: =IF('[2]2021_Base RPA'!$F641="","",'[2]2021_Base RPA'!$F641) -> 8930 | I6: 3 | J6: =IF('[2]2021_Base RPA'!$F663="","",'[2]2021_Base RPA'!$F663) -> 9736 | K6: 5 | L6: =IF('[2]2021_Base RPA'!$F686="","",'[2]2021_Base RPA'!$F686) -> 9769 | O6: 41334 | P6: 7662.4 | Q6: -0.050563938 | R6: 15212.929 | S6: -0.043966954
A7: 5 | B7: =IF('[2]2021_Base RPA'!$F578="","",'[2]2021_Base RPA'!$F578) -> 8346.5 | C7: 6 | D7: =IF('[2]2021_Base RPA'!$F600="","",'[2]2021_Base RPA'!$F600) -> 8280 | E7: 6 | F7: =IF('[2]2021_Base RPA'!$F621="","",'[2]2021_Base RPA'!$F621) -> 8441 | G7: 4 | H7: =IF('[2]2021_Base RPA'!$F642="","",'[2]2021_Base RPA'!$F642) -> 9256 | I7: 6 | J7: =IF('[2]2021_Base RPA'!$F664="","",'[2]2021_Base RPA'!$F664) -> FERIADO | K7: 6 | L7: =IF('[2]2021_Base RPA'!$F687="","",'[2]2021_Base RPA'!$F687) -> 9930 | O7: 41365 | P7: 7203.3571 | Q7: -0.059908496 | R7: 14413.918 | S7: -0.052521859
A8: 8 | B8: =IF('[2]2021_Base RPA'!$F579="","",'[2]2021_Base RPA'!$F579) -> 8295 | C8: 8 | D8: =IF('[2]2021_Base RPA'!$F602="","",'[2]2021_Base RPA'!$F602) -> 8202 | E8: 7 | F8: =IF('[2]2021_Base RPA'!$F622="","",'[2]2021_Base RPA'!$F622) -> 8559 | G8: 5 | H8: =IF('[2]2021_Base RPA'!$F643="","",'[2]2021_Base RPA'!$F643) -> 9197 | I8: 7 | J8: =IF('[2]2021_Base RPA'!$F665="","",'[2]2021_Base RPA'!$F665) -> 9846 | K8: 7 | L8: =IF('[2]2021_Base RPA'!$F688="","",'[2]2021_Base RPA'!$F688) -> 9840 | O8: 41395 | P8: 7229.1429 | Q8: 0.0035796801 | R8: 14704.077 | S8: 0.020130469
A9: 9 | B9: =IF('[2]2021_Base RPA'!$F580="","",'[2]2021_Base RPA'!$F580) -> 8301.5 | C9: 9 | D9: =IF('[2]2021_Base RPA'!$F603="","",'[2]2021_Base RPA'!$F603) -> 8091.5 | E9: 8 | F9: =IF('[2]2021_Base RPA'!$F623="","",'[2]2021_Base RPA'!$F623) -> 8552.5 | G9: 8 | H9: =IF('[2]2021_Base RPA'!$F644="","",'[2]2021_Base RPA'!$F644) -> 9301 | I9: 8 | J9: =IF('[2]2021_Base RPA'!$F666="","",'[2]2021_Base RPA'!$F666) -> 9739.5 | K9: 10 | L9: =IF('[2]2021_Base RPA'!$F689="","",'[2]2021_Base RPA'!$F689) -> 9694.5 | O9: 41426 | P9: 7004.05 | Q9: -0.031136867 | R9: 15198.789 | S9: 0.033644542
A10: 10 | B10: =IF('[2]2021_Base RPA'!$F581="","",'[2]2021_Base RPA'!$F581) -> 8285 | C10: 13 | D10: =IF('[2]2021_Base RPA'!$F605="","",'[2]2021_Base RPA'!$F605) -> 8185 | E10: 11 | F10: =IF('[2]2021_Base RPA'!$F624="","",'[2]2021_Base RPA'!$F624) -> 8522 | G10: 9 | H10: =IF('[2]2021_Base RPA'!$F645="","",'[2]2021_Base RPA'!$F645) -> 9295.5 | I10: 9 | J10: =IF('[2]2021_Base RPA'!$F667="","",'[2]2021_Base RPA'!$F667) -> 9726 | K10: 11 | L10: =IF('[2]2021_Base RPA'!$F690="","",'[2]2021_Base RPA'!$F690) -> 9567 | O10: 41456 | P10: 6896.9773 | Q10: -0.015287259 | R10: 15536.683 | S10: 0.022231658
A11: 11 | B11: =IF('[2]2021_Base RPA'!$F582="","",'[2]2021_Base RPA'!$F582) -> 8332 | C11: 14 | D11: =IF('[2]2021_Base RPA'!$F606="","",'[2]2021_Base RPA'!$F606) -> 8133.5 | E11: 12 | F11: =IF('[2]2021_Base RPA'!$F625="","",'[2]2021_Base RPA'!$F625) -> 8566 | G11: 10 | H11: =IF('[2]2021_Base RPA'!$F646="","",'[2]2021_Base RPA'!$F646) -> 9360 | I11: 10 | J11: =IF('[2]2021_Base RPA'!$F668="","",'[2]2021_Base RPA'!$F668) -> 9941.5 | K11: 12 | L11: =IF('[2]2021_Base RPA'!$F691="","",'[2]2021_Base RPA'!$F691) -> 9697.5 | O11: 41487 | P11: 7182.2619 | Q11: 0.041363719 | R11: 16802.902 | S11: 0.081498669
A12: 12 | B12: =IF('[2]2021_Base RPA'!$F583="","",'[2]2021_Base RPA'!$F583) -> 8289 | C12: 15 | D12: =IF('[2]2021_Base RPA'!$F607="","",'[2]2021_Base RPA'!$F607) -> 8153 | E12: 13 | F12: =IF('[2]2021_Base RPA'!$F626="","",'[2]2021_Base RPA'!$F626) -> 8727 | G12: 11 | H12: =IF('[2]2021_Base RPA'!$F647="","",'[2]2021_Base RPA'!$F647) -> 9239.5 | I12: 13 | J12: =IF('[2]2021_Base RPA'!$F669="","",'[2]2021_Base RPA'!$F669) -> 10008.5 | K12: 13 | L12: =IF('[2]2021_Base RPA'!$F692="","",'[2]2021_Base RPA'!$F692) -> 9733 | O12: 41518 | P12: 7161.4286 | Q12: -0.0029006647 | R12: 16264.32 | S12: -0.032052874
A13: 15 | B13: =IF('[2]2021_Base RPA'!$F584="","",'[2]2021_Base RPA'!$F584) -> 8238.5 | C13: 16 | D13: =IF('[2]2021_Base RPA'!$F608="","",'[2]2021_Base RPA'!$F608) -> 8322 | E13: 14 | F13: =IF('[2]2021_Base RPA'!$F627="","",'[2]2021_Base RPA'!$F627) -> 8791.5 | G13: 12 | H13: =IF('[2]2021_Base RPA'!$F648="","",'[2]2021_Base RPA'!$F648) -> 9400 | I13: 14 | J13: =IF('[2]2021_Base RPA'!$F670="","",'[2]2021_Base RPA'!$F670) -> 10076 | K13: 14 | L13: =IF('[2]2021_Base RPA'!$F693="","",'[2]2021_Base RPA'!$F693) -> 9650 | O13: 41548 | P13: 7188.7826 | Q13: 0.0038196342 | R13: 15720.43 | S13: -0.033440722
A14: 16 | B14: =IF('[2]2021_Base RPA'!$F585="","",'[2]2021_Base RPA'!$F585) -> 8280 | C14: 19 | D14: =IF('[2]2021_Base RPA'!$F609="","",'[2]2021_Base RPA'!$F609) -> 8364.5 | E14: 15 | F14: =IF('[2]2021_Base RPA'!$F628="","",'[2]2021_Base RPA'!$F628) -> 8906.5 | G14: 15 | H14: =IF('[2]2021_Base RPA'!$F649="","",'[2]2021_Base RPA'!$F649) -> 9385 | I14: 15 | J14: =IF('[2]2021_Base RPA'!$F671="","",'[2]2021_Base RPA'!$F671) -> 10221 | K14: 17 | L14: =IF('[2]2021_Base RPA'!$F694="","",'[2]2021_Base RPA'!$F694) -> 9477 | O14: 41579 | P14: 7066.4048 | Q14: -0.017023445 | R14: 16235.772 | S14: 0.032781659
